Workbook

Sheet 00_README_Dashboard
A1: HPL AI Dispatching & Routing Engine - Simulated Data for Clustering & VRPTW
A3: Item | B3: Content | C3: Note
A4: Workbook | B4: HPL AI Dispatching & Routing Engine - Simulated Dataset for Clustering & VRPTW
A5: Purpose | B5: Bộ dữ liệu mô phỏng cho hàng phân phối, lập kế hoạch cuối ngày cho ngày hôm sau, chưa kích hoạt dynamic re-routing
A6: Scope | B6: 40 xe nội bộ, 3 kịch bản năng lực: thừa, đủ, thiếu; dữ liệu order có pickup/drop, time window, tải trọng, dung tích, cước, ràng buộc xe và rủi ro
A7: Algorithm-ready | B7: Sử dụng được cho phân cụm trước và VRPTW/PDPTW sau: tọa độ, time window dạng text và minute, demand pickup/delivery, service time, vehicle compatibility, revenue/penalty
A8: Key Logic | B8: Bám theo flow: Order Management → Validation → Clustering → VRPTW → Dispatch Board → Control Tower; tập trung pre-day planning
A9: Scenario S1 | B9: Năng lực công ty còn thừa so với order; giữ xe dự phòng và tối ưu chi phí/km rỗng
A10: Scenario S2 | B10: Năng lực công ty đáp ứng đủ; ưu tiên khóa kế hoạch và đảm bảo SLA
A11: Scenario S3 | B11: Năng lực công ty thiếu; kích hoạt thuê ngoài/chuyển tải/đàm phán khung giờ
A12: Scenario Capacity Summary
A13: Scenario_ID | B13: Case | C13: Orders | D13: Internal_Vehicles_Available | E13: Estimated_Route/Vehicle_Need | F13: Capacity_Gap | G13: Planning_Meaning | H13: Proposed_Operational_Response | I13: Algorithm_Settings | J13: Presentation_Note
A14: S1 | B14: Năng lực công ty còn thừa so với order khách hàng | C14: 30 | D14: 40 | E14: 28 | F14: 12 | G14: Có xe dự phòng, không cần thuê ngoài | H14: Ưu tiên phương án giảm km, giảm chạy rỗng, giữ 3-5 xe dự phòng cho phát sinh; chọn xe nhỏ cho nội đô và xe 5T/8T cho tuyến dài | I14: Balanced Mode + Empty-run Reduction | J14: Dùng để chứng minh hệ thống không chỉ tìm đường mà còn tối ưu năng lực dư
A15: S2 | B15: Năng lực công ty đáp ứng đủ so với order khách hàng | C15: 44 | D15: 40 | E15: 40 | F15: 0 | G15: Không còn nhiều xe dự phòng, cần khóa kế hoạch chặt | H15: Ưu tiên SLA và feasibility; giữ 1 danh sách xe backup/3PL standby nhưng chưa kích hoạt; dispatcher cần duyệt sớm và gửi tài xế trước 19:00 | I15: On-time Priority + Manual-assisted Mode | J15: Phù hợp case lập kế hoạch ngày hôm sau khi order vừa khớp năng lực
A16: S3 | B16: Năng lực công ty thiếu so với order khách hàng | C16: 60 | D16: 40 | E16: 52 | F16: -12 | G16: Thiếu xe nội bộ, phải thuê ngoài/chuyển tải/đàm phán giờ | H16: Kích hoạt 3PL/thuê ngoài cho tuyến dài và cụm low-margin; tách đơn quá tải nội đô; xin khách nới time window với đơn ưu tiên C; ưu tiên đơn SLA A và tuyến có lợi nhuận tốt | I16: Profit Maximization + On-time Priority + Split/Transshipment Enabled | J16: Dùng để trình bày năng lực xử lý thiếu xe và trade-off lead time/profit
A18: Quick Formula Checks
A19: Metric | B19: S1 | C19: S2 | D19: S3
A20: Orders count | B20: =COUNTA(S1_Thua_NangLuc!$C$2:$C$31) | C20: =COUNTA(S2_DapUng_Du!$C$2:$C$45) | D20: =COUNTA(S3_Thieu_NangLuc!$C$2:$C$61) | F20: Scenario check | G20: Meaning | H20: Action priority | I20: Use in deck
A21: Orders Ready | B21: =COUNTIF(S1_Thua_NangLuc!$BF$2:$BF$31,"Ready") | C21: =COUNTIF(S2_DapUng_Du!$BF$2:$BF$45,"Ready") | D21: =COUNTIF(S3_Thieu_NangLuc!$BF$2:$BF$61,"Ready") | F21: S1 | G21: Capacity surplus | H21: Cost/empty-run optimization | I21: Shows reserve capacity
A22: Orders Review | B22: =COUNTIF(S1_Thua_NangLuc!$BF$2:$BF$31,"Review") | C22: =COUNTIF(S2_DapUng_Du!$BF$2:$BF$45,"Review") | D22: =COUNTIF(S3_Thieu_NangLuc!$BF$2:$BF$61,"Review") | F22: S2 | G22: Capacity exact | H22: SLA lock + backup list | I22: Shows tight plan
A23: Total Revenue | B23: =SUM(S1_Thua_NangLuc!$AP$2:$AP$31) | C23: =SUM(S2_DapUng_Du!$AP$2:$AP$45) | D23: =SUM(S3_Thieu_NangLuc!$AP$2:$AP$61) | F23: S3 | G23: Capacity shortage | H23: 3PL/transshipment/reschedule | I23: Shows decision support
A24: Average Distance km | B24: =AVERAGE(S1_Thua_NangLuc!$W$2:$W$31) | C24: =AVERAGE(S2_DapUng_Du!$W$2:$W$45) | D24: =AVERAGE(S3_Thieu_NangLuc!$W$2:$W$61) | F24: All | G24: Pre-day planning only | H24: Dynamic event fields excluded from solver run | I24: Use nodes sheet for OR-Tools/VRPTW

Sheet 01_Data_Dictionary
A1: Sheet | B1: Field | C1: Definition / Use in Algorithm
A2: S1/S2/S3 Orders | B2: Scenario_ID | C2: Trường đơn hàng dùng cho validation, phân cụm và VRPTW
A3: S1/S2/S3 Orders | B3: Planning_Date | C3: Trường đơn hàng dùng cho validation, phân cụm và VRPTW
A4: S1/S2/S3 Orders | B4: Order_ID | C4: Trường đơn hàng dùng cho validation, phân cụm và VRPTW
A5: S1/S2/S3 Orders | B5: Customer_Group | C5: Trường đơn hàng dùng cho validation, phân cụm và VRPTW
A6: S1/S2/S3 Orders | B6: Customer_Name | C6: Trường đơn hàng dùng cho validation, phân cụm và VRPTW
A7: S1/S2/S3 Orders | B7: Channel | C7: Trường đơn hàng dùng cho validation, phân cụm và VRPTW
A8: S1/S2/S3 Orders | B8: SKU_Code | C8: Trường đơn hàng dùng cho validation, phân cụm và VRPTW
A9: S1/S2/S3 Orders | B9: Product_Group | C9: Trường đơn hàng dùng cho validation, phân cụm và VRPTW
A10: S1/S2/S3 Orders | B10: Pickup_ID | C10: Trường đơn hàng dùng cho validation, phân cụm và VRPTW
A11: S1/S2/S3 Orders | B11: Pickup_Name | C11: Trường đơn hàng dùng cho validation, phân cụm và VRPTW
A12: S1/S2/S3 Orders | B12: Pickup_Province | C12: Trường đơn hàng dùng cho validation, phân cụm và VRPTW
... A120: Algorithm_Nodes | B120: Notes | C120: Bảng node chuẩn hóa cho PDPTW/VRPTW: mỗi order có 1 pickup node và 1 delivery node

Sheet 02_Depots_Zones
A1: Location_ID | B1: Location_Name | C1: Type | D1: Province | E1: District | F1: Latitude | G1: Longitude | H1: Allowed_Vehicle_Types | I1: Operating_Start | J1: Operating_End | K1: Notes
A2: PK_HPL_LB | B2: HPL Depot Long Biên - 20 Thạch Bàn | C2: Depot | D2: Hà Nội | E2: Long Biên | F2: 21.026155 | G2: 105.91418 | H2: 5 tạ;1.25T;5T;8T;3 chân;4 chân | I2: 06:00 | J2: 20:00 | K2: Có thể làm điểm xuất phát/kết thúc cho tuyến
A3: PK_LINFOX_VSIP | B3: Kho Linfox KCN VSIP Bắc Ninh | C3: Customer Warehouse | D3: Bắc Ninh | E3: Từ Sơn | F3: 21.082707 | G3: 105.99795 | H3: 5 tạ;1.25T;5T;8T;3 chân;4 chân | I3: 06:00 | J3: 20:00 | K3: Có thể làm điểm xuất phát/kết thúc cho tuyến
A4: PK_HY_MYHAO | B4: Kho/Nhà máy khách hàng Mỹ Hào | C4: Customer Factory | D4: Hưng Yên | E4: Mỹ Hào | F4: 20.9329 | G4: 106.065 | H4: 5 tạ;1.25T;5T;8T;3 chân;4 chân | I4: 06:00 | J4: 20:00 | K4: Có thể làm điểm xuất phát/kết thúc cho tuyến
A5: PK_HP_DINHVU | B5: Kho Hải Phòng - Đình Vũ | C5: Port/Depot | D5: Hải Phòng | E5: Hải An | F5: 20.8425 | G5: 106.77 | H5: 5 tạ;1.25T;5T;8T;3 chân;4 chân | I5: 06:00 | J5: 20:00 | K5: Có thể làm điểm xuất phát/kết thúc cho tuyến
A6: PK_TH_QX | B6: Kho DC Thanh Hóa - Quảng Xương | C6: DC | D6: Thanh Hóa | E6: Quảng Xương | F6: 19.731 | G6: 105.815 | H6: 5 tạ;1.25T;5T;8T;3 chân;4 chân | I6: 06:00 | J6: 20:00 | K6: Có thể làm điểm xuất phát/kết thúc cho tuyến
A7: PK_NA_BACVINH | B7: Kho DC Vinh - KCN Bắc Vinh | C7: DC | D7: Nghệ An | E7: Vinh | F7: 18.733 | G7: 105.681 | H7: 5 tạ;1.25T;5T;8T;3 chân;4 chân | I7: 06:00 | J7: 20:00 | K7: Có thể làm điểm xuất phát/kết thúc cho tuyến
A9: Zone/Rules below
A10: Zone_ID | B10: Zone_Name | C10: Province/Coverage | D10: Rule_Type | E10: Vehicle_Limit | F10: Time_Window/Restriction | G10: Default_Service_Min | H10: Empty_Run_Rule | I10: Notes
A11: Z_HN_INNER | B11: Nội thành Hà Nội | C11: Hà Nội | D11: Road/Vehicle | E11: <=1.25T | F11: Cấm xe >1.25T giờ cao điểm 06:00-09:00 và 16:30-19:30 | G11: 25 | H11: <100km có thể chấp nhận rỗng | I11: Ưu tiên xe nhỏ, nhiều điểm, kiểm tra đường hẹp/dây điện thấp
A12: Z_HN_OUTER | B12: Ngoại thành Hà Nội | C12: Hoài Đức, Hà Đông, Long Biên | D12: Operational | E12: <=5T | F12: Tùy tuyến/kho | G12: 30 | H12: <100km có thể chấp nhận rỗng | I12: Có thể ghép đơn cùng trục
A13: Z_DB | B13: Đông Bắc | C13: Bắc Ninh, Hải Phòng, Quảng Ninh, Hải Dương | D13: Corridor | E13: <=8T/3 chân tùy điểm | F13: Theo khung giờ nhập kho | G13: 35 | H13: >100km cần tìm chuyến về | I13: Ưu tiên corridor matching và return load
A14: Z_TB | B14: Tây Bắc | C14: Thái Nguyên, Phú Thọ, Vĩnh Phúc | D14: Corridor | E14: <=8T | F14: Theo khách hàng | G14: 35 | H14: >100km cần tìm chuyến về | I14: Cần tránh nhảy trục Đông Bắc/Tây Bắc
A15: Z_BTB | B15: Bắc Trung Bộ | C15: Ninh Bình, Thanh Hóa, Nghệ An | D15: Corridor | E15: <=8T/3 chân | F15: Theo khách hàng | G15: 45 | H15: >100km bắt buộc cố gắng xin hàng kéo về | I15: Tuyến dài, cần kiểm tra backhaul

Sheet 03_Cost_Constraints
A1: Parameter | B1: Value | C1: Unit | D1: Business Meaning / Source in user-provided logic
A2: Planning_Date | B2: 2026-06-05 | C2: date | D2: Kế hoạch cuối ngày cho ngày hôm sau
A3: Diesel_Price | B3: 30020 | C3: VND/litre | D3: Giá dầu giả lập dùng cho tính chi phí nhiên liệu
A4: Default_Avg_Speed | B4: 50 | C4: km/h | D4: Dùng để tính Direct_Drive_Min nếu chưa có speed riêng
A5: Inner_City_Avg_Speed | B5: 35 | C5: km/h | D5: Nội thành Hà Nội, nhiều điểm và cấm tải
A6: Allowed_KM_Error | B6: 0.05 | C6: % | D6: Sai số km GPS/Vietmap/Bình Anh/Maxi khoảng 3-5%
A7: Empty_Run_Threshold | B7: 100 | C7: km | D7: <100km có thể chạy rỗng; >100km cần tìm chuyến quay đầu
A8: Target_Profit_Margin | B8: 0.1 | C8: % | D8: Mục tiêu tối thiểu theo meeting: lợi nhuận khoảng 10%
A9: Target_Improved_Margin | B9: 0.12 | C9: % | D9: Câu hỏi mục tiêu: cải thiện lên 12-15%
A10: Driver_Max_Continuous_Drive | B10: 4 | C10: hours | D10: Không lái liên tục quá 4h
A11: Driver_Max_Daily_Drive | B11: 10 | C11: hours | D11: Không quá 10h/ngày
A12: Clustering_Radius_Default | B12: 15 | C12: km | D12: Bán kính gom cụm demo
A13: Time_Compatibility_Window | B13: 120 | C13: minutes | D13: Khung giờ tương thích để gom cụm
A14: w1_GeoSim | B14: 0.25 | C14: weight | D14: Trọng số khoảng cách địa lý
... A20: w7_WaitingRisk | B20: 0.05 | C20: weight | D20: Điểm phạt rủi ro chờ

Sheet 04_Fleet_40
A1: Vehicle_ID | B1: Plate_No | C1: Vehicle_Type | D1: Vehicle_Class | E1: Max_Weight_kg | F1: Max_Volume_m3 | G1: Refrigerated | H1: Driver_ID | I1: Driver_Name | J1: Depot_ID | K1: Depot_Name | L1: Preferred_Corridor | M1: Shift_Start | N1: Shift_End | O1: Max_Driving_Hours_per_Day | P1: Max_Stops | Q1: Fuel_L_per_km | R1: Fuel_Cost_per_km | S1: EmptyRun_Cost_per_km | T1: Fixed_Cost_per_Day | U1: Driver_Cost_per_Trip | V1: Avg_Speed_kmph | W1: HN_Inner_Allowed | X1: Road_Access_Class | Y1: Status | Z1: Available_Date | AA1: Current_Lat | AB1: Current_Lon | AC1: GPS_Status | AD1: Notes
A2: V001 | B2: 30F-50137 | C2: 5 tạ | D2: Phân phối | E2: 500 | F2: 4 | G2: No | H2: DRV001 | I2: Tài xế 01 | J2: PK_LINFOX_VSIP | K2: Kho Linfox KCN VSIP Bắc Ninh | L2: Nội thành Hà Nội | M2: 06:00 | N2: 18:00 | O2: 10 | P2: 5 | Q2: 0.09 | R2: =Q2*'03_Cost_Constraints'!$B$3 | S2: =R2*1.15 | T2: 220000 | U2: 250000 | V2: 35 | W2: Yes | X2: Inner-city compatible | Y2: Available | Z2: 2026-06-05 | AA2: 21.082707 | AB2: 105.99795 | AC2: OK | AD2: Sẵn sàng lập kế hoạch ngày hôm sau
A3: V002 | B3: 31F-50274 | C3: 5 tạ | D3: Phân phối | E3: 500 | F3: 4 | G3: No | H3: DRV002 | I3: Tài xế 02 | J3: PK_HY_MYHAO | K3: Kho/Nhà máy khách hàng Mỹ Hào | L3: Nội thành Hà Nội | M3: 06:00 | N3: 18:00 | O3: 10 | P3: 5 | Q3: 0.09 | R3: =Q3*'03_Cost_Constraints'!$B$3 | S3: =R3*1.15 | T3: 220000 | U3: 250000 | V3: 35 | W3: Yes | X3: Inner-city compatible | Y3: Available | Z3: 2026-06-05 | AA3: 20.9329 | AB3: 106.065 | AC3: OK | AD3: Sẵn sàng lập kế hoạch ngày hôm sau
A4: V003 | B4: 34C-50411 | C4: 5 tạ | D4: Phân phối | E4: 500 | F4: 4 | G4: No | H4: DRV003 | I4: Tài xế 03 | J4: PK_HP_DINHVU | K4: Kho Hải Phòng - Đình Vũ | L4: Nội thành Hà Nội | M4: 06:00 | N4: 18:00 | O4: 10 | P4: 5 | Q4: 0.09 | R4: =Q4*'03_Cost_Constraints'!$B$3 | S4: =R4*1.15 | T4: 220000 | U4: 250000 | V4: 35 | W4: Yes | X4: Inner-city compatible | Y4: Available | Z4: 2026-06-05 | AA4: 20.8425 | AB4: 106.77 | AC4: OK | AD4: Sẵn sàng lập kế hoạch ngày hôm sau
A5: V004 | B5: 36C-50548 | C5: 5 tạ | D5: Phân phối | E5: 500 | F5: 4 | G5: No | H5: DRV004 | I5: Tài xế 04 | J5: PK_TH_QX | K5: Kho DC Thanh Hóa - Quảng Xương | L5: Nội thành Hà Nội | M5: 06:00 | N5: 18:00 | O5: 10 | P5: 5 | Q5: 0.09 | R5: =Q5*'03_Cost_Constraints'!$B$3 | S5: =R5*1.15 | T5: 220000 | U5: 250000 | V5: 35 | W5: Yes | X5: Inner-city compatible | Y5: Available | Z5: 2026-06-05 | AA5: 19.731 | AB5: 105.815 | AC5: OK | AD5: Sẵn sàng lập kế hoạch ngày hôm sau
A6: V005 | B6: 17C-50685 | C6: 5 tạ | D6: Phân phối | E6: 500 | F6: 4 | G6: No | H6: DRV005 | I6: Tài xế 05 | J6: PK_NA_BACVINH | K6: Kho DC Vinh - KCN Bắc Vinh | L6: Nội thành Hà Nội | M6: 06:00 | N6: 18:00 | O6: 10 | P6: 5 | Q6: 0.09 | R6: =Q6*'03_Cost_Constraints'!$B$3 | S6: =R6*1.15 | T6: 220000 | U6: 250000 | V6: 35 | W6: Yes | X6: Inner-city compatible | Y6: Available | Z6: 2026-06-05 | AA6: 18.733 | AB6: 105.681 | AC6: OK | AD6: Sẵn sàng lập kế hoạch ngày hôm sau
A7: V006 | B7: 29C-50822 | C7: 5 tạ | D7: Phân phối | E7: 500 | F7: 4 | G7: No | H7: DRV006 | I7: Tài xế 06 | J7: PK_HPL_LB | K7: HPL Depot Long Biên - 20 Thạch Bàn | L7: Nội thành Hà Nội | M7: 06:00 | N7: 18:00 | O7: 10 | P7: 5 | Q7: 0.09 | R7: =Q7*'03_Cost_Constraints'!$B$3 | S7: =R7*1.15 | T7: 220000 | U7: 250000 | V7: 35 | W7: Yes | X7: Inner-city compatible | Y7: Available | Z7: 2026-06-05 | AA7: 21.026155 | AB7: 105.91418 | AC7: OK | AD7: Sẵn sàng lập kế hoạch ngày hôm sau
A8: V007 | B8: 30F-50959 | C8: 1.25T | D8: Phân phối | E8: 1250 | F8: 10 | G8: No | H8: DRV007 | I8: Tài xế 07 | J8: PK_LINFOX_VSIP | K8: Kho Linfox KCN VSIP Bắc Ninh | L8: Nội thành Hà Nội | M8: 06:00 | N8: 18:00 | O8: 10 | P8: 8 | Q8: 0.12 | R8: =Q8*'03_Cost_Constraints'!$B$3 | S8: =R8*1.15 | T8: 300000 | U8: 300000 | V8: 35 | W8: Yes | X8: Inner-city compatible | Y8: Available | Z8: 2026-06-05 | AA8: 21.082707 | AB8: 105.99795 | AC8: OK | AD8: Sẵn sàng lập kế hoạch ngày hôm sau
A9: V008 | B9: 31F-51096 | C9: 1.25T | D9: Phân phối | E9: 1250 | F9: 10 | G9: No | H9: DRV008 | I9: Tài xế 08 | J9: PK_HY_MYHAO | K9: Kho/Nhà máy khách hàng Mỹ Hào | L9: Nội thành Hà Nội | M9: 06:00 | N9: 18:00 | O9: 10 | P9: 8 | Q9: 0.12 | R9: =Q9*'03_Cost_Constraints'!$B$3 | S9: =R9*1.15 | T9: 300000 | U9: 300000 | V9: 35 | W9: Yes | X9: Inner-city compatible | Y9: Available | Z9: 2026-06-05 | AA9: 20.9329 | AB9: 106.065 | AC9: OK | AD9: Sẵn sàng lập kế hoạch ngày hôm sau
A10: V009 | B10: 34C-51233 | C10: 1.25T | D10: Phân phối | E10: 1250 | F10: 10 | G10: No | H10: DRV009 | I10: Tài xế 09 | J10: PK_HP_DINHVU | K10: Kho Hải Phòng - Đình Vũ | L10: Nội thành Hà Nội | M10: 06:00 | N10: 18:00 | O10: 10 | P10: 8 | Q10: 0.12 | R10: =Q10*'03_Cost_Constraints'!$B$3 | S10: =R10*1.15 | T10: 300000 | U10: 300000 | V10: 35 | W10: Yes | X10: Inner-city compatible | Y10: Available | Z10: 2026-06-05 | AA10: 20.8425 | AB10: 106.77 | AC10: OK | AD10: Sẵn sàng lập kế hoạch ngày hôm sau
A11: V010 | B11: 36C-51370 | C11: 1.25T | D11: Phân phối | E11: 1250 | F11: 10 | G11: No | H11: DRV010 | I11: Tài xế 10 | J11: PK_TH_QX | K11: Kho DC Thanh Hóa - Quảng Xương | L11: Nội thành Hà Nội | M11: 06:00 | N11: 18:00 | O11: 10 | P11: 8 | Q11: 0.12 | R11: =Q11*'03_Cost_Constraints'!$B$3 | S11: =R11*1.15 | T11: 300000 | U11: 300000 | V11: 35 | W11: Yes | X11: Inner-city compatible | Y11: Available | Z11: 2026-06-05 | AA11: 19.731 | AB11: 105.815 | AC11: OK | AD11: Sẵn sàng lập kế hoạch ngày hôm sau
A12: V011 | B12: 17C-51507 | C12: 1.25T | D12: Phân phối | E12: 1250 | F12: 10 | G12: No | H12: DRV011 | I12: Tài xế 11 | J12: PK_NA_BACVINH | K12: Kho DC Vinh - KCN Bắc Vinh | L12: Nội thành Hà Nội | M12: 06:00 | N12: 18:00 | O12: 10 | P12: 8 | Q12: 0.12 | R12: =Q12*'03_Cost_Constraints'!$B$3 | S12: =R12*1.15 | T12: 300000 | U12: 300000 | V12: 35 | W12: Yes | X12: Inner-city compatible | Y12: Available | Z12: 2026-06-05 | AA12: 18.733 | AB12: 105.681 | AC12: OK | AD12: Sẵn sàng lập kế hoạch ngày hôm sau
A13: V012 | B13: 29C-51644 | C13: 1.25T | D13: Phân phối | E13: 1250 | F13: 10 | G13: No | H13: DRV012 | I13: Tài xế 12 | J13: PK_HPL_LB | K13: HPL Depot Long Biên - 20 Thạch Bàn | L13: Nội thành Hà Nội | M13: 06:00 | N13: 18:00 | O13: 10 | P13: 8 | Q13: 0.12 | R13: =Q13*'03_Cost_Constraints'!$B$3 | S13: =R13*1.15 | T13: 300000 | U13: 300000 | V13: 35 | W13: Yes | X13: Inner-city compatible | Y13: Available | Z13: 2026-06-05 | AA13: 21.026155 | AB13: 105.91418 | AC13: OK | AD13: Sẵn sàng lập kế hoạch ngày hôm sau
... A41: V040 | B41: 36C-55480 | C41: 4 chân | D41: Phân phối | E41: 18000 | F41: 90 | G41: No | H41: DRV040 | I41: Tài xế 40 | J41: PK_NA_BACVINH | K41: Kho DC Vinh - KCN Bắc Vinh | L41: Bắc Trung Bộ | M41: 06:00 | N41: 18:00 | O41: 10 | P41: 3 | Q41: 0.39 | R41: =Q41*'03_Cost_Constraints'!$B$3 | S41: =R41*1.15 | T41: 1100000 | U41: 650000 | V41: 50 | W41: No | X41: Main-road only | Y41: Available | Z41: 2026-06-05 | AA41: 18.733 | AB41: 105.681 | AC41: OK | AD41: Sẵn sàng lập kế hoạch ngày hôm sau

Sheet S1_Thua_NangLuc
A1: Scenario_ID | B1: Planning_Date | C1: Order_ID | D1: Customer_Group | E1: Customer_Name | F1: Channel | G1: SKU_Code | H1: Product_Group | I1: Pickup_ID | J1: Pickup_Name | K1: Pickup_Province | L1: Pickup_District | M1: Pickup_Lat | N1: Pickup_Lon | O1: Delivery_ID | P1: Delivery_Name | Q1: Delivery_Province | R1: Delivery_District | S1: Delivery_Lat | T1: Delivery_Lon | U1: Corridor | V1: Route_Axis | W1: Direct_Distance_km | X1: Weight_kg | Y1: Volume_m3 | Z1: Pallet_Qty | AA1: Min_Vehicle_Type | AB1: Max_Vehicle_Type_Allowed | AC1: Required_Refrigeration | AD1: Can_Consolidate | AE1: Dedicated_Vehicle | AF1: Inner_City_Restriction | AG1: Access_Note | AH1: Pickup_TW_Start | AI1: Pickup_TW_End | AJ1: Drop_TW_Start | AK1: Drop_TW_End | AL1: TW_Flex_Min | AM1: Pickup_Service_Min | AN1: Drop_Service_Min | AO1: Lead_Time_Min | AP1: Freight_Revenue_VND | AQ1: Extra_Stop_Fee_VND | AR1: Waiting_Fee_Chargeable_VND | AS1: Late_Penalty_VND_per_30m | AT1: Customer_Priority | AU1: Contract_Route_ID | AV1: Source_System | AW1: Seed_Cluster_ID | AX1: Suggested_Vehicle_Type | AY1: Suggested_Action | AZ1: Validation_Status | BA1: Risk_Flag | BB1: Total_Service_Min | BC1: Direct_Drive_Min | BD1: Load_Class_kg | BE1: LeadTime_Check | BF1: Algorithm_Ready_Flag | BG1: Notes
A2: S1 | B2: 2026-06-05 | C2: S1-ORD-001 | D2: Linfox | E2: VINMART Võ Thị Sáu | F2: ST | G2: PAT2 | H2: Bia lon 333 | I2: PK_HY_MYHAO | J2: Kho/Nhà máy khách hàng Mỹ Hào | K2: Hưng Yên | L2: Mỹ Hào | M2: 20.9329 | N2: 106.065 | O2: DL_HN_VOTHISAU | P2: VINMART Võ Thị Sáu | Q2: Hà Nội | R2: Hai Bà Trưng | S2: 21.00441 | T2: 105.85515 | U2: Nội thành Hà Nội | V2: Nội thành Hà Nội | W2: 41.3 | X2: 385 | Y2: 0.93 | Z2: 1 | AA2: 5 tạ | AB2: 1.25T | AC2: No | AD2: Yes | AE2: No | AF2: Yes | AG2: Giờ cấm tải, xe <=1.25T | AH2: 08:00 | AI2: 10:30 | AJ2: 10:55 | AK2: 12:25 | AL2: 45 | AM2: 25 | AN2: 20 | AO2: 265 | AP2: 670000 | AQ2: 0 | AR2: 0 | AS2: 150000 | AT2: A - SLA chặt | AU2: CR-NỘIT-02 | AV2: Manual nhập điều phối | AW2: S1-C01 | AX2: 5 tạ | AY2: Send to Clustering | AZ2: OK | BA2: Cấm tải/đường nhỏ - đã chọn xe nhỏ | BB2: =AM2+AN2 | BC2: =ROUND(W2/'03_Cost_Constraints'!$B$4*60,0) | BD2: =IF(X2<=500,"5 tạ",IF(X2<=1250,"1.25T",IF(X2<=5000,"5T",IF(X2<=8000,"8T",IF(X2<=15000,"3 chân","4 chân"))))) | BE2: =IF((BB2+BC2)<=AO2,"OK","Risk") | BF2: =IF(AND(AZ2="OK",BE2="OK"),"Ready","Review")
A3: S1 | B3: 2026-06-05 | C3: S1-ORD-002 | D3: Linfox | E3: VINMART Royal City | F3: MT | G3: PAT2 | H3: Bia lon 333 | I3: PK_HY_MYHAO | J3: Kho/Nhà máy khách hàng Mỹ Hào | K3: Hưng Yên | L3: Mỹ Hào | M3: 20.9329 | N3: 106.065 | O3: DL_HN_ROYAL | P3: VINMART Royal City | Q3: Hà Nội | R3: Thanh Xuân | S3: 21.003388 | T3: 105.81621 | U3: Nội thành Hà Nội | V3: Nội thành Hà Nội | W3: 42.8 | X3: 307 | Y3: 0.88 | Z3: 1 | AA3: 5 tạ | AB3: 1.25T | AC3: No | AD3: Yes | AE3: No | AF3: Yes | AG3: Hầm trung tâm thương mại | AH3: 08:30 | AI3: 10:00 | AJ3: 11:58 | AK3: 13:58 | AL3: 45 | AM3: 25 | AN3: 30 | AO3: 328 | AP3: 860000 | AQ3: 0 | AR3: 120000 | AS3: 80000 | AT3: B - Thường | AU3: CR-NỘIT-03 | AV3: Excel khách hàng | AW3: S1-C02 | AX3: 5 tạ | AY3: Send to Clustering | AZ3: OK | BA3: Cấm tải/đường nhỏ - đã chọn xe nhỏ | BB3: =AM3+AN3 | BC3: =ROUND(W3/'03_Cost_Constraints'!$B$4*60,0) | BD3: =IF(X3<=500,"5 tạ",IF(X3<=1250,"1.25T",IF(X3<=5000,"5T",IF(X3<=8000,"8T",IF(X3<=15000,"3 chân","4 chân"))))) | BE3: =IF((BB3+BC3)<=AO3,"OK","Risk") | BF3: =IF(AND(AZ3="OK",BE3="OK"),"Ready","Review")
A4: S1 | B4: 2026-06-05 | C4: S1-ORD-003 | D4: MM Mega Market | E4: VINMART Quế Võ | F4: ST | G4: MILK | H4: Sữa hộp carton | I4: PK_LINFOX_VSIP | J4: Kho Linfox KCN VSIP Bắc Ninh | K4: Bắc Ninh | L4: Từ Sơn | M4: 21.082707 | N4: 105.99795 | O4: DL_BN_QUEVO_01 | P4: VINMART Quế Võ | Q4: Bắc Ninh | R4: Quế Võ | S4: 21.170139 | T4: 106.1024 | U4: Đông Bắc | V4: Đông Bắc | W4: 25.1 | X4: 7751 | Y4: 16.16 | Z4: 13 | AA4: 8T | AB4: 8T | AC4: No | AD4: Yes | AE4: No | AF4: No | AG4: Đường rộng, xe 5T/8T vào được | AH4: 07:30 | AI4: 09:00 | AJ4: 10:03 | AK4: 12:03 | AL4: 30 | AM4: 40 | AN4: 35 | AO4: 273 | AP4: 1810000 | AQ4: 150000 | AR4: 0 | AS4: 80000 | AT4: C - Có thể thương lượng | AU4: CR-ĐÔNG-04 | AV4: Hệ thống khách hàng | AW4: S1-C03 | AX4: 8T | AY4: Send to Clustering | AZ4: OK | BA4: OK | BB4: =AM4+AN4 | BC4: =ROUND(W4/'03_Cost_Constraints'!$B$4*60,0) | BD4: =IF(X4<=500,"5 tạ",IF(X4<=1250,"1.25T",IF(X4<=5000,"5T",IF(X4<=8000,"8T",IF(X4<=15000,"3 chân","4 chân"))))) | BE4: =IF((BB4+BC4)<=AO4,"OK","Risk") | BF4: =IF(AND(AZ4="OK",BE4="OK"),"Ready","Review")
A5: S1 | B5: 2026-06-05 | C5: S1-ORD-004 | D5: Bách Hóa Xanh | E5: VINMART Bắc Từ Liêm | F5: ST | G5: LVCA | H5: Bia lon Lạc Việt | I5: PK_HY_MYHAO | J5: Kho/Nhà máy khách hàng Mỹ Hào | K5: Hưng Yên | L5: Mỹ Hào | M5: 20.9329 | N5: 106.065 | O5: DL_HN_BACTULIEM | P5: VINMART Bắc Từ Liêm | Q5: Hà Nội | R5: Bắc Từ Liêm | S5: 21.052701 | T5: 105.78073 | U5: Nội thành Hà Nội | V5: Nội thành Hà Nội | W5: 54.1 | X5: 226 | Y5: 0.6 | Z5: 1 | AA5: 5 tạ | AB5: 1.25T | AC5: No | AD5: Yes | AE5: No | AF5: Yes | AG5: Nội đô, khung giờ hạn chế xe tải | AH5: 07:00 | AI5: 09:00 | AJ5: 09:17 | AK5: 12:17 | AL5: 45 | AM5: 25 | AN5: 20 | AO5: 317 | AP5: 850000 | AQ5: 0 | AR5: 0 | AS5: 80000 | AT5: C - Có thể thương lượng | AU5: CR-NỘIT-05 | AV5: Zalo/Email plan 17:00 | AW5: S1-C04 | AX5: 5 tạ | AY5: Send to Clustering | AZ5: OK | BA5: Cấm tải/đường nhỏ - đã chọn xe nhỏ | BB5: =AM5+AN5 | BC5: =ROUND(W5/'03_Cost_Constraints'!$B$4*60,0) | BD5: =IF(X5<=500,"5 tạ",IF(X5<=1250,"1.25T",IF(X5<=5000,"5T",IF(X5<=8000,"8T",IF(X5<=15000,"3 chân","4 chân"))))) | BE5: =IF((BB5+BC5)<=AO5,"OK","Risk") | BF5: =IF(AND(AZ5="OK",BE5="OK"),"Ready","Review") | BG5: Kế hoạch ngày hôm sau; cần chốt trước 19:00 và gửi tài xế sau duyệt
A6: S1 | B6: 2026-06-05 | C6: S1-ORD-005 | D6: Bách Hóa Xanh | E6: VINMART Võ Thị Sáu | F6: ST | G6: CHCA | H6: Bia lon Saigon Chill | I6: PK_HPL_LB | J6: HPL Depot Long Biên - 20 Thạch Bàn | K6: Hà Nội | L6: Long Biên | M6: 21.026155 | N6: 105.91418 | O6: DL_HN_VOTHISAU | P6: VINMART Võ Thị Sáu | Q6: Hà Nội | R6: Hai Bà Trưng | S6: 21.00441 | T6: 105.85515 | U6: Nội thành Hà Nội | V6: Nội thành Hà Nội | W6: 15.8 | X6: 661 | Y6: 1.58 | Z6: 1 | AA6: 1.25T | AB6: 1.25T | AC6: No | AD6: Yes | AE6: No | AF6: Yes | AG6: Giờ cấm tải, xe <=1.25T | AH6: 07:00 | AI6: 09:30 | AJ6: 09:12 | AK6: 11:12 | AL6: 45 | AM6: 25 | AN6: 20 | AO6: 252 | AP6: 490000 | AQ6: 0 | AR6: 0 | AS6: 80000 | AT6: B - Thường | AU6: CR-NỘIT-01 | AV6: Manual nhập điều phối | AW6: S1-C05 | AX6: 1.25T | AY6: Send to Clustering | AZ6: OK | BA6: Cấm tải/đường nhỏ - đã chọn xe nhỏ | BB6: =AM6+AN6 | BC6: =ROUND(W6/'03_Cost_Constraints'!$B$4*60,0) | BD6: =IF(X6<=500,"5 tạ",IF(X6<=1250,"1.25T",IF(X6<=5000,"5T",IF(X6<=8000,"8T",IF(X6<=15000,"3 chân","4 chân"))))) | BE6: =IF((BB6+BC6)<=AO6,"OK","Risk") | BF6: =IF(AND(AZ6="OK",BE6="OK"),"Ready","Review")
A7: S1 | B7: 2026-06-05 | C7: S1-ORD-006 | D7: Masan | E7: Siêu thị Hải Dương | F7: ST | G7: POSM | H7: POSM trưng bày | I7: PK_HPL_LB | J7: HPL Depot Long Biên - 20 Thạch Bàn | K7: Hà Nội | L7: Long Biên | M7: 21.026155 | N7: 105.91418 | O7: DL_HD_SIEUTHI | P7: Siêu thị Hải Dương | Q7: Hải Phòng | R7: Hải Dương | S7: 20.937341 | T7: 106.31455 | U7: Đông Bắc | V7: Đông Bắc | W7: 62.1 | X7: 7814 | Y7: 172.96 | Z7: 144 | AA7: Container | AB7: 8T | AC7: No | AD7: Yes | AE7: No | AF7: No | AG7: Quốc lộ 5, xe 8T vào được | AH7: 07:00 | AI7: 09:30 | AJ7: 12:12 | AK7: 14:12 | AL7: 30 | AM7: 120 | AN7: 90 | AO7: 432 | AP7: 3320000 | AQ7: 150000 | AR7: 0 | AS7: 80000 | AT7: C - Có thể thương lượng | AU7: CR-ĐÔNG-02 | AV7: Excel khách hàng | AW7: S1-C06 | AX7: Split/Chuyển tải | AY7: Split Order/Chuyển tải hoặc xin xe nhỏ nhiều chuyến | AZ7: Review | BA7: Vehicle Mismatch | BB7: =AM7+AN7 | BC7: =ROUND(W7/'03_Cost_Constraints'!$B$4*60,0) | BD7: =IF(X7<=500,"5 tạ",IF(X7<=1250,"1.25T",IF(X7<=5000,"5T",IF(X7<=8000,"8T",IF(X7<=15000,"3 chân","4 chân"))))) | BE7: =IF((BB7+BC7)<=AO7,"OK","Risk") | BF7: =IF(AND(AZ7="OK",BE7="OK"),"Ready","Review")
A8: S1 | B8: 2026-06-05 | C8: S1-ORD-007 | D8: Masan | E8: Thái Dương | F8: Đại lý | G8: POSM | H8: POSM trưng bày | I8: PK_HY_MYHAO | J8: Kho/Nhà máy khách hàng Mỹ Hào | K8: Hưng Yên | L8: Mỹ Hào | M8: 20.9329 | N8: 106.065 | O8: DL_HN_THAIDUONG | P8: Thái Dương | Q8: Hà Nội | R8: Hà Nội | S8: 20.929215 | T8: 105.87 | U8: Nội thành Hà Nội | V8: Nội thành Hà Nội | W8: 31.3 | X8: 1470 | Y8: 33.65 | Z8: 28 | AA8: 8T | AB8: 1.25T | AC8: No | AD8: Yes | AE8: No | AF8: Yes | AG8: Đường nhỏ, ưu tiên xe <=1.25T | AH8: 07:00 | AI8: 09:00 | AJ8: 09:23 | AK8: 11:23 | AL8: 30 | AM8: 40 | AN8: 35 | AO8: 263 | AP8: 660000 | AQ8: 0 | AR8: 0 | AS8: 80000 | AT8: B - Thường | AU8: CR-NỘIT-03 | AV8: Hệ thống khách hàng | AW8: S1-C07 | AX8: Split/Chuyển tải | AY8: Split Order/Chuyển tải hoặc xin xe nhỏ nhiều chuyến | AZ8: Review | BA8: Vehicle Mismatch | BB8: =AM8+AN8 | BC8: =ROUND(W8/'03_Cost_Constraints'!$B$4*60,0) | BD8: =IF(X8<=500,"5 tạ",IF(X8<=1250,"1.25T",IF(X8<=5000,"5T",IF(X8<=8000,"8T",IF(X8<=15000,"3 chân","4 chân"))))) | BE8: =IF((BB8+BC8)<=AO8,"OK","Risk") | BF8: =IF(AND(AZ8="OK",BE8="OK"),"Ready","Review")
A9: S1 | B9: 2026-06-05 | C9: S1-ORD-008 | D9: Acecook | E9: VINMART Võ Thị Sáu | F9: ST | G9: POSM | H9: POSM trưng bày | I9: PK_LINFOX_VSIP | J9: Kho Linfox KCN VSIP Bắc Ninh | K9: Bắc Ninh | L9: Từ Sơn | M9: 21.082707 | N9: 105.99795 | O9: DL_HN_VOTHISAU | P9: VINMART Võ Thị Sáu | Q9: Hà Nội | R9: Hai Bà Trưng | S9: 21.00441 | T9: 105.85515 | U9: Nội thành Hà Nội | V9: Nội thành Hà Nội | W9: 31.9 | X9: 1371 | Y9: 32.73 | Z9: 27 | AA9: 8T | AB9: 1.25T | AC9: No | AD9: Yes | AE9: No | AF9: Yes | AG9: Giờ cấm tải, xe <=1.25T | AH9: 09:00 | AI9: 10:30 | AJ9: 12:24 | AK9: 14:24 | AL9: 45 | AM9: 40 | AN9: 35 | AO9: 324 | AP9: 650000 | AQ9: 0 | AR9: 0 | AS9: 80000 | AT9: C - Có thể thương lượng | AU9: CR-NỘIT-04 | AV9: Zalo/Email plan 17:00 | AW9: S1-C07 | AX9: Split/Chuyển tải | AY9: Split Order/Chuyển tải hoặc xin xe nhỏ nhiều chuyến | AZ9: Review | BA9: Vehicle Mismatch | BB9: =AM9+AN9 | BC9: =ROUND(W9/'03_Cost_Constraints'!$B$4*60,0) | BD9: =IF(X9<=500,"5 tạ",IF(X9<=1250,"1.25T",IF(X9<=5000,"5T",IF(X9<=8000,"8T",IF(X9<=15000,"3 chân","4 chân"))))) | BE9: =IF((BB9+BC9)<=AO9,"OK","Risk") | BF9: =IF(AND(AZ9="OK",BE9="OK"),"Ready","Review") | BG9: Kế hoạch ngày hôm sau; cần chốt trước 19:00 và gửi tài xế sau duyệt
A10: S1 | B10: 2026-06-05 | C10: S1-ORD-009 | D10: MM Mega Market | E10: VINMART Hoài Đức | F10: ST | G10: EXPL | H10: Bia lon Saigon Export | I10: PK_HPL_LB | J10: HPL Depot Long Biên - 20 Thạch Bàn | K10: Hà Nội | L10: Long Biên | M10: 21.026155 | N10: 105.91418 | O10: DL_HN_HOAIDUC | P10: VINMART Hoài Đức | Q10: Hà Nội | R10: Hoài Đức | S10: 21.005046 | T10: 105.72829 | U10: Tây Bắc | V10: Tây Bắc | W10: 28.9 | X10: 4822 | Y10: 12.04 | Z10: 10 | AA10: 5T | AB10: 5T | AC10: No | AD10: Yes | AE10: No | AF10: No | AG10: Ngoại thành, xe 5T vào được | AH10: 08:00 | AI10: 10:30 | AJ10: 09:38 | AK10: 12:38 | AL10: 30 | AM10: 40 | AN10: 35 | AO10: 278 | AP10: 1170000 | AQ10: 150000 | AR10: 0 | AS10: 80000 | AT10: C - Có thể thương lượng | AU10: CR-TÂYB-05 | AV10: Manual nhập điều phối | AW10: S1-C09 | AX10: 5T | AY10: Send to Clustering | AZ10: OK | BA10: OK | BB10: =AM10+AN10 | BC10: =ROUND(W10/'03_Cost_Constraints'!$B$4*60,0) | BD10: =IF(X10<=500,"5 tạ",IF(X10<=1250,"1.25T",IF(X10<=5000,"5T",IF(X10<=8000,"8T",IF(X10<=15000,"3 chân","4 chân"))))) | BE10: =IF((BB10+BC10)<=AO10,"OK","Risk") | BF10: =IF(AND(AZ10="OK",BE10="OK"),"Ready","Review")
A11: S1 | B11: 2026-06-05 | C11: S1-ORD-010 | D11: Acecook | E11: Thái Dương | F11: Đại lý | G11: SP33 | H11: Bia lon Saigon Special | I11: PK_LINFOX_VSIP | J11: Kho Linfox KCN VSIP Bắc Ninh | K11: Bắc Ninh | L11: Từ Sơn | M11: 21.082707 | N11: 105.99795 | O11: DL_HN_THAIDUONG | P11: Thái Dương | Q11: Hà Nội | R11: Hà Nội | S11: 20.929215 | T11: 105.87 | U11: Nội thành Hà Nội | V11: Nội thành Hà Nội | W11: 35.5 | X11: 909 | Y11: 1.5 | Z11: 1 | AA11: 1.25T | AB11: 1.25T | AC11: No | AD11: Yes | AE11: No | AF11: Yes | AG11: Đường nhỏ, ưu tiên xe <=1.25T | AH11: 07:00 | AI11: 08:30 | AJ11: 09:15 | AK11: 10:45 | AL11: 45 | AM11: 25 | AN11: 20 | AO11: 225 | AP11: 600000 | AQ11: 0 | AR11: 0 | AS11: 80000 | AT11: C - Có thể thương lượng | AU11: CR-NỘIT-01 | AV11: Excel khách hàng | AW11: S1-C10 | AX11: 1.25T | AY11: Send to Clustering | AZ11: OK | BA11: Cấm tải/đường nhỏ - đã chọn xe nhỏ | BB11: =AM11+AN11 | BC11: =ROUND(W11/'03_Cost_Constraints'!$B$4*60,0) | BD11: =IF(X11<=500,"5 tạ",IF(X11<=1250,"1.25T",IF(X11<=5000,"5T",IF(X11<=8000,"8T",IF(X11<=15000,"3 chân","4 chân"))))) | BE11: =IF((BB11+BC11)<=AO11,"OK","Risk") | BF11: =IF(AND(AZ11="OK",BE11="OK"),"Ready","Review")
A12: S1 | B12: 2026-06-05 | C12: S1-ORD-011 | D12: MM Mega Market | E12: VINMART Bắc Từ Liêm | F12: ST | G12: SP33 | H12: Bia lon Saigon Special | I12: PK_HPL_LB | J12: HPL Depot Long Biên - 20 Thạch Bàn | K12: Hà Nội | L12: Long Biên | M12: 21.026155 | N12: 105.91418 | O12: DL_HN_BACTULIEM | P12: VINMART Bắc Từ Liêm | Q12: Hà Nội | R12: Bắc Từ Liêm | S12: 21.052701 | T12: 105.78073 | U12: Nội thành Hà Nội | V12: Nội thành Hà Nội | W12: 26.2 | X12: 945 | Y12: 2.06 | Z12: 1 | AA12: 1.25T | AB12: 1.25T | AC12: No | AD12: Yes | AE12: No | AF12: Yes | AG12: Nội đô, khung giờ hạn chế xe tải | AH12: 07:00 | AI12: 09:00 | AJ12: 09:29 | AK12: 10:59 | AL12: 30 | AM12: 25 | AN12: 20 | AO12: 239 | AP12: 910000 | AQ12: 0 | AR12: 0 | AS12: 80000 | AT12: B - Thường | AU12: CR-NỘIT-02 | AV12: Hệ thống khách hàng | AW12: S1-C11 | AX12: 1.25T | AY12: Send to Clustering | AZ12: OK | BA12: Cấm tải/đường nhỏ - đã chọn xe nhỏ | BB12: =AM12+AN12 | BC12: =ROUND(W12/'03_Cost_Constraints'!$B$4*60,0) | BD12: =IF(X12<=500,"5 tạ",IF(X12<=1250,"1.25T",IF(X12<=5000,"5T",IF(X12<=8000,"8T",IF(X12<=15000,"3 chân","4 chân"))))) | BE12: =IF((BB12+BC12)<=AO12,"OK","Risk") | BF12: =IF(AND(AZ12="OK",BE12="OK"),"Ready","Review")
A13: S1 | B13: 2026-06-05 | C13: S1-ORD-012 | D13: VinCommerce | E13: TOPS MARKET Garden Mall | F13: MT | G13: EXPL | H13: Bia lon Saigon Export | I13: PK_LINFOX_VSIP | J13: Kho Linfox KCN VSIP Bắc Ninh | K13: Bắc Ninh | L13: Từ Sơn | M13: 21.082707 | N13: 105.99795 | O13: DL_HN_GARDEN | P13: TOPS MARKET Garden Mall | Q13: Hà Nội | R13: Nam Từ Liêm | S13: 21.015324 | T13: 105.77784 | U13: Nội thành Hà Nội | V13: Nội thành Hà Nội | W13: 39.8 | X13: 349 | Y13: 0.89 | Z13: 1 | AA13: 5 tạ | AB13: 1.25T | AC13: No | AD13: Yes | AE13: No | AF13: Yes | AG13: Khung giờ nhập kho cố định | AH13: 08:00 | AI13: 10:00 | AJ13: 10:23 | AK13: 13:23 | AL13: 45 | AM13: 25 | AN13: 30 | AO13: 323 | AP13: 510000 | AQ13: 150000 | AR13: 120000 | AS13: 80000 | AT13: B - Thường | AU13: CR-NỘIT-03 | AV13: Zalo/Email plan 17:00 | AW13: S1-C12 | AX13: 5 tạ | AY13: Send to Clustering | AZ13: OK | BA13: Cấm tải/đường nhỏ - đã chọn xe nhỏ | BB13: =AM13+AN13 | BC13: =ROUND(W13/'03_Cost_Constraints'!$B$4*60,0) | BD13: =IF(X13<=500,"5 tạ",IF(X13<=1250,"1.25T",IF(X13<=5000,"5T",IF(X13<=8000,"8T",IF(X13<=15000,"3 chân","4 chân"))))) | BE13: =IF((BB13+BC13)<=AO13,"OK","Risk") | BF13: =IF(AND(AZ13="OK",BE13="OK"),"Ready","Review") | BG13: Kế hoạch ngày hôm sau; cần chốt trước 19:00 và gửi tài xế sau duyệt
A14: S1 | B14: 2026-06-05 | C14: S1-ORD-013 | D14: VinCommerce | E14: Siêu thị Hải Dương | F14: ST | G14: CHCA | H14: Bia lon Saigon Chill | I14: PK_LINFOX_VSIP | J14: Kho Linfox KCN VSIP Bắc Ninh | K14: Bắc Ninh | L14: Từ Sơn | M14: 21.082707 | N14: 105.99795 | O14: DL_HD_SIEUTHI | P14: Siêu thị Hải Dương | Q14: Hải Phòng | R14: Hải Dương | S14: 20.937341 | T14: 106.31455 | U14: Đông Bắc | V14: Đông Bắc | W14: 49.4 | X14: 1820 | Y14: 2.93 | Z14: 2 | AA14: 5T | AB14: 8T | AC14: No | AD14: Yes | AE14: No | AF14: No | AG14: Quốc lộ 5, xe 8T vào được | AH14: 08:30 | AI14: 10:30 | AJ14: 12:05 | AK14: 15:05 | AL14: 45 | AM14: 40 | AN14: 35 | AO14: 395 | AP14: 910000 | AQ14: 0 | AR14: 0 | AS14: 80000 | AT14: C - Có thể thương lượng | AU14: CR-ĐÔNG-04 | AV14: Manual nhập điều phối | AW14: S1-C13 | AX14: 5T | AY14: Send to Clustering | AZ14: OK | BA14: OK | BB14: =AM14+AN14 | BC14: =ROUND(W14/'03_Cost_Constraints'!$B$4*60,0) | BD14: =IF(X14<=500,"5 tạ",IF(X14<=1250,"1.25T",IF(X14<=5000,"5T",IF(X14<=8000,"8T",IF(X14<=15000,"3 chân","4 chân"))))) | BE14: =IF((BB14+BC14)<=AO14,"OK","Risk") | BF14: =IF(AND(AZ14="OK",BE14="OK"),"Ready","Review")
A15: S1 | B15: 2026-06-05 | C15: S1-ORD-014 | D15: Sabeco | E15: LOTTE MART Ba Đình | F15: MT | G15: FMCG | H15: Hàng tiêu dùng nhanh hỗn hợp | I15: PK_HY_MYHAO | J15: Kho/Nhà máy khách hàng Mỹ Hào | K15: Hưng Yên | L15: Mỹ Hào | M15: 20.9329 | N15: 106.065 | O15: DL_HN_LOTTE_BD | P15: LOTTE MART Ba Đình | Q15: Hà Nội | R15: Ba Đình | S15: 21.032177 | T15: 105.81244 | U15: Nội thành Hà Nội | V15: Nội thành Hà Nội | W15: 47.7 | X15: 1392 | Y15: 4.83 | Z15: 4 | AA15: 5T | AB15: 1.25T | AC15: No | AD15: Yes | AE15: No | AF15: Yes | AG15: Giờ cấm tải, ưu tiên xe 1.25T | AH15: 09:00 | AI15: 11:30 | AJ15: 11:21 | AK15: 12:51 | AL15: 30 | AM15: 40 | AN15: 45 | AO15: 231 | AP15: 910000 | AQ15: 0 | AR15: 120000 | AS15: 80000 | AT15: C - Có thể thương lượng | AU15: CR-NỘIT-05 | AV15: Excel khách hàng | AW15: S1-C14 | AX15: Split/Chuyển tải | AY15: Split Order/Chuyển tải hoặc xin xe nhỏ nhiều chuyến | AZ15: Review | BA15: Vehicle Mismatch | BB15: =AM15+AN15 | BC15: =ROUND(W15/'03_Cost_Constraints'!$B$4*60,0) | BD15: =IF(X15<=500,"5 tạ",IF(X15<=1250,"1.25T",IF(X15<=5000,"5T",IF(X15<=8000,"8T",IF(X15<=15000,"3 chân","4 chân"))))) | BE15: =IF((BB15+BC15)<=AO15,"OK","Risk") | BF15: =IF(AND(AZ15="OK",BE15="OK"),"Ready","Review")
A16: S1 | B16: 2026-06-05 | C16: S1-ORD-015 | D16: Acecook | E16: VINMART Trương Định | F16: ST | G16: CHCA | H16: Bia lon Saigon Chill | I16: PK_HPL_LB | J16: HPL Depot Long Biên - 20 Thạch Bàn | K16: Hà Nội | L16: Long Biên | M16: 21.026155 | N16: 105.91418 | O16: DL_HN_TRUONGDINH | P16: VINMART Trương Định | Q16: Hà Nội | R16: Hoàng Mai | S16: 20.979293 | T16: 105.84471 | U16: Nội thành Hà Nội | V16: Nội thành Hà Nội | W16: 17 | X16: 914 | Y16: 2 | Z16: 1 | AA16: 1.25T | AB16: 1.25T | AC16: No | AD16: Yes | AE16: No | AF16: Yes | AG16: Đường nhỏ, khó quay đầu | AH16: 09:00 | AI16: 10:30 | AJ16: 11:44 | AK16: 13:14 | AL16: 45 | AM16: 25 | AN16: 20 | AO16: 254 | AP16: 520000 | AQ16: 150000 | AR16: 0 | AS16: 80000 | AT16: C - Có thể thương lượng | AU16: CR-NỘIT-01 | AV16: Hệ thống khách hàng | AW16: S1-C15 | AX16: 1.25T | AY16: Send to Clustering | AZ16: OK | BA16: Cấm tải/đường nhỏ - đã chọn xe nhỏ | BB16: =AM16+AN16 | BC16: =ROUND(W16/'03_Cost_Constraints'!$B$4*60,0) | BD16: =IF(X16<=500,"5 tạ",IF(X16<=1250,"1.25T",IF(X16<=5000,"5T",IF(X16<=8000,"8T",IF(X16<=15000,"3 chân","4 chân"))))) | BE16: =IF((BB16+BC16)<=AO16,"OK","Risk") | BF16: =IF(AND(AZ16="OK",BE16="OK"),"Ready","Review")
A17: S1 | B17: 2026-06-05 | C17: S1-ORD-016 | D17: Linfox | E17: VINMART Hoài Đức | F17: ST | G17: NOODLE | H17: Mì gói/Acecook carton | I17: PK_LINFOX_VSIP | J17: Kho Linfox KCN VSIP Bắc Ninh | K17: Bắc Ninh | L17: Từ Sơn | M17: 21.082707 | N17: 105.99795 | O17: DL_HN_HOAIDUC | P17: VINMART Hoài Đức | Q17: Hà Nội | R17: Hoài Đức | S17: 21.005046 | T17: 105.72829 | U17: Tây Bắc | V17: Tây Bắc | W17: 43.7 | X17: 7741 | Y17: 70.3 | Z17: 58 | AA17: 4 chân | AB17: 5T | AC17: No | AD17: Yes | AE17: No | AF17: No | AG17: Ngoại thành, xe 5T vào được | AH17: 08:30 | AI17: 11:00 | AJ17: 13:18 | AK17: 15:48 | AL17: 45 | AM17: 120 | AN17: 90 | AO17: 438 | AP17: 2200000 | AQ17: 0 | AR17: 0 | AS17: 80000 | AT17: B - Thường | AU17: CR-TÂYB-02 | AV17: Zalo/Email plan 17:00 | AW17: S1-C16 | AX17: Split/Chuyển tải | AY17: Split Order/Chuyển tải hoặc xin xe nhỏ nhiều chuyến | AZ17: Review | BA17: Vehicle Mismatch | BB17: =AM17+AN17 | BC17: =ROUND(W17/'03_Cost_Constraints'!$B$4*60,0) | BD17: =IF(X17<=500,"5 tạ",IF(X17<=1250,"1.25T",IF(X17<=5000,"5T",IF(X17<=8000,"8T",IF(X17<=15000,"3 chân","4 chân"))))) | BE17: =IF((BB17+BC17)<=AO17,"OK","Risk") | BF17: =IF(AND(AZ17="OK",BE17="OK"),"Ready","Review") | BG17: Kế hoạch ngày hôm sau; cần chốt trước 19:00 và gửi tài xế sau duyệt
A18: S1 | B18: 2026-06-05 | C18: S1-ORD-017 | D18: MM Mega Market | E18: Nam Dương | F18: Đại lý | G18: MILK | H18: Sữa hộp carton | I18: PK_HPL_LB | J18: HPL Depot Long Biên - 20 Thạch Bàn | K18: Hà Nội | L18: Long Biên | M18: 21.026155 | N18: 105.91418 | O18: DL_HN_NAMDUONG | P18: Nam Dương | Q18: Hà Nội | R18: Hà Nội | S18: 21.062911 | T18: 105.83235 | U18: Nội thành Hà Nội | V18: Nội thành Hà Nội | W18: 18.4 | X18: 1076 | Y18: 2.93 | Z18: 2 | AA18: 1.25T | AB18: 1.25T | AC18: No | AD18: Yes | AE18: No | AF18: Yes | AG18: Đường nội đô, có khung giờ cấm tải | AH18: 07:30 | AI18: 09:30 | AJ18: 10:16 | AK18: 12:16 | AL18: 30 | AM18: 25 | AN18: 20 | AO18: 286 | AP18: 890000 | AQ18: 0 | AR18: 0 | AS18: 80000 | AT18: B - Thường | AU18: CR-NỘIT-03 | AV18: Manual nhập điều phối | AW18: S1-C16 | AX18: 1.25T | AY18: Send to Clustering | AZ18: OK | BA18: Cấm tải/đường nhỏ - đã chọn xe nhỏ | BB18: =AM18+AN18 | BC18: =ROUND(W18/'03_Cost_Constraints'!$B$4*60,0) | BD18: =IF(X18<=500,"5 tạ",IF(X18<=1250,"1.25T",IF(X18<=5000,"5T",IF(X18<=8000,"8T",IF(X18<=15000,"3 chân","4 chân"))))) | BE18: =IF((BB18+BC18)<=AO18,"OK","Risk") | BF18: =IF(AND(AZ18="OK",BE18="OK"),"Ready","Review")
A19: S1 | B19: 2026-06-05 | C19: S1-ORD-018 | D19: Linfox | E19: LOTTE MART Ba Đình | F19: MT | G19: PAT2 | H19: Bia lon 333 | I19: PK_HY_MYHAO | J19: Kho/Nhà máy khách hàng Mỹ Hào | K19: Hưng Yên | L19: Mỹ Hào | M19: 20.9329 | N19: 106.065 | O19: DL_HN_LOTTE_BD | P19: LOTTE MART Ba Đình | Q19: Hà Nội | R19: Ba Đình | S19: 21.032177 | T19: 105.81244 | U19: Nội thành Hà Nội | V19: Nội thành Hà Nội | W19: 48.9 | X19: 670 | Y19: 1.57 | Z19: 1 | AA19: 1.25T | AB19: 1.25T | AC19: No | AD19: Yes | AE19: No | AF19: Yes | AG19: Giờ cấm tải, ưu tiên xe 1.25T | AH19: 07:30 | AI19: 09:00 | AJ19: 09:38 | AK19: 12:08 | AL19: 45 | AM19: 25 | AN19: 30 | AO19: 278 | AP19: 750000 | AQ19: 150000 | AR19: 120000 | AS19: 80000 | AT19: B - Thường | AU19: CR-NỘIT-04 | AV19: Excel khách hàng | AW19: S1-C18 | AX19: 1.25T | AY19: Send to Clustering | AZ19: OK | BA19: Cấm tải/đường nhỏ - đã chọn xe nhỏ | BB19: =AM19+AN19 | BC19: =ROUND(W19/'03_Cost_Constraints'!$B$4*60,0) | BD19: =IF(X19<=500,"5 tạ",IF(X19<=1250,"1.25T",IF(X19<=5000,"5T",IF(X19<=8000,"8T",IF(X19<=15000,"3 chân","4 chân"))))) | BE19: =IF((BB19+BC19)<=AO19,"OK","Risk") | BF19: =IF(AND(AZ19="OK",BE19="OK"),"Ready","Review")
A20: S1 | B20: 2026-06-05 | C20: S1-ORD-019 | D20: Bách Hóa Xanh | E20: VINMART Royal City | F20: MT | G20: PAT2 | H20: Bia lon 333 | I20: PK_HPL_LB | J20: HPL Depot Long Biên - 20 Thạch Bàn | K20: Hà Nội | L20: Long Biên | M20: 21.026155 | N20: 105.91418 | O20: DL_HN_ROYAL | P20: VINMART Royal City | Q20: Hà Nội | R20: Thanh Xuân | S20: 21.003388 | T20: 105.81621 | U20: Nội thành Hà Nội | V20: Nội thành Hà Nội | W20: 22.1 | X20: 1179 | Y20: 2.33 | Z20: 1 | AA20: 1.25T | AB20: 1.25T | AC20: No | AD20: Yes | AE20: No | AF20: Yes | AG20: Hầm trung tâm thương mại | AH20: 08:30 | AI20: 10:30 | AJ20: 09:52 | AK20: 11:52 | AL20: 45 | AM20: 25 | AN20: 30 | AO20: 202 | AP20: 720000 | AQ20: 0 | AR20: 120000 | AS20: 150000 | AT20: A - SLA chặt | AU20: CR-NỘIT-05 | AV20: Hệ thống khách hàng | AW20: S1-C19 | AX20: 1.25T | AY20: Send to Clustering | AZ20: OK | BA20: Cấm tải/đường nhỏ - đã chọn xe nhỏ | BB20: =AM20+AN20 | BC20: =ROUND(W20/'03_Cost_Constraints'!$B$4*60,0) | BD20: =IF(X20<=500,"5 tạ",IF(X20<=1250,"1.25T",IF(X20<=5000,"5T",IF(X20<=8000,"8T",IF(X20<=15000,"3 chân","4 chân"))))) | BE20: =IF((BB20+BC20)<=AO20,"OK","Risk") | BF20: =IF(AND(AZ20="OK",BE20="OK"),"Ready","Review")
A21: S1 | B21: 2026-06-05 | C21: S1-ORD-020 | D21: MM Mega Market | E21: Siêu thị Hải Dương | F21: ST | G21: EXPL | H21: Bia lon Saigon Export | I21: PK_LINFOX_VSIP | J21: Kho Linfox KCN VSIP Bắc Ninh | K21: Bắc Ninh | L21: Từ Sơn | M21: 21.082707 | N21: 105.99795 | O21: DL_HD_SIEUTHI | P21: Siêu thị Hải Dương | Q21: Hải Phòng | R21: Hải Dương | S21: 20.937341 | T21: 106.31455 | U21: Đông Bắc | V21: Đông Bắc | W21: 51 | X21: 6453 | Y21: 16.2 | Z21: 13 | AA21: 8T | AB21: 8T | AC21: No | AD21: Yes | AE21: No | AF21: No | AG21: Quốc lộ 5, xe 8T vào được | AH21: 08:30 | AI21: 10:30 | AJ21: 11:08 | AK21: 13:08 | AL21: 30 | AM21: 40 | AN21: 35 | AO21: 278 | AP21: 2510000 | AQ21: 0 | AR21: 0 | AS21: 150000 | AT21: A - SLA chặt | AU21: CR-ĐÔNG-01 | AV21: Zalo/Email plan 17:00 | AW21: S1-C20 | AX21: 8T | AY21: Send to Clustering | AZ21: OK | BA21: OK | BB21: =AM21+AN21 | BC21: =ROUND(W21/'03_Cost_Constraints'!$B$4*60,0) | BD21: =IF(X21<=500,"5 tạ",IF(X21<=1250,"1.25T",IF(X21<=5000,"5T",IF(X21<=8000,"8T",IF(X21<=15000,"3 chân","4 chân"))))) | BE21: =IF((BB21+BC21)<=AO21,"OK","Risk") | BF21: =IF(AND(AZ21="OK",BE21="OK"),"Ready","Review") | BG21: Kế hoạch ngày hôm sau; cần chốt trước 19:00 và gửi tài xế sau duyệt
A22: S1 | B22: 2026-06-05 | C22: S1-ORD-021 | D22: Unilever | E22: VINMART Uông Bí | F22: ST | G22: PAT2 | H22: Bia lon 333 | I22: PK_LINFOX_VSIP | J22: Kho Linfox KCN VSIP Bắc Ninh | K22: Bắc Ninh | L22: Từ Sơn | M22: 21.082707 | N22: 105.99795 | O22: DL_QN_UONGBI | P22: VINMART Uông Bí | Q22: Quảng Ninh | R22: Uông Bí | S22: 21.031495 | T22: 106.76688 | U22: Đông Bắc | V22: Đông Bắc | W22: 105.5 | X22: 1872 | Y22: 3.67 | Z22: 3 | AA22: 5T | AB22: 8T | AC22: No | AD22: Yes | AE22: No | AF22: No | AG22: Đường tỉnh, xe 5T/8T vào được | AH22: 08:30 | AI22: 10:30 | AJ22: 13:20 | AK22: 14:50 | AL22: 45 | AM22: 40 | AN22: 35 | AO22: 380 | AP22: 1820000 | AQ22: 150000 | AR22: 0 | AS22: 80000 | AT22: C - Có thể thương lượng | AU22: CR-ĐÔNG-02 | AV22: Manual nhập điều phối | AW22: S1-C21 | AX22: 5T | AY22: Send to Clustering | AZ22: OK | BA22: Empty-run >100km cần tìm chuyến về | BB22: =AM22+AN22 | BC22: =ROUND(W22/'03_Cost_Constraints'!$B$4*60,0) | BD22: =IF(X22<=500,"5 tạ",IF(X22<=1250,"1.25T",IF(X22<=5000,"5T",IF(X22<=8000,"8T",IF(X22<=15000,"3 chân","4 chân"))))) | BE22: =IF((BB22+BC22)<=AO22,"OK","Risk") | BF22: =IF(AND(AZ22="OK",BE22="OK"),"Ready","Review")
A23: S1 | B23: 2026-06-05 | C23: S1-ORD-022 | D23: VinCommerce | E23: TOPS MARKET Garden Mall | F23: MT | G23: LVCA | H23: Bia lon Lạc Việt | I23: PK_LINFOX_VSIP | J23: Kho Linfox KCN VSIP Bắc Ninh | K23: Bắc Ninh | L23: Từ Sơn | M23: 21.082707 | N23: 105.99795 | O23: DL_HN_GARDEN | P23: TOPS MARKET Garden Mall | Q23: Hà Nội | R23: Nam Từ Liêm | S23: 21.015324 | T23: 105.77784 | U23: Nội thành Hà Nội | V23: Nội thành Hà Nội | W23: 38.4 | X23: 1345 | Y23: 3.52 | Z23: 2 | AA23: 5T | AB23: 1.25T | AC23: No | AD23: Yes | AE23: No | AF23: Yes | AG23: Khung giờ nhập kho cố định | AH23: 09:00 | AI23: 10:30 | AJ23: 12:05 | AK23: 14:05 | AL23: 45 | AM23: 40 | AN23: 45 | AO23: 305 | AP23: 690000 | AQ23: 0 | AR23: 120000 | AS23: 80000 | AT23: C - Có thể thương lượng | AU23: CR-NỘIT-03 | AV23: Excel khách hàng | AW23: S1-C22 | AX23: Split/Chuyển tải | AY23: Split Order/Chuyển tải hoặc xin xe nhỏ nhiều chuyến | AZ23: Review | BA23: Vehicle Mismatch | BB23: =AM23+AN23 | BC23: =ROUND(W23/'03_Cost_Constraints'!$B$4*60,0) | BD23: =IF(X23<=500,"5 tạ",IF(X23<=1250,"1.25T",IF(X23<=5000,"5T",IF(X23<=8000,"8T",IF(X23<=15000,"3 chân","4 chân"))))) | BE23: =IF((BB23+BC23)<=AO23,"OK","Risk") | BF23: =IF(AND(AZ23="OK",BE23="OK"),"Ready","Review")
A24: S1 | B24: 2026-06-05 | C24: S1-ORD-023 | D24: Acecook | E24: Siêu thị Hải Phòng | F24: MT | G24: EXPL | H24: Bia lon Saigon Export | I24: PK_HP_DINHVU | J24: Kho Hải Phòng - Đình Vũ | K24: Hải Phòng | L24: Hải An | M24: 20.8425 | N24: 106.77 | O24: DL_HP_SIEUTHI | P24: Siêu thị Hải Phòng | Q24: Hải Phòng | R24: Gia Viên | S24: 20.84442 | T24: 106.7011 | U24: Đông Bắc | V24: Đông Bắc | W24: 13.2 | X24: 1219 | Y24: 2.74 | Z24: 2 | AA24: 1.25T | AB24: 5T | AC24: No | AD24: Yes | AE24: No | AF24: No | AG24: Khung giờ nhập kho 13:00-16:00 | AH24: 08:00 | AI24: 10:30 | AJ24: 09:32 | AK24: 12:02 | AL24: 45 | AM24: 25 | AN24: 30 | AO24: 242 | AP24: 530000 | AQ24: 0 | AR24: 120000 | AS24: 150000 | AT24: A - SLA chặt | AU24: CR-ĐÔNG-04 | AV24: Hệ thống khách hàng | AW24: S1-C23 | AX24: 1.25T | AY24: Send to Clustering | AZ24: OK | BA24: OK | BB24: =AM24+AN24 | BC24: =ROUND(W24/'03_Cost_Constraints'!$B$4*60,0) | BD24: =IF(X24<=500,"5 tạ",IF(X24<=1250,"1.25T",IF(X24<=5000,"5T",IF(X24<=8000,"8T",IF(X24<=15000,"3 chân","4 chân"))))) | BE24: =IF((BB24+BC24)<=AO24,"OK","Risk") | BF24: =IF(AND(AZ24="OK",BE24="OK"),"Ready","Review")
A25: S1 | B25: 2026-06-05 | C25: S1-ORD-024 | D25: Acecook | E25: LOTTE MART Đống Đa | F25: MT | G25: NOODLE | H25: Mì gói/Acecook carton | I25: PK_HY_MYHAO | J25: Kho/Nhà máy khách hàng Mỹ Hào | K25: Hưng Yên | L25: Mỹ Hào | M25: 20.9329 | N25: 106.065 | O25: DL_HN_LOTTE_DD | P25: LOTTE MART Đống Đa | Q25: Hà Nội | R25: Đống Đa | S25: 21.005536 | T25: 105.82394 | U25: Nội thành Hà Nội | V25: Nội thành Hà Nội | W25: 44.3 | X25: 1402 | Y25: 8.84 | Z25: 7 | AA25: 5T | AB25: 1.25T | AC25: No | AD25: Yes | AE25: No | AF25: Yes | AG25: Hầm giao nhận, chỉ xe nhỏ/1.25T | AH25: 07:00 | AI25: 08:30 | AJ25: 10:15 | AK25: 13:15 | AL25: 45 | AM25: 40 | AN25: 45 | AO25: 375 | AP25: 1090000 | AQ25: 150000 | AR25: 120000 | AS25: 150000 | AT25: A - SLA chặt | AU25: CR-NỘIT-05 | AV25: Zalo/Email plan 17:00 | AW25: S1-C24 | AX25: Split/Chuyển tải | AY25: Split Order/Chuyển tải hoặc xin xe nhỏ nhiều chuyến | AZ25: Review | BA25: Vehicle Mismatch | BB25: =AM25+AN25 | BC25: =ROUND(W25/'03_Cost_Constraints'!$B$4*60,0) | BD25: =IF(X25<=500,"5 tạ",IF(X25<=1250,"1.25T",IF(X25<=5000,"5T",IF(X25<=8000,"8T",IF(X25<=15000,"3 chân","4 chân"))))) | BE25: =IF((BB25+BC25)<=AO25,"OK","Risk") | BF25: =IF(AND(AZ25="OK",BE25="OK"),"Ready","Review") | BG25: Kế hoạch ngày hôm sau; cần chốt trước 19:00 và gửi tài xế sau duyệt
A26: S1 | B26: 2026-06-05 | C26: S1-ORD-025 | D26: MM Mega Market | E26: VINMART Bắc Từ Liêm | F26: ST | G26: CHCA | H26: Bia lon Saigon Chill | I26: PK_LINFOX_VSIP | J26: Kho Linfox KCN VSIP Bắc Ninh | K26: Bắc Ninh | L26: Từ Sơn | M26: 21.082707 | N26: 105.99795 | O26: DL_HN_BACTULIEM | P26: VINMART Bắc Từ Liêm | Q26: Hà Nội | R26: Bắc Từ Liêm | S26: 21.052701 | T26: 105.78073 | U26: Nội thành Hà Nội | V26: Nội thành Hà Nội | W26: 40.4 | X26: 988 | Y26: 1.61 | Z26: 1 | AA26: 1.25T | AB26: 1.25T | AC26: No | AD26: Yes | AE26: No | AF26: Yes | AG26: Nội đô, khung giờ hạn chế xe tải | AH26: 09:00 | AI26: 11:30 | AJ26: 12:24 | AK26: 15:24 | AL26: 30 | AM26: 25 | AN26: 20 | AO26: 384 | AP26: 780000 | AQ26: 0 | AR26: 0 | AS26: 80000 | AT26: B - Thường | AU26: CR-NỘIT-01 | AV26: Manual nhập điều phối | AW26: S1-C25 | AX26: 1.25T | AY26: Send to Clustering | AZ26: OK | BA26: Cấm tải/đường nhỏ - đã chọn xe nhỏ | BB26: =AM26+AN26 | BC26: =ROUND(W26/'03_Cost_Constraints'!$B$4*60,0) | BD26: =IF(X26<=500,"5 tạ",IF(X26<=1250,"1.25T",IF(X26<=5000,"5T",IF(X26<=8000,"8T",IF(X26<=15000,"3 chân","4 chân"))))) | BE26: =IF((BB26+BC26)<=AO26,"OK","Risk") | BF26: =IF(AND(AZ26="OK",BE26="OK"),"Ready","Review")
A27: S1 | B27: 2026-06-05 | C27: S1-ORD-026 | D27: Linfox | E27: TOPS MARKET Garden Mall | F27: MT | G27: POSM | H27: POSM trưng bày | I27: PK_HPL_LB | J27: HPL Depot Long Biên - 20 Thạch Bàn | K27: Hà Nội | L27: Long Biên | M27: 21.026155 | N27: 105.91418 | O27: DL_HN_GARDEN | P27: TOPS MARKET Garden Mall | Q27: Hà Nội | R27: Nam Từ Liêm | S27: 21.015324 | T27: 105.77784 | U27: Nội thành Hà Nội | V27: Nội thành Hà Nội | W27: 22.5 | X27: 1043 | Y27: 22.83 | Z27: 19 | AA27: 5T | AB27: 1.25T | AC27: No | AD27: Yes | AE27: No | AF27: Yes | AG27: Khung giờ nhập kho cố định | AH27: 09:00 | AI27: 10:30 | AJ27: 10:38 | AK27: 13:08 | AL27: 45 | AM27: 40 | AN27: 45 | AO27: 248 | AP27: 710000 | AQ27: 0 | AR27: 120000 | AS27: 80000 | AT27: C - Có thể thương lượng | AU27: CR-NỘIT-02 | AV27: Excel khách hàng | AW27: S1-C26 | AX27: Split/Chuyển tải | AY27: Split Order/Chuyển tải hoặc xin xe nhỏ nhiều chuyến | AZ27: Review | BA27: Vehicle Mismatch | BB27: =AM27+AN27 | BC27: =ROUND(W27/'03_Cost_Constraints'!$B$4*60,0) | BD27: =IF(X27<=500,"5 tạ",IF(X27<=1250,"1.25T",IF(X27<=5000,"5T",IF(X27<=8000,"8T",IF(X27<=15000,"3 chân","4 chân"))))) | BE27: =IF((BB27+BC27)<=AO27,"OK","Risk") | BF27: =IF(AND(AZ27="OK",BE27="OK"),"Ready","Review")
A28: S1 | B28: 2026-06-05 | C28: S1-ORD-027 | D28: Bách Hóa Xanh | E28: Siêu thị Hải Phòng | F28: MT | G28: FMCG | H28: Hàng tiêu dùng nhanh hỗn hợp | I28: PK_HP_DINHVU | J28: Kho Hải Phòng - Đình Vũ | K28: Hải Phòng | L28: Hải An | M28: 20.8425 | N28: 106.77 | O28: DL_HP_SIEUTHI | P28: Siêu thị Hải Phòng | Q28: Hải Phòng | R28: Gia Viên | S28: 20.84442 | T28: 106.7011 | U28: Đông Bắc | V28: Đông Bắc | W28: 13.1 | X28: 1775 | Y28: 9.34 | Z28: 7 | AA28: 5T | AB28: 5T | AC28: No | AD28: Yes | AE28: No | AF28: No | AG28: Khung giờ nhập kho 13:00-16:00 | AH28: 08:00 | AI28: 10:30 | AJ28: 10:17 | AK28: 12:47 | AL28: 45 | AM28: 40 | AN28: 45 | AO28: 287 | AP28: 720000 | AQ28: 150000 | AR28: 120000 | AS28: 80000 | AT28: B - Thường | AU28: CR-ĐÔNG-03 | AV28: Hệ thống khách hàng | AW28: S1-C27 | AX28: 5T | AY28: Send to Clustering | AZ28: OK | BA28: OK | BB28: =AM28+AN28 | BC28: =ROUND(W28/'03_Cost_Constraints'!$B$4*60,0) | BD28: =IF(X28<=500,"5 tạ",IF(X28<=1250,"1.25T",IF(X28<=5000,"5T",IF(X28<=8000,"8T",IF(X28<=15000,"3 chân","4 chân"))))) | BE28: =IF((BB28+BC28)<=AO28,"OK","Risk") | BF28: =IF(AND(AZ28="OK",BE28="OK"),"Ready","Review")
A29: S1 | B29: 2026-06-05 | C29: S1-ORD-028 | D29: MM Mega Market | E29: LOTTE MART Đống Đa | F29: MT | G29: POSM | H29: POSM trưng bày | I29: PK_HPL_LB | J29: HPL Depot Long Biên - 20 Thạch Bàn | K29: Hà Nội | L29: Long Biên | M29: 21.026155 | N29: 105.91418 | O29: DL_HN_LOTTE_DD | P29: LOTTE MART Đống Đa | Q29: Hà Nội | R29: Đống Đa | S29: 21.005536 | T29: 105.82394 | U29: Nội thành Hà Nội | V29: Nội thành Hà Nội | W29: 16.1 | X29: 1438 | Y29: 37.08 | Z29: 30 | AA29: 8T | AB29: 1.25T | AC29: No | AD29: Yes | AE29: No | AF29: Yes | AG29: Hầm giao nhận, chỉ xe nhỏ/1.25T | AH29: 08:30 | AI29: 11:00 | AJ29: 09:57 | AK29: 12:27 | AL29: 30 | AM29: 40 | AN29: 45 | AO29: 237 | AP29: 700000 | AQ29: 0 | AR29: 120000 | AS29: 80000 | AT29: C - Có thể thương lượng | AU29: CR-NỘIT-04 | AV29: Zalo/Email plan 17:00 | AW29: S1-C28 | AX29: Split/Chuyển tải | AY29: Split Order/Chuyển tải hoặc xin xe nhỏ nhiều chuyến | AZ29: Review | BA29: Vehicle Mismatch | BB29: =AM29+AN29 | BC29: =ROUND(W29/'03_Cost_Constraints'!$B$4*60,0) | BD29: =IF(X29<=500,"5 tạ",IF(X29<=1250,"1.25T",IF(X29<=5000,"5T",IF(X29<=8000,"8T",IF(X29<=15000,"3 chân","4 chân"))))) | BE29: =IF((BB29+BC29)<=AO29,"OK","Risk") | BF29: =IF(AND(AZ29="OK",BE29="OK"),"Ready","Review") | BG29: Kế hoạch ngày hôm sau; cần chốt trước 19:00 và gửi tài xế sau duyệt
A30: S1 | B30: 2026-06-05 | C30: S1-ORD-029 | D30: Masan | E30: VINMART Times City | F30: MT | G30: PAT2 | H30: Bia lon 333 | I30: PK_HPL_LB | J30: HPL Depot Long Biên - 20 Thạch Bàn | K30: Hà Nội | L30: Long Biên | M30: 21.026155 | N30: 105.91418 | O30: DL_HN_TIMESCITY | P30: VINMART Times City | Q30: Hà Nội | R30: Hai Bà Trưng | S30: 20.994022 | T30: 105.86964 | U30: Nội thành Hà Nội | V30: Nội thành Hà Nội | W30: 14.4 | X30: 223 | Y30: 0.6 | Z30: 1 | AA30: 5 tạ | AB30: 1.25T | AC30: No | AD30: Yes | AE30: No | AF30: Yes | AG30: Nội khu, xe lớn hạn chế | AH30: 07:00 | AI30: 09:30 | AJ30: 08:09 | AK30: 10:39 | AL30: 30 | AM30: 25 | AN30: 30 | AO30: 219 | AP30: 610000 | AQ30: 0 | AR30: 120000 | AS30: 80000 | AT30: B - Thường | AU30: CR-NỘIT-05 | AV30: Manual nhập điều phối | AW30: S1-C02 | AX30: 5 tạ | AY30: Send to Clustering | AZ30: OK | BA30: Cấm tải/đường nhỏ - đã chọn xe nhỏ | BB30: =AM30+AN30 | BC30: =ROUND(W30/'03_Cost_Constraints'!$B$4*60,0) | BD30: =IF(X30<=500,"5 tạ",IF(X30<=1250,"1.25T",IF(X30<=5000,"5T",IF(X30<=8000,"8T",IF(X30<=15000,"3 chân","4 chân"))))) | BE30: =IF((BB30+BC30)<=AO30,"OK","Risk") | BF30: =IF(AND(AZ30="OK",BE30="OK"),"Ready","Review")
A31: S1 | B31: 2026-06-05 | C31: S1-ORD-030 | D31: Sabeco | E31: Siêu thị Hải Phòng | F31: MT | G31: LVCA | H31: Bia lon Lạc Việt | I31: PK_LINFOX_VSIP | J31: Kho Linfox KCN VSIP Bắc Ninh | K31: Bắc Ninh | L31: Từ Sơn | M31: 21.082707 | N31: 105.99795 | O31: DL_HP_SIEUTHI | P31: Siêu thị Hải Phòng | Q31: Hải Phòng | R31: Gia Viên | S31: 20.84442 | T31: 106.7011 | U31: Đông Bắc | V31: Đông Bắc | W31: 102.4 | X31: 4789 | Y31: 12.42 | Z31: 10 | AA31: 5T | AB31: 5T | AC31: No | AD31: Yes | AE31: No | AF31: No | AG31: Khung giờ nhập kho 13:00-16:00 | AH31: 08:00 | AI31: 10:30 | AJ31: 11:16 | AK31: 13:46 | AL31: 30 | AM31: 40 | AN31: 45 | AO31: 346 | AP31: 3350000 | AQ31: 150000 | AR31: 120000 | AS31: 150000 | AT31: A - SLA chặt | AU31: CR-ĐÔNG-01 | AV31: Excel khách hàng | AW31: S1-C03 | AX31: 5T | AY31: Send to Clustering | AZ31: OK | BA31: Empty-run >100km cần tìm chuyến về | BB31: =AM31+AN31 | BC31: =ROUND(W31/'03_Cost_Constraints'!$B$4*60,0) | BD31: =IF(X31<=500,"5 tạ",IF(X31<=1250,"1.25T",IF(X31<=5000,"5T",IF(X31<=8000,"8T",IF(X31<=15000,"3 chân","4 chân"))))) | BE31: =IF((BB31+BC31)<=AO31,"OK","Risk") | BF31: =IF(AND(AZ31="OK",BE31="OK"),"Ready","Review")

Sheet S2_DapUng_Du
A1: Scenario_ID | B1: Planning_Date | C1: Order_ID | D1: Customer_Group | E1: Customer_Name | F1: Channel | G1: SKU_Code | H1: Product_Group | I1: Pickup_ID | J1: Pickup_Name | K1: Pickup_Province | L1: Pickup_District | M1: Pickup_Lat | N1: Pickup_Lon | O1: Delivery_ID | P1: Delivery_Name | Q1: Delivery_Province | R1: Delivery_District | S1: Delivery_Lat | T1: Delivery_Lon | U1: Corridor | V1: Route_Axis | W1: Direct_Distance_km | X1: Weight_kg | Y1: Volume_m3 | Z1: Pallet_Qty | AA1: Min_Vehicle_Type | AB1: Max_Vehicle_Type_Allowed | AC1: Required_Refrigeration | AD1: Can_Consolidate | AE1: Dedicated_Vehicle | AF1: Inner_City_Restriction | AG1: Access_Note | AH1: Pickup_TW_Start | AI1: Pickup_TW_End | AJ1: Drop_TW_Start | AK1: Drop_TW_End | AL1: TW_Flex_Min | AM1: Pickup_Service_Min | AN1: Drop_Service_Min | AO1: Lead_Time_Min | AP1: Freight_Revenue_VND | AQ1: Extra_Stop_Fee_VND | AR1: Waiting_Fee_Chargeable_VND | AS1: Late_Penalty_VND_per_30m | AT1: Customer_Priority | AU1: Contract_Route_ID | AV1: Source_System | AW1: Seed_Cluster_ID | AX1: Suggested_Vehicle_Type | AY1: Suggested_Action | AZ1: Validation_Status | BA1: Risk_Flag | BB1: Total_Service_Min | BC1: Direct_Drive_Min | BD1: Load_Class_kg | BE1: LeadTime_Check | BF1: Algorithm_Ready_Flag | BG1: Notes
A2: S2 | B2: 2026-06-05 | C2: S2-ORD-001 | D2: Sabeco | E2: AKJUKY | F2: Đại lý | G2: EXPL | H2: Bia lon Saigon Export | I2: PK_LINFOX_VSIP | J2: Kho Linfox KCN VSIP Bắc Ninh | K2: Bắc Ninh | L2: Từ Sơn | M2: 21.082707 | N2: 105.99795 | O2: DL_HN_AKJUKY | P2: AKJUKY | Q2: Hà Nội | R2: Long Biên | S2: 21.063695 | T2: 105.88999 | U2: Nội thành Hà Nội | V2: Nội thành Hà Nội | W2: 19.8 | X2: 371 | Y2: 0.67 | Z2: 1 | AA2: 5 tạ | AB2: 1.25T | AC2: No | AD2: No | AE2: Yes | AF2: Yes | AG2: Đường nhỏ nội đô | AH2: 08:00 | AI2: 09:30 | AJ2: 09:48 | AK2: 12:48 | AL2: 30 | AM2: 25 | AN2: 20 | AO2: 288 | AP2: 480000 | AQ2: 0 | AR2: 0 | AS2: 150000 | AT2: A - SLA chặt | AU2: CR-NỘIT-02 | AV2: Manual nhập điều phối | AW2: S2-C01 | AX2: 5 tạ | AY2: Send to Clustering | AZ2: OK | BA2: Cấm tải/đường nhỏ - đã chọn xe nhỏ | BB2: =AM2+AN2 | BC2: =ROUND(W2/'03_Cost_Constraints'!$B$4*60,0) | BD2: =IF(X2<=500,"5 tạ",IF(X2<=1250,"1.25T",IF(X2<=5000,"5T",IF(X2<=8000,"8T",IF(X2<=15000,"3 chân","4 chân"))))) | BE2: =IF((BB2+BC2)<=AO2,"OK","Risk") | BF2: =IF(AND(AZ2="OK",BE2="OK"),"Ready","Review")
A3: S2 | B3: 2026-06-05 | C3: S2-ORD-002 | D3: Linfox | E3: VINMART Royal City | F3: MT | G3: PAT2 | H3: Bia lon 333 | I3: PK_HPL_LB | J3: HPL Depot Long Biên - 20 Thạch Bàn | K3: Hà Nội | L3: Long Biên | M3: 21.026155 | N3: 105.91418 | O3: DL_HN_ROYAL | P3: VINMART Royal City | Q3: Hà Nội | R3: Thanh Xuân | S3: 21.003388 | T3: 105.81621 | U3: Nội thành Hà Nội | V3: Nội thành Hà Nội | W3: 19.1 | X3: 386 | Y3: 1.11 | Z3: 1 | AA3: 5 tạ | AB3: 1.25T | AC3: No | AD3: Yes | AE3: No | AF3: Yes | AG3: Hầm trung tâm thương mại | AH3: 08:00 | AI3: 10:30 | AJ3: 09:47 | AK3: 12:17 | AL3: 45 | AM3: 25 | AN3: 30 | AO3: 257 | AP3: 830000 | AQ3: 0 | AR3: 120000 | AS3: 150000 | AT3: A - SLA chặt | AU3: CR-NỘIT-03 | AV3: Excel khách hàng | AW3: S2-C02 | AX3: 5 tạ | AY3: Send to Clustering | AZ3: OK | BA3: Cấm tải/đường nhỏ - đã chọn xe nhỏ | BB3: =AM3+AN3 | BC3: =ROUND(W3/'03_Cost_Constraints'!$B$4*60,0) | BD3: =IF(X3<=500,"5 tạ",IF(X3<=1250,"1.25T",IF(X3<=5000,"5T",IF(X3<=8000,"8T",IF(X3<=15000,"3 chân","4 chân"))))) | BE3: =IF((BB3+BC3)<=AO3,"OK","Risk") | BF3: =IF(AND(AZ3="OK",BE3="OK"),"Ready","Review")
A4: S2 | B4: 2026-06-05 | C4: S2-ORD-003 | D4: Bách Hóa Xanh | E4: Siêu thị Hải Dương | F4: ST | G4: CHCA | H4: Bia lon Saigon Chill | I4: PK_HPL_LB | J4: HPL Depot Long Biên - 20 Thạch Bàn | K4: Hà Nội | L4: Long Biên | M4: 21.026155 | N4: 105.91418 | O4: DL_HD_SIEUTHI | P4: Siêu thị Hải Dương | Q4: Hải Phòng | R4: Hải Dương | S4: 20.937341 | T4: 106.31455 | U4: Đông Bắc | V4: Đông Bắc | W4: 60.9 | X4: 1914 | Y4: 5.15 | Z4: 4 | AA4: 5T | AB4: 8T | AC4: No | AD4: Yes | AE4: No | AF4: No | AG4: Quốc lộ 5, xe 8T vào được | AH4: 08:00 | AI4: 10:30 | AJ4: 10:51 | AK4: 13:51 | AL4: 45 | AM4: 40 | AN4: 35 | AO4: 351 | AP4: 1050000 | AQ4: 150000 | AR4: 0 | AS4: 150000 | AT4: A - SLA chặt | AU4: CR-ĐÔNG-04 | AV4: Hệ thống khách hàng | AW4: S2-C03 | AX4: 5T | AY4: Send to Clustering | AZ4: OK | BA4: OK | BB4: =AM4+AN4 | BC4: =ROUND(W4/'03_Cost_Constraints'!$B$4*60,0) | BD4: =IF(X4<=500,"5 tạ",IF(X4<=1250,"1.25T",IF(X4<=5000,"5T",IF(X4<=8000,"8T",IF(X4<=15000,"3 chân","4 chân"))))) | BE4: =IF((BB4+BC4)<=AO4,"OK","Risk") | BF4: =IF(AND(AZ4="OK",BE4="OK"),"Ready","Review")
A5: S2 | B5: 2026-06-05 | C5: S2-ORD-004 | D5: MM Mega Market | E5: Thái Dương | F5: Đại lý | G5: MILK | H5: Sữa hộp carton | I5: PK_LINFOX_VSIP | J5: Kho Linfox KCN VSIP Bắc Ninh | K5: Bắc Ninh | L5: Từ Sơn | M5: 21.082707 | N5: 105.99795 | O5: DL_HN_THAIDUONG | P5: Thái Dương | Q5: Hà Nội | R5: Hà Nội | S5: 20.929215 | T5: 105.87 | U5: Nội thành Hà Nội | V5: Nội thành Hà Nội | W5: 33.6 | X5: 1286 | Y5: 2.73 | Z5: 2 | AA5: 5T | AB5: 1.25T | AC5: No | AD5: Yes | AE5: No | AF5: Yes | AG5: Đường nhỏ, ưu tiên xe <=1.25T | AH5: 08:00 | AI5: 09:30 | AJ5: 10:57 | AK5: 12:27 | AL5: 30 | AM5: 40 | AN5: 35 | AO5: 267 | AP5: 800000 | AQ5: 0 | AR5: 0 | AS5: 150000 | AT5: A - SLA chặt | AU5: CR-NỘIT-05 | AV5: Zalo/Email plan 17:00 | AW5: S2-C04 | AX5: Split/Chuyển tải | AY5: Split Order/Chuyển tải hoặc xin xe nhỏ nhiều chuyến | AZ5: Review | BA5: Vehicle Mismatch | BB5: =AM5+AN5 | BC5: =ROUND(W5/'03_Cost_Constraints'!$B$4*60,0) | BD5: =IF(X5<=500,"5 tạ",IF(X5<=1250,"1.25T",IF(X5<=5000,"5T",IF(X5<=8000,"8T",IF(X5<=15000,"3 chân","4 chân"))))) | BE5: =IF((BB5+BC5)<=AO5,"OK","Risk") | BF5: =IF(AND(AZ5="OK",BE5="OK"),"Ready","Review") | BG5: Kế hoạch ngày hôm sau; cần chốt trước 19:00 và gửi tài xế sau duyệt
A6: S2 | B6: 2026-06-05 | C6: S2-ORD-005 | D6: Masan | E6: VINMART Bắc Từ Liêm | F6: ST | G6: CHCA | H6: Bia lon Saigon Chill | I6: PK_LINFOX_VSIP | J6: Kho Linfox KCN VSIP Bắc Ninh | K6: Bắc Ninh | L6: Từ Sơn | M6: 21.082707 | N6: 105.99795 | O6: DL_HN_BACTULIEM | P6: VINMART Bắc Từ Liêm | Q6: Hà Nội | R6: Bắc Từ Liêm | S6: 21.052701 | T6: 105.78073 | U6: Nội thành Hà Nội | V6: Nội thành Hà Nội | W6: 37.4 | X6: 925 | Y6: 2.41 | Z6: 2 | AA6: 1.25T | AB6: 1.25T | AC6: No | AD6: Yes | AE6: No | AF6: Yes | AG6: Nội đô, khung giờ hạn chế xe tải | AH6: 07:30 | AI6: 09:30 | AJ6: 09:19 | AK6: 12:19 | AL6: 30 | AM6: 25 | AN6: 20 | AO6: 289 | AP6: 760000 | AQ6: 0 | AR6: 0 | AS6: 80000 | AT6: B - Thường | AU6: CR-NỘIT-01 | AV6: Manual nhập điều phối | AW6: S2-C05 | AX6: 1.25T | AY6: Send to Clustering | AZ6: OK | BA6: Cấm tải/đường nhỏ - đã chọn xe nhỏ | BB6: =AM6+AN6 | BC6: =ROUND(W6/'03_Cost_Constraints'!$B$4*60,0) | BD6: =IF(X6<=500,"5 tạ",IF(X6<=1250,"1.25T",IF(X6<=5000,"5T",IF(X6<=8000,"8T",IF(X6<=15000,"3 chân","4 chân"))))) | BE6: =IF((BB6+BC6)<=AO6,"OK","Risk") | BF6: =IF(AND(AZ6="OK",BE6="OK"),"Ready","Review")
A7: S2 | B7: 2026-06-05 | C7: S2-ORD-006 | D7: Unilever | E7: VINMART Times City | F7: MT | G7: FMCG | H7: Hàng tiêu dùng nhanh hỗn hợp | I7: PK_HY_MYHAO | J7: Kho/Nhà máy khách hàng Mỹ Hào | K7: Hưng Yên | L7: Mỹ Hào | M7: 20.9329 | N7: 106.065 | O7: DL_HN_TIMESCITY | P7: VINMART Times City | Q7: Hà Nội | R7: Hai Bà Trưng | S7: 20.994022 | T7: 105.86964 | U7: Nội thành Hà Nội | V7: Nội thành Hà Nội | W7: 38.8 | X7: 221 | Y7: 1.08 | Z7: 1 | AA7: 5 tạ | AB7: 1.25T | AC7: No | AD7: Yes | AE7: No | AF7: Yes | AG7: Nội khu, xe lớn hạn chế | AH7: 09:00 | AI7: 11:30 | AJ7: 11:51 | AK7: 13:51 | AL7: 45 | AM7: 25 | AN7: 30 | AO7: 291 | AP7: 490000 | AQ7: 150000 | AR7: 120000 | AS7: 150000 | AT7: A - SLA chặt | AU7: CR-NỘIT-02 | AV7: Excel khách hàng | AW7: S2-C06 | AX7: 5 tạ | AY7: Send to Clustering | AZ7: OK | BA7: Cấm tải/đường nhỏ - đã chọn xe nhỏ | BB7: =AM7+AN7 | BC7: =ROUND(W7/'03_Cost_Constraints'!$B$4*60,0) | BD7: =IF(X7<=500,"5 tạ",IF(X7<=1250,"1.25T",IF(X7<=5000,"5T",IF(X7<=8000,"8T",IF(X7<=15000,"3 chân","4 chân"))))) | BE7: =IF((BB7+BC7)<=AO7,"OK","Risk") | BF7: =IF(AND(AZ7="OK",BE7="OK"),"Ready","Review")
A8: S2 | B8: 2026-06-05 | C8: S2-ORD-007 | D8: Sabeco | E8: MM Hồng Bàng | F8: MT | G8: MILK | H8: Sữa hộp carton | I8: PK_HPL_LB | J8: HPL Depot Long Biên - 20 Thạch Bàn | K8: Hà Nội | L8: Long Biên | M8: 21.026155 | N8: 105.91418 | O8: DL_HP_HONGBANG | P8: MM Hồng Bàng | Q8: Hải Phòng | R8: Hồng Bàng | S8: 20.856112 | T8: 106.68224 | U8: Đông Bắc | V8: Đông Bắc | W8: 106.8 | X8: 4798 | Y8: 12.02 | Z8: 10 | AA8: 5T | AB8: 5T | AC8: No | AD8: Yes | AE8: No | AF8: No | AG8: Đường đô thị Hải Phòng, xe 5T vào được | AH8: 08:30 | AI8: 10:30 | AJ8: 13:22 | AK8: 14:52 | AL8: 30 | AM8: 40 | AN8: 45 | AO8: 382 | AP8: 3460000 | AQ8: 0 | AR8: 120000 | AS8: 150000 | AT8: A - SLA chặt | AU8: CR-ĐÔNG-03 | AV8: Hệ thống khách hàng | AW8: S2-C07 | AX8: 5T | AY8: Send to Clustering | AZ8: OK | BA8: Empty-run >100km cần tìm chuyến về | BB8: =AM8+AN8 | BC8: =ROUND(W8/'03_Cost_Constraints'!$B$4*60,0) | BD8: =IF(X8<=500,"5 tạ",IF(X8<=1250,"1.25T",IF(X8<=5000,"5T",IF(X8<=8000,"8T",IF(X8<=15000,"3 chân","4 chân"))))) | BE8: =IF((BB8+BC8)<=AO8,"OK","Risk") | BF8: =IF(AND(AZ8="OK",BE8="OK"),"Ready","Review")
A9: S2 | B9: 2026-06-05 | C9: S2-ORD-008 | D9: Acecook | E9: Thái Dương | F9: Đại lý | G9: FMCG | H9: Hàng tiêu dùng nhanh hỗn hợp | I9: PK_HY_MYHAO | J9: Kho/Nhà máy khách hàng Mỹ Hào | K9: Hưng Yên | L9: Mỹ Hào | M9: 20.9329 | N9: 106.065 | O9: DL_HN_THAIDUONG | P9: Thái Dương | Q9: Hà Nội | R9: Hà Nội | S9: 20.929215 | T9: 105.87 | U9: Nội thành Hà Nội | V9: Nội thành Hà Nội | W9: 36 | X9: 283 | Y9: 1.16 | Z9: 1 | AA9: 5 tạ | AB9: 1.25T | AC9: No | AD9: Yes | AE9: No | AF9: Yes | AG9: Đường nhỏ, ưu tiên xe <=1.25T | AH9: 08:30 | AI9: 10:30 | AJ9: 11:16 | AK9: 14:16 | AL9: 45 | AM9: 25 | AN9: 20 | AO9: 346 | AP9: 640000 | AQ9: 0 | AR9: 0 | AS9: 150000 | AT9: A - SLA chặt | AU9: CR-NỘIT-04 | AV9: Zalo/Email plan 17:00 | AW9: S2-C08 | AX9: 5 tạ | AY9: Send to Clustering | AZ9: OK | BA9: Cấm tải/đường nhỏ - đã chọn xe nhỏ | BB9: =AM9+AN9 | BC9: =ROUND(W9/'03_Cost_Constraints'!$B$4*60,0) | BD9: =IF(X9<=500,"5 tạ",IF(X9<=1250,"1.25T",IF(X9<=5000,"5T",IF(X9<=8000,"8T",IF(X9<=15000,"3 chân","4 chân"))))) | BE9: =IF((BB9+BC9)<=AO9,"OK","Risk") | BF9: =IF(AND(AZ9="OK",BE9="OK"),"Ready","Review") | BG9: Kế hoạch ngày hôm sau; cần chốt trước 19:00 và gửi tài xế sau duyệt
A10: S2 | B10: 2026-06-05 | C10: S2-ORD-009 | D10: MM Mega Market | E10: AKJUKY | F10: Đại lý | G10: SP33 | H10: Bia lon Saigon Special | I10: PK_HPL_LB | J10: HPL Depot Long Biên - 20 Thạch Bàn | K10: Hà Nội | L10: Long Biên | M10: 21.026155 | N10: 105.91418 | O10: DL_HN_AKJUKY | P10: AKJUKY | Q10: Hà Nội | R10: Long Biên | S10: 21.063695 | T10: 105.88999 | U10: Nội thành Hà Nội | V10: Nội thành Hà Nội | W10: 9.7 | X10: 387 | Y10: 0.65 | Z10: 1 | AA10: 5 tạ | AB10: 1.25T | AC10: No | AD10: Yes | AE10: No | AF10: Yes | AG10: Đường nhỏ nội đô | AH10: 07:00 | AI10: 09:30 | AJ10: 09:31 | AK10: 11:31 | AL10: 30 | AM10: 25 | AN10: 20 | AO10: 271 | AP10: 810000 | AQ10: 0 | AR10: 0 | AS10: 80000 | AT10: B - Thường | AU10: CR-NỘIT-05 | AV10: Manual nhập điều phối | AW10: S2-C08 | AX10: 5 tạ | AY10: Send to Clustering | AZ10: OK | BA10: Cấm tải/đường nhỏ - đã chọn xe nhỏ | BB10: =AM10+AN10 | BC10: =ROUND(W10/'03_Cost_Constraints'!$B$4*60,0) | BD10: =IF(X10<=500,"5 tạ",IF(X10<=1250,"1.25T",IF(X10<=5000,"5T",IF(X10<=8000,"8T",IF(X10<=15000,"3 chân","4 chân"))))) | BE10: =IF((BB10+BC10)<=AO10,"OK","Risk") | BF10: =IF(AND(AZ10="OK",BE10="OK"),"Ready","Review")
A11: S2 | B11: 2026-06-05 | C11: S2-ORD-010 | D11: Bách Hóa Xanh | E11: VINMART Vũ Trọng Phụng | F11: ST | G11: LVCA | H11: Bia lon Lạc Việt | I11: PK_LINFOX_VSIP | J11: Kho Linfox KCN VSIP Bắc Ninh | K11: Bắc Ninh | L11: Từ Sơn | M11: 21.082707 | N11: 105.99795 | O11: DL_HN_VUTRONGPHUNG | P11: VINMART Vũ Trọng Phụng | Q11: Hà Nội | R11: Thanh Xuân | S11: 20.997621 | T11: 105.80944 | U11: Nội thành Hà Nội | V11: Nội thành Hà Nội | W11: 34.5 | X11: 397 | Y11: 1.03 | Z11: 1 | AA11: 5 tạ | AB11: 1.25T | AC11: No | AD11: No | AE11: Yes | AF11: Yes | AG11: Hầm giao nhận thấp | AH11: 07:00 | AI11: 09:30 | AJ11: 09:44 | AK11: 12:14 | AL11: 45 | AM11: 25 | AN11: 20 | AO11: 314 | AP11: 510000 | AQ11: 0 | AR11: 0 | AS11: 80000 | AT11: C - Có thể thương lượng | AU11: CR-NỘIT-01 | AV11: Excel khách hàng | AW11: S2-C10 | AX11: 5 tạ | AY11: Send to Clustering | AZ11: OK | BA11: Cấm tải/đường nhỏ - đã chọn xe nhỏ | BB11: =AM11+AN11 | BC11: =ROUND(W11/'03_Cost_Constraints'!$B$4*60,0) | BD11: =IF(X11<=500,"5 tạ",IF(X11<=1250,"1.25T",IF(X11<=5000,"5T",IF(X11<=8000,"8T",IF(X11<=15000,"3 chân","4 chân"))))) | BE11: =IF((BB11+BC11)<=AO11,"OK","Risk") | BF11: =IF(AND(AZ11="OK",BE11="OK"),"Ready","Review")
A12: S2 | B12: 2026-06-05 | C12: S2-ORD-011 | D12: Bách Hóa Xanh | E12: Siêu thị Hải Dương | F12: ST | G12: LVCA | H12: Bia lon Lạc Việt | I12: PK_LINFOX_VSIP | J12: Kho Linfox KCN VSIP Bắc Ninh | K12: Bắc Ninh | L12: Từ Sơn | M12: 21.082707 | N12: 105.99795 | O12: DL_HD_SIEUTHI | P12: Siêu thị Hải Dương | Q12: Hải Phòng | R12: Hải Dương | S12: 20.937341 | T12: 106.31455 | U12: Đông Bắc | V12: Đông Bắc | W12: 52.5 | X12: 4903 | Y12: 11.58 | Z12: 9 | AA12: 5T | AB12: 8T | AC12: No | AD12: Yes | AE12: No | AF12: No | AG12: Quốc lộ 5, xe 8T vào được | AH12: 08:30 | AI12: 10:30 | AJ12: 11:10 | AK12: 14:10 | AL12: 45 | AM12: 40 | AN12: 35 | AO12: 340 | AP12: 2130000 | AQ12: 0 | AR12: 0 | AS12: 80000 | AT12: B - Thường | AU12: CR-ĐÔNG-02 | AV12: Hệ thống khách hàng | AW12: S2-C11 | AX12: 5T | AY12: Send to Clustering | AZ12: OK | BA12: OK | BB12: =AM12+AN12 | BC12: =ROUND(W12/'03_Cost_Constraints'!$B$4*60,0) | BD12: =IF(X12<=500,"5 tạ",IF(X12<=1250,"1.25T",IF(X12<=5000,"5T",IF(X12<=8000,"8T",IF(X12<=15000,"3 chân","4 chân"))))) | BE12: =IF((BB12+BC12)<=AO12,"OK","Risk") | BF12: =IF(AND(AZ12="OK",BE12="OK"),"Ready","Review")
A13: S2 | B13: 2026-06-05 | C13: S2-ORD-012 | D13: Unilever | E13: Siêu thị Ninh Bình | F13: ST | G13: NOODLE | H13: Mì gói/Acecook carton | I13: PK_NA_BACVINH | J13: Kho DC Vinh - KCN Bắc Vinh | K13: Nghệ An | L13: Vinh | M13: 18.733 | N13: 105.681 | O13: DL_NB_SIEUTHI | P13: Siêu thị Ninh Bình | Q13: Ninh Bình | R13: Hoa Lư | S13: 20.250614 | T13: 105.97445 | U13: Bắc Trung Bộ | V13: Bắc Trung Bộ | W13: 222.8 | X13: 3651 | Y13: 31.71 | Z13: 26 | AA13: 8T | AB13: 8T | AC13: No | AD13: Yes | AE13: No | AF13: No | AG13: Xe 8T vào được | AH13: 08:30 | AI13: 11:00 | AJ13: 14:57 | AK13: 17:27 | AL13: 45 | AM13: 40 | AN13: 35 | AO13: 537 | AP13: 5680000 | AQ13: 150000 | AR13: 0 | AS13: 150000 | AT13: A - SLA chặt | AU13: CR-BẮCT-03 | AV13: Zalo/Email plan 17:00 | AW13: S2-C12 | AX13: 8T | AY13: Send to Clustering | AZ13: OK | BA13: Empty-run >100km cần tìm chuyến về | BB13: =AM13+AN13 | BC13: =ROUND(W13/'03_Cost_Constraints'!$B$4*60,0) | BD13: =IF(X13<=500,"5 tạ",IF(X13<=1250,"1.25T",IF(X13<=5000,"5T",IF(X13<=8000,"8T",IF(X13<=15000,"3 chân","4 chân"))))) | BE13: =IF((BB13+BC13)<=AO13,"OK","Risk") | BF13: =IF(AND(AZ13="OK",BE13="OK"),"Ready","Review") | BG13: Kế hoạch ngày hôm sau; cần chốt trước 19:00 và gửi tài xế sau duyệt
A14: S2 | B14: 2026-06-05 | C14: S2-ORD-013 | D14: VinCommerce | E14: Thái Dương | F14: Đại lý | G14: NOODLE | H14: Mì gói/Acecook carton | I14: PK_HPL_LB | J14: HPL Depot Long Biên - 20 Thạch Bàn | K14: Hà Nội | L14: Long Biên | M14: 21.026155 | N14: 105.91418 | O14: DL_HN_THAIDUONG | P14: Thái Dương | Q14: Hà Nội | R14: Hà Nội | S14: 20.929215 | T14: 105.87 | U14: Nội thành Hà Nội | V14: Nội thành Hà Nội | W14: 23.4 | X14: 418 | Y14: 4.21 | Z14: 3 | AA14: 1.25T | AB14: 1.25T | AC14: No | AD14: Yes | AE14: No | AF14: Yes | AG14: Đường nhỏ, ưu tiên xe <=1.25T | AH14: 08:00 | AI14: 10:30 | AJ14: 10:55 | AK14: 12:25 | AL14: 45 | AM14: 25 | AN14: 20 | AO14: 265 | AP14: 840000 | AQ14: 0 | AR14: 0 | AS14: 150000 | AT14: A - SLA chặt | AU14: CR-NỘIT-04 | AV14: Manual nhập điều phối | AW14: S2-C13 | AX14: 1.25T | AY14: Send to Clustering | AZ14: OK | BA14: Cấm tải/đường nhỏ - đã chọn xe nhỏ | BB14: =AM14+AN14 | BC14: =ROUND(W14/'03_Cost_Constraints'!$B$4*60,0) | BD14: =IF(X14<=500,"5 tạ",IF(X14<=1250,"1.25T",IF(X14<=5000,"5T",IF(X14<=8000,"8T",IF(X14<=15000,"3 chân","4 chân"))))) | BE14: =IF((BB14+BC14)<=AO14,"OK","Risk") | BF14: =IF(AND(AZ14="OK",BE14="OK"),"Ready","Review")
A15: S2 | B15: 2026-06-05 | C15: S2-ORD-014 | D15: Sabeco | E15: VINMART Trung Hòa | F15: ST | G15: CHCA | H15: Bia lon Saigon Chill | I15: PK_LINFOX_VSIP | J15: Kho Linfox KCN VSIP Bắc Ninh | K15: Bắc Ninh | L15: Từ Sơn | M15: 21.082707 | N15: 105.99795 | O15: DL_HN_TRUNGHOA | P15: VINMART Trung Hòa | Q15: Hà Nội | R15: Cầu Giấy | S15: 21.007288 | T15: 105.80157 | U15: Nội thành Hà Nội | V15: Nội thành Hà Nội | W15: 36.1 | X15: 980 | Y15: 2.37 | Z15: 1 | AA15: 1.25T | AB15: 1.25T | AC15: No | AD15: Yes | AE15: No | AF15: Yes | AG15: Khung giờ giao sát, bãi giao hẹp | AH15: 07:00 | AI15: 09:30 | AJ15: 10:16 | AK15: 12:46 | AL15: 30 | AM15: 25 | AN15: 20 | AO15: 346 | AP15: 760000 | AQ15: 0 | AR15: 0 | AS15: 150000 | AT15: A - SLA chặt | AU15: CR-NỘIT-05 | AV15: Excel khách hàng | AW15: S2-C14 | AX15: 1.25T | AY15: Send to Clustering | AZ15: OK | BA15: Cấm tải/đường nhỏ - đã chọn xe nhỏ | BB15: =AM15+AN15 | BC15: =ROUND(W15/'03_Cost_Constraints'!$B$4*60,0) | BD15: =IF(X15<=500,"5 tạ",IF(X15<=1250,"1.25T",IF(X15<=5000,"5T",IF(X15<=8000,"8T",IF(X15<=15000,"3 chân","4 chân"))))) | BE15: =IF((BB15+BC15)<=AO15,"OK","Risk") | BF15: =IF(AND(AZ15="OK",BE15="OK"),"Ready","Review")
A16: S2 | B16: 2026-06-05 | C16: S2-ORD-015 | D16: Acecook | E16: VINMART Royal City | F16: MT | G16: FMCG | H16: Hàng tiêu dùng nhanh hỗn hợp | I16: PK_HPL_LB | J16: HPL Depot Long Biên - 20 Thạch Bàn | K16: Hà Nội | L16: Long Biên | M16: 21.026155 | N16: 105.91418 | O16: DL_HN_ROYAL | P16: VINMART Royal City | Q16: Hà Nội | R16: Thanh Xuân | S16: 21.003388 | T16: 105.81621 | U16: Nội thành Hà Nội | V16: Nội thành Hà Nội | W16: 21 | X16: 1391 | Y16: 5.23 | Z16: 4 | AA16: 5T | AB16: 1.25T | AC16: No | AD16: No | AE16: Yes | AF16: Yes | AG16: Hầm trung tâm thương mại | AH16: 07:00 | AI16: 09:30 | AJ16: 10:06 | AK16: 13:06 | AL16: 45 | AM16: 40 | AN16: 45 | AO16: 366 | AP16: 730000 | AQ16: 150000 | AR16: 120000 | AS16: 80000 | AT16: C - Có thể thương lượng | AU16: CR-NỘIT-01 | AV16: Hệ thống khách hàng | AW16: S2-C15 | AX16: Split/Chuyển tải | AY16: Split Order/Chuyển tải hoặc xin xe nhỏ nhiều chuyến | AZ16: Review | BA16: Vehicle Mismatch | BB16: =AM16+AN16 | BC16: =ROUND(W16/'03_Cost_Constraints'!$B$4*60,0) | BD16: =IF(X16<=500,"5 tạ",IF(X16<=1250,"1.25T",IF(X16<=5000,"5T",IF(X16<=8000,"8T",IF(X16<=15000,"3 chân","4 chân"))))) | BE16: =IF((BB16+BC16)<=AO16,"OK","Risk") | BF16: =IF(AND(AZ16="OK",BE16="OK"),"Ready","Review")
A17: S2 | B17: 2026-06-05 | C17: S2-ORD-016 | D17: Masan | E17: Siêu thị Hải Dương | F17: ST | G17: FMCG | H17: Hàng tiêu dùng nhanh hỗn hợp | I17: PK_HP_DINHVU | J17: Kho Hải Phòng - Đình Vũ | K17: Hải Phòng | L17: Hải An | M17: 20.8425 | N17: 106.77 | O17: DL_HD_SIEUTHI | P17: Siêu thị Hải Dương | Q17: Hải Phòng | R17: Hải Dương | S17: 20.937341 | T17: 106.31455 | U17: Đông Bắc | V17: Đông Bắc | W17: 69.1 | X17: 1817 | Y17: 7.07 | Z17: 5 | AA17: 5T | AB17: 8T | AC17: No | AD17: No | AE17: Yes | AF17: No | AG17: Quốc lộ 5, xe 8T vào được | AH17: 08:30 | AI17: 10:30 | AJ17: 11:02 | AK17: 14:02 | AL17: 30 | AM17: 40 | AN17: 35 | AO17: 332 | AP17: 1250000 | AQ17: 0 | AR17: 0 | AS17: 80000 | AT17: C - Có thể thương lượng | AU17: CR-ĐÔNG-02 | AV17: Zalo/Email plan 17:00 | AW17: S2-C16 | AX17: 5T | AY17: Send to Clustering | AZ17: OK | BA17: OK | BB17: =AM17+AN17 | BC17: =ROUND(W17/'03_Cost_Constraints'!$B$4*60,0) | BD17: =IF(X17<=500,"5 tạ",IF(X17<=1250,"1.25T",IF(X17<=5000,"5T",IF(X17<=8000,"8T",IF(X17<=15000,"3 chân","4 chân"))))) | BE17: =IF((BB17+BC17)<=AO17,"OK","Risk") | BF17: =IF(AND(AZ17="OK",BE17="OK"),"Ready","Review") | BG17: Kế hoạch ngày hôm sau; cần chốt trước 19:00 và gửi tài xế sau duyệt
A18: S2 | B18: 2026-06-05 | C18: S2-ORD-017 | D18: Acecook | E18: VINMART Quế Võ | F18: ST | G18: MILK | H18: Sữa hộp carton | I18: PK_HP_DINHVU | J18: Kho Hải Phòng - Đình Vũ | K18: Hải Phòng | L18: Hải An | M18: 20.8425 | N18: 106.77 | O18: DL_BN_QUEVO_01 | P18: VINMART Quế Võ | Q18: Bắc Ninh | R18: Quế Võ | S18: 21.170139 | T18: 106.1024 | U18: Đông Bắc | V18: Đông Bắc | W18: 105 | X18: 4860 | Y18: 14.62 | Z18: 12 | AA18: 5T | AB18: 8T | AC18: No | AD18: Yes | AE18: No | AF18: No | AG18: Đường rộng, xe 5T/8T vào được | AH18: 07:00 | AI18: 09:30 | AJ18: 11:20 | AK18: 13:20 | AL18: 45 | AM18: 40 | AN18: 35 | AO18: 380 | AP18: 3250000 | AQ18: 0 | AR18: 0 | AS18: 80000 | AT18: C - Có thể thương lượng | AU18: CR-ĐÔNG-03 | AV18: Manual nhập điều phối | AW18: S2-C17 | AX18: 5T | AY18: Send to Clustering | AZ18: OK | BA18: Empty-run >100km cần tìm chuyến về | BB18: =AM18+AN18 | BC18: =ROUND(W18/'03_Cost_Constraints'!$B$4*60,0) | BD18: =IF(X18<=500,"5 tạ",IF(X18<=1250,"1.25T",IF(X18<=5000,"5T",IF(X18<=8000,"8T",IF(X18<=15000,"3 chân","4 chân"))))) | BE18: =IF((BB18+BC18)<=AO18,"OK","Risk") | BF18: =IF(AND(AZ18="OK",BE18="OK"),"Ready","Review")
A19: S2 | B19: 2026-06-05 | C19: S2-ORD-018 | D19: Linfox | E19: VINMART Trung Hòa | F19: ST | G19: SP33 | H19: Bia lon Saigon Special | I19: PK_HY_MYHAO | J19: Kho/Nhà máy khách hàng Mỹ Hào | K19: Hưng Yên | L19: Mỹ Hào | M19: 20.9329 | N19: 106.065 | O19: DL_HN_TRUNGHOA | P19: VINMART Trung Hòa | Q19: Hà Nội | R19: Cầu Giấy | S19: 21.007288 | T19: 105.80157 | U19: Nội thành Hà Nội | V19: Nội thành Hà Nội | W19: 46.7 | X19: 1426 | Y19: 3.42 | Z19: 2 | AA19: 5T | AB19: 1.25T | AC19: No | AD19: Yes | AE19: No | AF19: Yes | AG19: Khung giờ giao sát, bãi giao hẹp | AH19: 09:00 | AI19: 10:30 | AJ19: 12:50 | AK19: 15:20 | AL19: 45 | AM19: 40 | AN19: 35 | AO19: 380 | AP19: 1110000 | AQ19: 0 | AR19: 0 | AS19: 80000 | AT19: B - Thường | AU19: CR-NỘIT-04 | AV19: Excel khách hàng | AW19: S2-C17 | AX19: Split/Chuyển tải | AY19: Split Order/Chuyển tải hoặc xin xe nhỏ nhiều chuyến | AZ19: Review | BA19: Vehicle Mismatch | BB19: =AM19+AN19 | BC19: =ROUND(W19/'03_Cost_Constraints'!$B$4*60,0) | BD19: =IF(X19<=500,"5 tạ",IF(X19<=1250,"1.25T",IF(X19<=5000,"5T",IF(X19<=8000,"8T",IF(X19<=15000,"3 chân","4 chân"))))) | BE19: =IF((BB19+BC19)<=AO19,"OK","Risk") | BF19: =IF(AND(AZ19="OK",BE19="OK"),"Ready","Review")
A20: S2 | B20: 2026-06-05 | C20: S2-ORD-019 | D20: Linfox | E20: VINMART Royal City | F20: MT | G20: PAT2 | H20: Bia lon 333 | I20: PK_HPL_LB | J20: HPL Depot Long Biên - 20 Thạch Bàn | K20: Hà Nội | L20: Long Biên | M20: 21.026155 | N20: 105.91418 | O20: DL_HN_ROYAL | P20: VINMART Royal City | Q20: Hà Nội | R20: Thanh Xuân | S20: 21.003388 | T20: 105.81621 | U20: Nội thành Hà Nội | V20: Nội thành Hà Nội | W20: 20.9 | X20: 803 | Y20: 2.22 | Z20: 1 | AA20: 1.25T | AB20: 1.25T | AC20: No | AD20: Yes | AE20: No | AF20: Yes | AG20: Hầm trung tâm thương mại | AH20: 08:00 | AI20: 10:00 | AJ20: 10:20 | AK20: 12:50 | AL20: 45 | AM20: 25 | AN20: 30 | AO20: 290 | AP20: 870000 | AQ20: 0 | AR20: 120000 | AS20: 80000 | AT20: C - Có thể thương lượng | AU20: CR-NỘIT-05 | AV20: Hệ thống khách hàng | AW20: S2-C19 | AX20: 1.25T | AY20: Send to Clustering | AZ20: OK | BA20: Cấm tải/đường nhỏ - đã chọn xe nhỏ | BB20: =AM20+AN20 | BC20: =ROUND(W20/'03_Cost_Constraints'!$B$4*60,0) | BD20: =IF(X20<=500,"5 tạ",IF(X20<=1250,"1.25T",IF(X20<=5000,"5T",IF(X20<=8000,"8T",IF(X20<=15000,"3 chân","4 chân"))))) | BE20: =IF((BB20+BC20)<=AO20,"OK","Risk") | BF20: =IF(AND(AZ20="OK",BE20="OK"),"Ready","Review")
A21: S2 | B21: 2026-06-05 | C21: S2-ORD-020 | D21: Unilever | E21: Siêu thị Thái Bình | F21: ST | G21: LASG | H21: Bia lon Saigon Lager 330ml | I21: PK_HPL_LB | J21: HPL Depot Long Biên - 20 Thạch Bàn | K21: Hà Nội | L21: Long Biên | M21: 21.026155 | N21: 105.91418 | O21: DL_TB_SIEUTHI | P21: Siêu thị Thái Bình | Q21: Hưng Yên | R21: Thái Bình | S21: 20.446344 | T21: 106.33658 | U21: Đông Nam Hà Nội | V21: Đông Nam Hà Nội | W21: 110.6 | X21: 3715 | Y21: 9.81 | Z21: 8 | AA21: 5T | AB21: 8T | AC21: No | AD21: Yes | AE21: No | AF21: No | AG21: Ngoại thành, xe 5T/8T | AH21: 08:00 | AI21: 10:00 | AJ21: 12:27 | AK21: 14:27 | AL21: 45 | AM21: 40 | AN21: 35 | AO21: 387 | AP21: 2730000 | AQ21: 0 | AR21: 0 | AS21: 150000 | AT21: A - SLA chặt | AU21: CR-ĐÔNG-01 | AV21: Zalo/Email plan 17:00 | AW21: S2-C20 | AX21: 5T | AY21: Send to Clustering | AZ21: OK | BA21: Empty-run >100km cần tìm chuyến về | BB21: =AM21+AN21 | BC21: =ROUND(W21/'03_Cost_Constraints'!$B$4*60,0) | BD21: =IF(X21<=500,"5 tạ",IF(X21<=1250,"1.25T",IF(X21<=5000,"5T",IF(X21<=8000,"8T",IF(X21<=15000,"3 chân","4 chân"))))) | BE21: =IF((BB21+BC21)<=AO21,"OK","Risk") | BF21: =IF(AND(AZ21="OK",BE21="OK"),"Ready","Review") | BG21: Kế hoạch ngày hôm sau; cần chốt trước 19:00 và gửi tài xế sau duyệt
A22: S2 | B22: 2026-06-05 | C22: S2-ORD-021 | D22: VinCommerce | E22: BHX Thanh Hóa - Kho DC Quảng Xương | F22: DC | G22: EXPL | H22: Bia lon Saigon Export | I22: PK_HPL_LB | J22: HPL Depot Long Biên - 20 Thạch Bàn | K22: Hà Nội | L22: Long Biên | M22: 21.026155 | N22: 105.91418 | O22: DL_TH_BHX_QX | P22: BHX Thanh Hóa - Kho DC Quảng Xương | Q22: Thanh Hóa | R22: Quảng Xương | S22: 19.731 | T22: 105.815 | U22: Bắc Trung Bộ | V22: Bắc Trung Bộ | W22: 187.4 | X22: 11928 | Y22: 33.95 | Z22: 28 | AA22: 3 chân | AB22: 3 chân | AC22: No | AD22: No | AE22: Yes | AF22: No | AG22: DC có thể nhận xe 8T/3 chân | AH22: 07:00 | AI22: 09:00 | AJ22: 14:04 | AK22: 16:04 | AL22: 45 | AM22: 120 | AN22: 90 | AO22: 544 | AP22: 14210000 | AQ22: 150000 | AR22: 0 | AS22: 150000 | AT22: A - SLA chặt | AU22: CR-BẮCT-02 | AV22: Manual nhập điều phối | AW22: S2-C21 | AX22: 3 chân | AY22: Send to Clustering | AZ22: OK | BA22: Empty-run >100km cần tìm chuyến về | BB22: =AM22+AN22 | BC22: =ROUND(W22/'03_Cost_Constraints'!$B$4*60,0) | BD22: =IF(X22<=500,"5 tạ",IF(X22<=1250,"1.25T",IF(X22<=5000,"5T",IF(X22<=8000,"8T",IF(X22<=15000,"3 chân","4 chân"))))) | BE22: =IF((BB22+BC22)<=AO22,"OK","Risk") | BF22: =IF(AND(AZ22="OK",BE22="OK"),"Ready","Review")
A23: S2 | B23: 2026-06-05 | C23: S2-ORD-022 | D23: Sabeco | E23: VINMART Bắc Từ Liêm | F23: ST | G23: PAT2 | H23: Bia lon 333 | I23: PK_LINFOX_VSIP | J23: Kho Linfox KCN VSIP Bắc Ninh | K23: Bắc Ninh | L23: Từ Sơn | M23: 21.082707 | N23: 105.99795 | O23: DL_HN_BACTULIEM | P23: VINMART Bắc Từ Liêm | Q23: Hà Nội | R23: Bắc Từ Liêm | S23: 21.052701 | T23: 105.78073 | U23: Nội thành Hà Nội | V23: Nội thành Hà Nội | W23: 38.2 | X23: 646 | Y23: 1.19 | Z23: 1 | AA23: 1.25T | AB23: 1.25T | AC23: No | AD23: Yes | AE23: No | AF23: Yes | AG23: Nội đô, khung giờ hạn chế xe tải | AH23: 08:30 | AI23: 11:00 | AJ23: 11:20 | AK23: 12:50 | AL23: 30 | AM23: 25 | AN23: 20 | AO23: 260 | AP23: 910000 | AQ23: 0 | AR23: 0 | AS23: 150000 | AT23: A - SLA chặt | AU23: CR-NỘIT-03 | AV23: Excel khách hàng | AW23: S2-C22 | AX23: 1.25T | AY23: Send to Clustering | AZ23: OK | BA23: Cấm tải/đường nhỏ - đã chọn xe nhỏ | BB23: =AM23+AN23 | BC23: =ROUND(W23/'03_Cost_Constraints'!$B$4*60,0) | BD23: =IF(X23<=500,"5 tạ",IF(X23<=1250,"1.25T",IF(X23<=5000,"5T",IF(X23<=8000,"8T",IF(X23<=15000,"3 chân","4 chân"))))) | BE23: =IF((BB23+BC23)<=AO23,"OK","Risk") | BF23: =IF(AND(AZ23="OK",BE23="OK"),"Ready","Review")
A24: S2 | B24: 2026-06-05 | C24: S2-ORD-023 | D24: Acecook | E24: VINMART Times City | F24: MT | G24: LVCA | H24: Bia lon Lạc Việt | I24: PK_HY_MYHAO | J24: Kho/Nhà máy khách hàng Mỹ Hào | K24: Hưng Yên | L24: Mỹ Hào | M24: 20.9329 | N24: 106.065 | O24: DL_HN_TIMESCITY | P24: VINMART Times City | Q24: Hà Nội | R24: Hai Bà Trưng | S24: 20.994022 | T24: 105.86964 | U24: Nội thành Hà Nội | V24: Nội thành Hà Nội | W24: 33.3 | X24: 916 | Y24: 2.09 | Z24: 1 | AA24: 1.25T | AB24: 1.25T | AC24: No | AD24: Yes | AE24: No | AF24: Yes | AG24: Nội khu, xe lớn hạn chế | AH24: 07:30 | AI24: 09:30 | AJ24: 10:42 | AK24: 13:12 | AL24: 45 | AM24: 25 | AN24: 30 | AO24: 342 | AP24: 940000 | AQ24: 0 | AR24: 120000 | AS24: 80000 | AT24: B - Thường | AU24: CR-NỘIT-04 | AV24: Hệ thống khách hàng | AW24: S2-C23 | AX24: 1.25T | AY24: Send to Clustering | AZ24: OK | BA24: Cấm tải/đường nhỏ - đã chọn xe nhỏ | BB24: =AM24+AN24 | BC24: =ROUND(W24/'03_Cost_Constraints'!$B$4*60,0) | BD24: =IF(X24<=500,"5 tạ",IF(X24<=1250,"1.25T",IF(X24<=5000,"5T",IF(X24<=8000,"8T",IF(X24<=15000,"3 chân","4 chân"))))) | BE24: =IF((BB24+BC24)<=AO24,"OK","Risk") | BF24: =IF(AND(AZ24="OK",BE24="OK"),"Ready","Review")
A25: S2 | B25: 2026-06-05 | C25: S2-ORD-024 | D25: Acecook | E25: Siêu thị Hải Phòng | F25: MT | G25: LVCA | H25: Bia lon Lạc Việt | I25: PK_HP_DINHVU | J25: Kho Hải Phòng - Đình Vũ | K25: Hải Phòng | L25: Hải An | M25: 20.8425 | N25: 106.77 | O25: DL_HP_SIEUTHI | P25: Siêu thị Hải Phòng | Q25: Hải Phòng | R25: Gia Viên | S25: 20.84442 | T25: 106.7011 | U25: Đông Bắc | V25: Đông Bắc | W25: 14.7 | X25: 4833 | Y25: 12.33 | Z25: 10 | AA25: 5T | AB25: 5T | AC25: No | AD25: Yes | AE25: No | AF25: No | AG25: Khung giờ nhập kho 13:00-16:00 | AH25: 07:30 | AI25: 10:00 | AJ25: 08:49 | AK25: 11:19 | AL25: 45 | AM25: 40 | AN25: 45 | AO25: 229 | AP25: 1160000 | AQ25: 150000 | AR25: 120000 | AS25: 80000 | AT25: B - Thường | AU25: CR-ĐÔNG-05 | AV25: Zalo/Email plan 17:00 | AW25: S2-C24 | AX25: 5T | AY25: Send to Clustering | AZ25: OK | BA25: OK | BB25: =AM25+AN25 | BC25: =ROUND(W25/'03_Cost_Constraints'!$B$4*60,0) | BD25: =IF(X25<=500,"5 tạ",IF(X25<=1250,"1.25T",IF(X25<=5000,"5T",IF(X25<=8000,"8T",IF(X25<=15000,"3 chân","4 chân"))))) | BE25: =IF((BB25+BC25)<=AO25,"OK","Risk") | BF25: =IF(AND(AZ25="OK",BE25="OK"),"Ready","Review") | BG25: Kế hoạch ngày hôm sau; cần chốt trước 19:00 và gửi tài xế sau duyệt
A26: S2 | B26: 2026-06-05 | C26: S2-ORD-025 | D26: MM Mega Market | E26: GO! Hà Nam | F26: MT | G26: POSM | H26: POSM trưng bày | I26: PK_NA_BACVINH | J26: Kho DC Vinh - KCN Bắc Vinh | K26: Nghệ An | L26: Vinh | M26: 18.733 | N26: 105.681 | O26: DL_HN_GO_HANAM | P26: GO! Hà Nam | Q26: Ninh Bình | R26: Phủ Lý | S26: 20.541 | T26: 105.913 | U26: Bắc Trung Bộ | V26: Bắc Trung Bộ | W26: 265.1 | X26: 1262 | Y26: 27.87 | Z26: 23 | AA26: 5T | AB26: 8T | AC26: No | AD26: Yes | AE26: No | AF26: No | AG26: Xe 5T/8T vào được | AH26: 09:00 | AI26: 11:30 | AJ26: 16:18 | AK26: 18:00 | AL26: 30 | AM26: 40 | AN26: 45 | AO26: 540 | AP26: 2450000 | AQ26: 0 | AR26: 120000 | AS26: 150000 | AT26: A - SLA chặt | AU26: CR-BẮCT-01 | AV26: Manual nhập điều phối | AW26: S2-C25 | AX26: 5T | AY26: Send to Clustering | AZ26: OK | BA26: Empty-run >100km cần tìm chuyến về | BB26: =AM26+AN26 | BC26: =ROUND(W26/'03_Cost_Constraints'!$B$4*60,0) | BD26: =IF(X26<=500,"5 tạ",IF(X26<=1250,"1.25T",IF(X26<=5000,"5T",IF(X26<=8000,"8T",IF(X26<=15000,"3 chân","4 chân"))))) | BE26: =IF((BB26+BC26)<=AO26,"OK","Risk") | BF26: =IF(AND(AZ26="OK",BE26="OK"),"Ready","Review")
A27: S2 | B27: 2026-06-05 | C27: S2-ORD-026 | D27: Bách Hóa Xanh | E27: LOTTE MART Ba Đình | F27: MT | G27: NOODLE | H27: Mì gói/Acecook carton | I27: PK_HPL_LB | J27: HPL Depot Long Biên - 20 Thạch Bàn | K27: Hà Nội | L27: Long Biên | M27: 21.026155 | N27: 105.91418 | O27: DL_HN_LOTTE_BD | P27: LOTTE MART Ba Đình | Q27: Hà Nội | R27: Ba Đình | S27: 21.032177 | T27: 105.81244 | U27: Nội thành Hà Nội | V27: Nội thành Hà Nội | W27: 22.1 | X27: 396 | Y27: 3.53 | Z27: 2 | AA27: 5 tạ | AB27: 1.25T | AC27: No | AD27: Yes | AE27: No | AF27: Yes | AG27: Giờ cấm tải, ưu tiên xe 1.25T | AH27: 08:30 | AI27: 10:00 | AJ27: 09:52 | AK27: 11:52 | AL27: 45 | AM27: 25 | AN27: 30 | AO27: 202 | AP27: 840000 | AQ27: 0 | AR27: 120000 | AS27: 150000 | AT27: A - SLA chặt | AU27: CR-NỘIT-02 | AV27: Excel khách hàng | AW27: S2-C26 | AX27: 5 tạ | AY27: Send to Clustering | AZ27: OK | BA27: Cấm tải/đường nhỏ - đã chọn xe nhỏ | BB27: =AM27+AN27 | BC27: =ROUND(W27/'03_Cost_Constraints'!$B$4*60,0) | BD27: =IF(X27<=500,"5 tạ",IF(X27<=1250,"1.25T",IF(X27<=5000,"5T",IF(X27<=8000,"8T",IF(X27<=15000,"3 chân","4 chân"))))) | BE27: =IF((BB27+BC27)<=AO27,"OK","Risk") | BF27: =IF(AND(AZ27="OK",BE27="OK"),"Ready","Review")
A28: S2 | B28: 2026-06-05 | C28: S2-ORD-027 | D28: Bách Hóa Xanh | E28: TOPS MARKET Garden Mall | F28: MT | G28: POSM | H28: POSM trưng bày | I28: PK_HY_MYHAO | J28: Kho/Nhà máy khách hàng Mỹ Hào | K28: Hưng Yên | L28: Mỹ Hào | M28: 20.9329 | N28: 106.065 | O28: DL_HN_GARDEN | P28: TOPS MARKET Garden Mall | Q28: Hà Nội | R28: Nam Từ Liêm | S28: 21.015324 | T28: 105.77784 | U28: Nội thành Hà Nội | V28: Nội thành Hà Nội | W28: 50.4 | X28: 1146 | Y28: 30.76 | Z28: 25 | AA28: 8T | AB28: 1.25T | AC28: No | AD28: Yes | AE28: No | AF28: Yes | AG28: Khung giờ nhập kho cố định | AH28: 07:00 | AI28: 09:00 | AJ28: 10:26 | AK28: 13:26 | AL28: 45 | AM28: 40 | AN28: 45 | AO28: 386 | AP28: 870000 | AQ28: 0 | AR28: 120000 | AS28: 150000 | AT28: A - SLA chặt | AU28: CR-NỘIT-03 | AV28: Hệ thống khách hàng | AW28: S2-C26 | AX28: Split/Chuyển tải | AY28: Split Order/Chuyển tải hoặc xin xe nhỏ nhiều chuyến | AZ28: Review | BA28: Vehicle Mismatch | BB28: =AM28+AN28 | BC28: =ROUND(W28/'03_Cost_Constraints'!$B$4*60,0) | BD28: =IF(X28<=500,"5 tạ",IF(X28<=1250,"1.25T",IF(X28<=5000,"5T",IF(X28<=8000,"8T",IF(X28<=15000,"3 chân","4 chân"))))) | BE28: =IF((BB28+BC28)<=AO28,"OK","Risk") | BF28: =IF(AND(AZ28="OK",BE28="OK"),"Ready","Review")
A29: S2 | B29: 2026-06-05 | C29: S2-ORD-028 | D29: MM Mega Market | E29: MM Hồng Bàng | F29: MT | G29: SP33 | H29: Bia lon Saigon Special | I29: PK_LINFOX_VSIP | J29: Kho Linfox KCN VSIP Bắc Ninh | K29: Bắc Ninh | L29: Từ Sơn | M29: 21.082707 | N29: 105.99795 | O29: DL_HP_HONGBANG | P29: MM Hồng Bàng | Q29: Hải Phòng | R29: Hồng Bàng | S29: 20.856112 | T29: 106.68224 | U29: Đông Bắc | V29: Đông Bắc | W29: 101.3 | X29: 6527 | Y29: 14.58 | Z29: 12 | AA29: 8T | AB29: 5T | AC29: No | AD29: Yes | AE29: No | AF29: No | AG29: Đường đô thị Hải Phòng, xe 5T vào được | AH29: 09:00 | AI29: 10:30 | AJ29: 12:15 | AK29: 14:45 | AL29: 30 | AM29: 40 | AN29: 45 | AO29: 345 | AP29: 3880000 | AQ29: 0 | AR29: 120000 | AS29: 150000 | AT29: A - SLA chặt | AU29: CR-ĐÔNG-04 | AV29: Zalo/Email plan 17:00 | AW29: S2-C28 | AX29: Split/Chuyển tải | AY29: Split Order/Chuyển tải hoặc xin xe nhỏ nhiều chuyến | AZ29: Review | BA29: Vehicle Mismatch | BB29: =AM29+AN29 | BC29: =ROUND(W29/'03_Cost_Constraints'!$B$4*60,0) | BD29: =IF(X29<=500,"5 tạ",IF(X29<=1250,"1.25T",IF(X29<=5000,"5T",IF(X29<=8000,"8T",IF(X29<=15000,"3 chân","4 chân"))))) | BE29: =IF((BB29+BC29)<=AO29,"OK","Risk") | BF29: =IF(AND(AZ29="OK",BE29="OK"),"Ready","Review") | BG29: Kế hoạch ngày hôm sau; cần chốt trước 19:00 và gửi tài xế sau duyệt
A30: S2 | B30: 2026-06-05 | C30: S2-ORD-029 | D30: Bách Hóa Xanh | E30: Siêu thị Thái Bình | F30: ST | G30: POSM | H30: POSM trưng bày | I30: PK_HPL_LB | J30: HPL Depot Long Biên - 20 Thạch Bàn | K30: Hà Nội | L30: Long Biên | M30: 21.026155 | N30: 105.91418 | O30: DL_TB_SIEUTHI | P30: Siêu thị Thái Bình | Q30: Hưng Yên | R30: Thái Bình | S30: 20.446344 | T30: 106.33658 | U30: Đông Nam Hà Nội | V30: Đông Nam Hà Nội | W30: 112.4 | X30: 7813 | Y30: 193.56 | Z30: 161 | AA30: Container | AB30: 8T | AC30: No | AD30: Yes | AE30: No | AF30: No | AG30: Ngoại thành, xe 5T/8T | AH30: 08:00 | AI30: 09:30 | AJ30: 13:49 | AK30: 15:19 | AL30: 45 | AM30: 120 | AN30: 90 | AO30: 439 | AP30: 5160000 | AQ30: 0 | AR30: 0 | AS30: 80000 | AT30: B - Thường | AU30: CR-ĐÔNG-05 | AV30: Manual nhập điều phối | AW30: S2-C29 | AX30: Split/Chuyển tải | AY30: Split Order/Chuyển tải hoặc xin xe nhỏ nhiều chuyến | AZ30: Review | BA30: Vehicle Mismatch | BB30: =AM30+AN30 | BC30: =ROUND(W30/'03_Cost_Constraints'!$B$4*60,0) | BD30: =IF(X30<=500,"5 tạ",IF(X30<=1250,"1.25T",IF(X30<=5000,"5T",IF(X30<=8000,"8T",IF(X30<=15000,"3 chân","4 chân"))))) | BE30: =IF((BB30+BC30)<=AO30,"OK","Risk") | BF30: =IF(AND(AZ30="OK",BE30="OK"),"Ready","Review")
A31: S2 | B31: 2026-06-05 | C31: S2-ORD-030 | D31: Sabeco | E31: Nam Dương | F31: Đại lý | G31: PAT2 | H31: Bia lon 333 | I31: PK_HPL_LB | J31: HPL Depot Long Biên - 20 Thạch Bàn | K31: Hà Nội | L31: Long Biên | M31: 21.026155 | N31: 105.91418 | O31: DL_HN_NAMDUONG | P31: Nam Dương | Q31: Hà Nội | R31: Hà Nội | S31: 21.062911 | T31: 105.83235 | U31: Nội thành Hà Nội | V31: Nội thành Hà Nội | W31: 21.6 | X31: 565 | Y31: 1.27 | Z31: 1 | AA31: 1.25T | AB31: 1.25T | AC31: No | AD31: Yes | AE31: No | AF31: Yes | AG31: Đường nội đô, có khung giờ cấm tải | AH31: 08:00 | AI31: 09:30 | AJ31: 10:52 | AK31: 13:52 | AL31: 30 | AM31: 25 | AN31: 20 | AO31: 352 | AP31: 500000 | AQ31: 150000 | AR31: 0 | AS31: 80000 | AT31: B - Thường | AU31: CR-NỘIT-01 | AV31: Excel khách hàng | AW31: S2-C30 | AX31: 1.25T | AY31: Send to Clustering | AZ31: OK | BA31: Cấm tải/đường nhỏ - đã chọn xe nhỏ | BB31: =AM31+AN31 | BC31: =ROUND(W31/'03_Cost_Constraints'!$B$4*60,0) | BD31: =IF(X31<=500,"5 tạ",IF(X31<=1250,"1.25T",IF(X31<=5000,"5T",IF(X31<=8000,"8T",IF(X31<=15000,"3 chân","4 chân"))))) | BE31: =IF((BB31+BC31)<=AO31,"OK","Risk") | BF31: =IF(AND(AZ31="OK",BE31="OK"),"Ready","Review")
A32: S2 | B32: 2026-06-05 | C32: S2-ORD-031 | D32: Masan | E32: VINMART Võ Thị Sáu | F32: ST | G32: LVCA | H32: Bia lon Lạc Việt | I32: PK_HY_MYHAO | J32: Kho/Nhà máy khách hàng Mỹ Hào | K32: Hưng Yên | L32: Mỹ Hào | M32: 20.9329 | N32: 106.065 | O32: DL_HN_VOTHISAU | P32: VINMART Võ Thị Sáu | Q32: Hà Nội | R32: Hai Bà Trưng | S32: 21.00441 | T32: 105.85515 | U32: Nội thành Hà Nội | V32: Nội thành Hà Nội | W32: 36.8 | X32: 339 | Y32: 0.82 | Z32: 1 | AA32: 5 tạ | AB32: 1.25T | AC32: No | AD32: Yes | AE32: No | AF32: Yes | AG32: Giờ cấm tải, xe <=1.25T | AH32: 08:30 | AI32: 10:00 | AJ32: 10:48 | AK32: 12:48 | AL32: 30 | AM32: 25 | AN32: 20 | AO32: 258 | AP32: 850000 | AQ32: 0 | AR32: 0 | AS32: 150000 | AT32: A - SLA chặt | AU32: CR-NỘIT-02 | AV32: Hệ thống khách hàng | AW32: S2-C31 | AX32: 5 tạ | AY32: Send to Clustering | AZ32: OK | BA32: Cấm tải/đường nhỏ - đã chọn xe nhỏ | BB32: =AM32+AN32 | BC32: =ROUND(W32/'03_Cost_Constraints'!$B$4*60,0) | BD32: =IF(X32<=500,"5 tạ",IF(X32<=1250,"1.25T",IF(X32<=5000,"5T",IF(X32<=8000,"8T",IF(X32<=15000,"3 chân","4 chân"))))) | BE32: =IF((BB32+BC32)<=AO32,"OK","Risk") | BF32: =IF(AND(AZ32="OK",BE32="OK"),"Ready","Review")
A33: S2 | B33: 2026-06-05 | C33: S2-ORD-032 | D33: Acecook | E33: TOPS MARKET ParkCity | F33: MT | G33: LVCA | H33: Bia lon Lạc Việt | I33: PK_HPL_LB | J33: HPL Depot Long Biên - 20 Thạch Bàn | K33: Hà Nội | L33: Long Biên | M33: 21.026155 | N33: 105.91418 | O33: DL_HN_PARKCITY | P33: TOPS MARKET ParkCity | Q33: Hà Nội | R33: Hà Đông | S33: 20.965724 | T33: 105.75614 | U33: Nội thành Hà Nội | V33: Nội thành Hà Nội | W33: 31.5 | X33: 508 | Y33: 1.28 | Z33: 1 | AA33: 1.25T | AB33: 1.25T | AC33: No | AD33: Yes | AE33: No | AF33: Yes | AG33: Bãi giao giới hạn chiều cao | AH33: 07:30 | AI33: 10:00 | AJ33: 09:39 | AK33: 12:09 | AL33: 45 | AM33: 25 | AN33: 30 | AO33: 279 | AP33: 670000 | AQ33: 0 | AR33: 120000 | AS33: 80000 | AT33: B - Thường | AU33: CR-NỘIT-03 | AV33: Zalo/Email plan 17:00 | AW33: S2-C32 | AX33: 1.25T | AY33: Send to Clustering | AZ33: OK | BA33: Cấm tải/đường nhỏ - đã chọn xe nhỏ | BB33: =AM33+AN33 | BC33: =ROUND(W33/'03_Cost_Constraints'!$B$4*60,0) | BD33: =IF(X33<=500,"5 tạ",IF(X33<=1250,"1.25T",IF(X33<=5000,"5T",IF(X33<=8000,"8T",IF(X33<=15000,"3 chân","4 chân"))))) | BE33: =IF((BB33+BC33)<=AO33,"OK","Risk") | BF33: =IF(AND(AZ33="OK",BE33="OK"),"Ready","Review") | BG33: Kế hoạch ngày hôm sau; cần chốt trước 19:00 và gửi tài xế sau duyệt
A34: S2 | B34: 2026-06-05 | C34: S2-ORD-033 | D34: Linfox | E34: Siêu thị Ninh Bình | F34: ST | G34: EXPL | H34: Bia lon Saigon Export | I34: PK_HPL_LB | J34: HPL Depot Long Biên - 20 Thạch Bàn | K34: Hà Nội | L34: Long Biên | M34: 21.026155 | N34: 105.91418 | O34: DL_NB_SIEUTHI | P34: Siêu thị Ninh Bình | Q34: Ninh Bình | R34: Hoa Lư | S34: 20.250614 | T34: 105.97445 | U34: Bắc Trung Bộ | V34: Bắc Trung Bộ | W34: 114 | X34: 4842 | Y34: 10.99 | Z34: 9 | AA34: 5T | AB34: 8T | AC34: No | AD34: Yes | AE34: No | AF34: No | AG34: Xe 8T vào được | AH34: 07:00 | AI34: 09:30 | AJ34: 12:02 | AK34: 15:02 | AL34: 45 | AM34: 40 | AN34: 35 | AO34: 482 | AP34: 3320000 | AQ34: 150000 | AR34: 0 | AS34: 80000 | AT34: C - Có thể thương lượng | AU34: CR-BẮCT-04 | AV34: Manual nhập điều phối | AW34: S2-C33 | AX34: 5T | AY34: Send to Clustering | AZ34: OK | BA34: Empty-run >100km cần tìm chuyến về | BB34: =AM34+AN34 | BC34: =ROUND(W34/'03_Cost_Constraints'!$B$4*60,0) | BD34: =IF(X34<=500,"5 tạ",IF(X34<=1250,"1.25T",IF(X34<=5000,"5T",IF(X34<=8000,"8T",IF(X34<=15000,"3 chân","4 chân"))))) | BE34: =IF((BB34+BC34)<=AO34,"OK","Risk") | BF34: =IF(AND(AZ34="OK",BE34="OK"),"Ready","Review")
A35: S2 | B35: 2026-06-05 | C35: S2-ORD-034 | D35: Acecook | E35: VINMART Quế Võ | F35: ST | G35: CHCA | H35: Bia lon Saigon Chill | I35: PK_HP_DINHVU | J35: Kho Hải Phòng - Đình Vũ | K35: Hải Phòng | L35: Hải An | M35: 20.8425 | N35: 106.77 | O35: DL_BN_QUEVO_01 | P35: VINMART Quế Võ | Q35: Bắc Ninh | R35: Quế Võ | S35: 21.170139 | T35: 106.1024 | U35: Đông Bắc | V35: Đông Bắc | W35: 104 | X35: 3522 | Y35: 8 | Z35: 6 | AA35: 5T | AB35: 8T | AC35: No | AD35: Yes | AE35: No | AF35: No | AG35: Đường rộng, xe 5T/8T vào được | AH35: 08:30 | AI35: 10:30 | AJ35: 13:18 | AK35: 16:18 | AL35: 45 | AM35: 40 | AN35: 35 | AO35: 468 | AP35: 2500000 | AQ35: 0 | AR35: 0 | AS35: 80000 | AT35: B - Thường | AU35: CR-ĐÔNG-05 | AV35: Excel khách hàng | AW35: S2-C34 | AX35: 5T | AY35: Send to Clustering | AZ35: OK | BA35: Empty-run >100km cần tìm chuyến về | BB35: =AM35+AN35 | BC35: =ROUND(W35/'03_Cost_Constraints'!$B$4*60,0) | BD35: =IF(X35<=500,"5 tạ",IF(X35<=1250,"1.25T",IF(X35<=5000,"5T",IF(X35<=8000,"8T",IF(X35<=15000,"3 chân","4 chân"))))) | BE35: =IF((BB35+BC35)<=AO35,"OK","Risk") | BF35: =IF(AND(AZ35="OK",BE35="OK"),"Ready","Review")
A36: S2 | B36: 2026-06-05 | C36: S2-ORD-035 | D36: Bách Hóa Xanh | E36: LOTTE MART Cầu Giấy | F36: MT | G36: FMCG | H36: Hàng tiêu dùng nhanh hỗn hợp | I36: PK_HPL_LB | J36: HPL Depot Long Biên - 20 Thạch Bàn | K36: Hà Nội | L36: Long Biên | M36: 21.026155 | N36: 105.91418 | O36: DL_HN_LOTTE_CG | P36: LOTTE MART Cầu Giấy | Q36: Hà Nội | R36: Cầu Giấy | S36: 21.035513 | T36: 105.79406 | U36: Nội thành Hà Nội | V36: Nội thành Hà Nội | W36: 23.4 | X36: 1445 | Y36: 7.19 | Z36: 5 | AA36: 5T | AB36: 1.25T | AC36: No | AD36: Yes | AE36: No | AF36: Yes | AG36: Khung giờ nhập kho cố định | AH36: 07:30 | AI36: 09:00 | AJ36: 10:10 | AK36: 13:10 | AL36: 45 | AM36: 40 | AN36: 45 | AO36: 340 | AP36: 600000 | AQ36: 0 | AR36: 120000 | AS36: 80000 | AT36: C - Có thể thương lượng | AU36: CR-NỘIT-01 | AV36: Hệ thống khách hàng | AW36: S2-C35 | AX36: Split/Chuyển tải | AY36: Split Order/Chuyển tải hoặc xin xe nhỏ nhiều chuyến | AZ36: Review | BA36: Vehicle Mismatch | BB36: =AM36+AN36 | BC36: =ROUND(W36/'03_Cost_Constraints'!$B$4*60,0) | BD36: =IF(X36<=500,"5 tạ",IF(X36<=1250,"1.25T",IF(X36<=5000,"5T",IF(X36<=8000,"8T",IF(X36<=15000,"3 chân","4 chân"))))) | BE36: =IF((BB36+BC36)<=AO36,"OK","Risk") | BF36: =IF(AND(AZ36="OK",BE36="OK"),"Ready","Review")
A37: S2 | B37: 2026-06-05 | C37: S2-ORD-036 | D37: Unilever | E37: VINMART Times City | F37: MT | G37: NOODLE | H37: Mì gói/Acecook carton | I37: PK_LINFOX_VSIP | J37: Kho Linfox KCN VSIP Bắc Ninh | K37: Bắc Ninh | L37: Từ Sơn | M37: 21.082707 | N37: 105.99795 | O37: DL_HN_TIMESCITY | P37: VINMART Times City | Q37: Hà Nội | R37: Hai Bà Trưng | S37: 20.994022 | T37: 105.86964 | U37: Nội thành Hà Nội | V37: Nội thành Hà Nội | W37: 28.9 | X37: 1006 | Y37: 7.73 | Z37: 6 | AA37: 1.25T | AB37: 1.25T | AC37: No | AD37: Yes | AE37: No | AF37: Yes | AG37: Nội khu, xe lớn hạn chế | AH37: 08:00 | AI37: 10:00 | AJ37: 10:34 | AK37: 12:34 | AL37: 45 | AM37: 25 | AN37: 30 | AO37: 274 | AP37: 930000 | AQ37: 0 | AR37: 120000 | AS37: 80000 | AT37: B - Thường | AU37: CR-NỘIT-02 | AV37: Zalo/Email plan 17:00 | AW37: S2-C35 | AX37: 1.25T | AY37: Send to Clustering | AZ37: OK | BA37: Cấm tải/đường nhỏ - đã chọn xe nhỏ | BB37: =AM37+AN37 | BC37: =ROUND(W37/'03_Cost_Constraints'!$B$4*60,0) | BD37: =IF(X37<=500,"5 tạ",IF(X37<=1250,"1.25T",IF(X37<=5000,"5T",IF(X37<=8000,"8T",IF(X37<=15000,"3 chân","4 chân"))))) | BE37: =IF((BB37+BC37)<=AO37,"OK","Risk") | BF37: =IF(AND(AZ37="OK",BE37="OK"),"Ready","Review") | BG37: Kế hoạch ngày hôm sau; cần chốt trước 19:00 và gửi tài xế sau duyệt
A38: S2 | B38: 2026-06-05 | C38: S2-ORD-037 | D38: VinCommerce | E38: MM Hồng Bàng | F38: MT | G38: FMCG | H38: Hàng tiêu dùng nhanh hỗn hợp | I38: PK_LINFOX_VSIP | J38: Kho Linfox KCN VSIP Bắc Ninh | K38: Bắc Ninh | L38: Từ Sơn | M38: 21.082707 | N38: 105.99795 | O38: DL_HP_HONGBANG | P38: MM Hồng Bàng | Q38: Hải Phòng | R38: Hồng Bàng | S38: 20.856112 | T38: 106.68224 | U38: Đông Bắc | V38: Đông Bắc | W38: 102.4 | X38: 6467 | Y38: 25.04 | Z38: 20 | AA38: 8T | AB38: 5T | AC38: No | AD38: Yes | AE38: No | AF38: No | AG38: Đường đô thị Hải Phòng, xe 5T vào được | AH38: 08:00 | AI38: 10:30 | AJ38: 12:16 | AK38: 14:46 | AL38: 45 | AM38: 40 | AN38: 45 | AO38: 406 | AP38: 4040000 | AQ38: 0 | AR38: 120000 | AS38: 80000 | AT38: C - Có thể thương lượng | AU38: CR-ĐÔNG-03 | AV38: Manual nhập điều phối | AW38: S2-C37 | AX38: Split/Chuyển tải | AY38: Split Order/Chuyển tải hoặc xin xe nhỏ nhiều chuyến | AZ38: Review | BA38: Vehicle Mismatch | BB38: =AM38+AN38 | BC38: =ROUND(W38/'03_Cost_Constraints'!$B$4*60,0) | BD38: =IF(X38<=500,"5 tạ",IF(X38<=1250,"1.25T",IF(X38<=5000,"5T",IF(X38<=8000,"8T",IF(X38<=15000,"3 chân","4 chân"))))) | BE38: =IF((BB38+BC38)<=AO38,"OK","Risk") | BF38: =IF(AND(AZ38="OK",BE38="OK"),"Ready","Review")
A39: S2 | B39: 2026-06-05 | C39: S2-ORD-038 | D39: Sabeco | E39: GO! Hà Nam | F39: MT | G39: SP33 | H39: Bia lon Saigon Special | I39: PK_NA_BACVINH | J39: Kho DC Vinh - KCN Bắc Vinh | K39: Nghệ An | L39: Vinh | M39: 18.733 | N39: 105.681 | O39: DL_HN_GO_HANAM | P39: GO! Hà Nam | Q39: Ninh Bình | R39: Phủ Lý | S39: 20.541 | T39: 105.913 | U39: Bắc Trung Bộ | V39: Bắc Trung Bộ | W39: 263.9 | X39: 2506 | Y39: 4.08 | Z39: 3 | AA39: 5T | AB39: 8T | AC39: No | AD39: Yes | AE39: No | AF39: No | AG39: Xe 5T/8T vào được | AH39: 07:00 | AI39: 09:00 | AJ39: 13:16 | AK39: 15:16 | AL39: 30 | AM39: 40 | AN39: 45 | AO39: 496 | AP39: 4760000 | AQ39: 0 | AR39: 120000 | AS39: 80000 | AT39: B - Thường | AU39: CR-BẮCT-04 | AV39: Excel khách hàng | AW39: S2-C38 | AX39: 5T | AY39: Send to Clustering | AZ39: OK | BA39: Empty-run >100km cần tìm chuyến về | BB39: =AM39+AN39 | BC39: =ROUND(W39/'03_Cost_Constraints'!$B$4*60,0) | BD39: =IF(X39<=500,"5 tạ",IF(X39<=1250,"1.25T",IF(X39<=5000,"5T",IF(X39<=8000,"8T",IF(X39<=15000,"3 chân","4 chân"))))) | BE39: =IF((BB39+BC39)<=AO39,"OK","Risk") | BF39: =IF(AND(AZ39="OK",BE39="OK"),"Ready","Review")
A40: S2 | B40: 2026-06-05 | C40: S2-ORD-039 | D40: Sabeco | E40: VINMART Uông Bí | F40: ST | G40: SP33 | H40: Bia lon Saigon Special | I40: PK_HP_DINHVU | J40: Kho Hải Phòng - Đình Vũ | K40: Hải Phòng | L40: Hải An | M40: 20.8425 | N40: 106.77 | O40: DL_QN_UONGBI | P40: VINMART Uông Bí | Q40: Quảng Ninh | R40: Uông Bí | S40: 21.031495 | T40: 106.76688 | U40: Đông Bắc | V40: Đông Bắc | W40: 33.1 | X40: 2471 | Y40: 7.1 | Z40: 5 | AA40: 5T | AB40: 8T | AC40: No | AD40: Yes | AE40: No | AF40: No | AG40: Đường tỉnh, xe 5T/8T vào được | AH40: 08:30 | AI40: 11:00 | AJ40: 10:14 | AK40: 13:14 | AL40: 30 | AM40: 40 | AN40: 35 | AO40: 284 | AP40: 870000 | AQ40: 150000 | AR40: 0 | AS40: 80000 | AT40: C - Có thể thương lượng | AU40: CR-ĐÔNG-05 | AV40: Hệ thống khách hàng | AW40: S2-C39 | AX40: 5T | AY40: Send to Clustering | AZ40: OK | BA40: OK | BB40: =AM40+AN40 | BC40: =ROUND(W40/'03_Cost_Constraints'!$B$4*60,0) | BD40: =IF(X40<=500,"5 tạ",IF(X40<=1250,"1.25T",IF(X40<=5000,"5T",IF(X40<=8000,"8T",IF(X40<=15000,"3 chân","4 chân"))))) | BE40: =IF((BB40+BC40)<=AO40,"OK","Risk") | BF40: =IF(AND(AZ40="OK",BE40="OK"),"Ready","Review")
A41: S2 | B41: 2026-06-05 | C41: S2-ORD-040 | D41: Linfox | E41: VINMART Times City | F41: MT | G41: LASG | H41: Bia lon Saigon Lager 330ml | I41: PK_LINFOX_VSIP | J41: Kho Linfox KCN VSIP Bắc Ninh | K41: Bắc Ninh | L41: Từ Sơn | M41: 21.082707 | N41: 105.99795 | O41: DL_HN_TIMESCITY | P41: VINMART Times City | Q41: Hà Nội | R41: Hai Bà Trưng | S41: 20.994022 | T41: 105.86964 | U41: Nội thành Hà Nội | V41: Nội thành Hà Nội | W41: 27.6 | X41: 455 | Y41: 0.84 | Z41: 1 | AA41: 5 tạ | AB41: 1.25T | AC41: No | AD41: Yes | AE41: No | AF41: Yes | AG41: Nội khu, xe lớn hạn chế | AH41: 08:30 | AI41: 10:00 | AJ41: 11:02 | AK41: 13:32 | AL41: 45 | AM41: 25 | AN41: 30 | AO41: 302 | AP41: 500000 | AQ41: 0 | AR41: 120000 | AS41: 80000 | AT41: B - Thường | AU41: CR-NỘIT-01 | AV41: Zalo/Email plan 17:00 | AW41: S2-C40 | AX41: 5 tạ | AY41: Send to Clustering | AZ41: OK | BA41: Cấm tải/đường nhỏ - đã chọn xe nhỏ | BB41: =AM41+AN41 | BC41: =ROUND(W41/'03_Cost_Constraints'!$B$4*60,0) | BD41: =IF(X41<=500,"5 tạ",IF(X41<=1250,"1.25T",IF(X41<=5000,"5T",IF(X41<=8000,"8T",IF(X41<=15000,"3 chân","4 chân"))))) | BE41: =IF((BB41+BC41)<=AO41,"OK","Risk") | BF41: =IF(AND(AZ41="OK",BE41="OK"),"Ready","Review") | BG41: Kế hoạch ngày hôm sau; cần chốt trước 19:00 và gửi tài xế sau duyệt
A42: S2 | B42: 2026-06-05 | C42: S2-ORD-041 | D42: Linfox | E42: VINMART Phạm Ngọc Thạch | F42: ST | G42: LVCA | H42: Bia lon Lạc Việt | I42: PK_HY_MYHAO | J42: Kho/Nhà máy khách hàng Mỹ Hào | K42: Hưng Yên | L42: Mỹ Hào | M42: 20.9329 | N42: 106.065 | O42: DL_HN_PNT | P42: VINMART Phạm Ngọc Thạch | Q42: Hà Nội | R42: Đống Đa | S42: 21.006268 | T42: 105.83193 | U42: Nội thành Hà Nội | V42: Nội thành Hà Nội | W42: 39.2 | X42: 1130 | Y42: 2.33 | Z42: 1 | AA42: 1.25T | AB42: 1.25T | AC42: No | AD42: Yes | AE42: No | AF42: Yes | AG42: Đường đông, cần giao đúng slot | AH42: 08:00 | AI42: 09:30 | AJ42: 11:22 | AK42: 12:52 | AL42: 45 | AM42: 25 | AN42: 20 | AO42: 292 | AP42: 800000 | AQ42: 0 | AR42: 0 | AS42: 150000 | AT42: A - SLA chặt | AU42: CR-NỘIT-02 | AV42: Manual nhập điều phối | AW42: S2-C02 | AX42: 1.25T | AY42: Send to Clustering | AZ42: OK | BA42: Cấm tải/đường nhỏ - đã chọn xe nhỏ | BB42: =AM42+AN42 | BC42: =ROUND(W42/'03_Cost_Constraints'!$B$4*60,0) | BD42: =IF(X42<=500,"5 tạ",IF(X42<=1250,"1.25T",IF(X42<=5000,"5T",IF(X42<=8000,"8T",IF(X42<=15000,"3 chân","4 chân"))))) | BE42: =IF((BB42+BC42)<=AO42,"OK","Risk") | BF42: =IF(AND(AZ42="OK",BE42="OK"),"Ready","Review")
A43: S2 | B43: 2026-06-05 | C43: S2-ORD-042 | D43: Acecook | E43: Siêu thị Thái Bình | F43: ST | G43: PAT2 | H43: Bia lon 333 | I43: PK_HPL_LB | J43: HPL Depot Long Biên - 20 Thạch Bàn | K43: Hà Nội | L43: Long Biên | M43: 21.026155 | N43: 105.91418 | O43: DL_TB_SIEUTHI | P43: Siêu thị Thái Bình | Q43: Hưng Yên | R43: Thái Bình | S43: 20.446344 | T43: 106.33658 | U43: Đông Nam Hà Nội | V43: Đông Nam Hà Nội | W43: 109.8 | X43: 2498 | Y43: 6.61 | Z43: 5 | AA43: 5T | AB43: 8T | AC43: No | AD43: Yes | AE43: No | AF43: No | AG43: Ngoại thành, xe 5T/8T | AH43: 08:30 | AI43: 10:30 | AJ43: 11:56 | AK43: 14:26 | AL43: 45 | AM43: 40 | AN43: 35 | AO43: 356 | AP43: 2020000 | AQ43: 150000 | AR43: 0 | AS43: 80000 | AT43: C - Có thể thương lượng | AU43: CR-ĐÔNG-03 | AV43: Excel khách hàng | AW43: S2-C03 | AX43: 5T | AY43: Send to Clustering | AZ43: OK | BA43: Empty-run >100km cần tìm chuyến về | BB43: =AM43+AN43 | BC43: =ROUND(W43/'03_Cost_Constraints'!$B$4*60,0) | BD43: =IF(X43<=500,"5 tạ",IF(X43<=1250,"1.25T",IF(X43<=5000,"5T",IF(X43<=8000,"8T",IF(X43<=15000,"3 chân","4 chân"))))) | BE43: =IF((BB43+BC43)<=AO43,"OK","Risk") | BF43: =IF(AND(AZ43="OK",BE43="OK"),"Ready","Review")
A44: S2 | B44: 2026-06-05 | C44: S2-ORD-043 | D44: Bách Hóa Xanh | E44: Thái Dương | F44: Đại lý | G44: LVCA | H44: Bia lon Lạc Việt | I44: PK_HPL_LB | J44: HPL Depot Long Biên - 20 Thạch Bàn | K44: Hà Nội | L44: Long Biên | M44: 21.026155 | N44: 105.91418 | O44: DL_HN_THAIDUONG | P44: Thái Dương | Q44: Hà Nội | R44: Hà Nội | S44: 20.929215 | T44: 105.87 | U44: Nội thành Hà Nội | V44: Nội thành Hà Nội | W44: 21.5 | X44: 1070 | Y44: 2.13 | Z44: 1 | AA44: 1.25T | AB44: 1.25T | AC44: No | AD44: Yes | AE44: No | AF44: Yes | AG44: Đường nhỏ, ưu tiên xe <=1.25T | AH44: 07:00 | AI44: 08:30 | AJ44: 09:21 | AK44: 10:51 | AL44: 45 | AM44: 25 | AN44: 20 | AO44: 231 | AP44: 550000 | AQ44: 0 | AR44: 0 | AS44: 150000 | AT44: A - SLA chặt | AU44: CR-NỘIT-04 | AV44: Hệ thống khách hàng | AW44: S2-C04 | AX44: 1.25T | AY44: Send to Clustering | AZ44: OK | BA44: Cấm tải/đường nhỏ - đã chọn xe nhỏ | BB44: =AM44+AN44 | BC44: =ROUND(W44/'03_Cost_Constraints'!$B$4*60,0) | BD44: =IF(X44<=500,"5 tạ",IF(X44<=1250,"1.25T",IF(X44<=5000,"5T",IF(X44<=8000,"8T",IF(X44<=15000,"3 chân","4 chân"))))) | BE44: =IF((BB44+BC44)<=AO44,"OK","Risk") | BF44: =IF(AND(AZ44="OK",BE44="OK"),"Ready","Review")
A45: S2 | B45: 2026-06-05 | C45: S2-ORD-044 | D45: Unilever | E45: VINMART Vũ Trọng Phụng | F45: ST | G45: NOODLE | H45: Mì gói/Acecook carton | I45: PK_HPL_LB | J45: HPL Depot Long Biên - 20 Thạch Bàn | K45: Hà Nội | L45: Long Biên | M45: 21.026155 | N45: 105.91418 | O45: DL_HN_VUTRONGPHUNG | P45: VINMART Vũ Trọng Phụng | Q45: Hà Nội | R45: Thanh Xuân | S45: 20.997621 | T45: 105.80944 | U45: Nội thành Hà Nội | V45: Nội thành Hà Nội | W45: 21.2 | X45: 1169 | Y45: 12.57 | Z45: 10 | AA45: 5T | AB45: 1.25T | AC45: No | AD45: Yes | AE45: No | AF45: Yes | AG45: Hầm giao nhận thấp | AH45: 08:30 | AI45: 10:30 | AJ45: 11:36 | AK45: 14:36 | AL45: 45 | AM45: 40 | AN45: 35 | AO45: 366 | AP45: 910000 | AQ45: 0 | AR45: 0 | AS45: 80000 | AT45: B - Thường | AU45: CR-NỘIT-05 | AV45: Zalo/Email plan 17:00 | AW45: S2-C05 | AX45: Split/Chuyển tải | AY45: Split Order/Chuyển tải hoặc xin xe nhỏ nhiều chuyến | AZ45: Review | BA45: Vehicle Mismatch | BB45: =AM45+AN45 | BC45: =ROUND(W45/'03_Cost_Constraints'!$B$4*60,0) | BD45: =IF(X45<=500,"5 tạ",IF(X45<=1250,"1.25T",IF(X45<=5000,"5T",IF(X45<=8000,"8T",IF(X45<=15000,"3 chân","4 chân"))))) | BE45: =IF((BB45+BC45)<=AO45,"OK","Risk") | BF45: =IF(AND(AZ45="OK",BE45="OK"),"Ready","Review") | BG45: Kế hoạch ngày hôm sau; cần chốt trước 19:00 và gửi tài xế sau duyệt

Sheet S3_Thieu_NangLuc
A1: Scenario_ID | B1: Planning_Date | C1: Order_ID | D1: Customer_Group | E1: Customer_Name | F1: Channel | G1: SKU_Code | H1: Product_Group | I1: Pickup_ID | J1: Pickup_Name | K1: Pickup_Province | L1: Pickup_District | M1: Pickup_Lat | N1: Pickup_Lon | O1: Delivery_ID | P1: Delivery_Name | Q1: Delivery_Province | R1: Delivery_District | S1: Delivery_Lat | T1: Delivery_Lon | U1: Corridor | V1: Route_Axis | W1: Direct_Distance_km | X1: Weight_kg | Y1: Volume_m3 | Z1: Pallet_Qty | AA1: Min_Vehicle_Type | AB1: Max_Vehicle_Type_Allowed | AC1: Required_Refrigeration | AD1: Can_Consolidate | AE1: Dedicated_Vehicle | AF1: Inner_City_Restriction | AG1: Access_Note | AH1: Pickup_TW_Start | AI1: Pickup_TW_End | AJ1: Drop_TW_Start | AK1: Drop_TW_End | AL1: TW_Flex_Min | AM1: Pickup_Service_Min | AN1: Drop_Service_Min | AO1: Lead_Time_Min | AP1: Freight_Revenue_VND | AQ1: Extra_Stop_Fee_VND | AR1: Waiting_Fee_Chargeable_VND | AS1: Late_Penalty_VND_per_30m | AT1: Customer_Priority | AU1: Contract_Route_ID | AV1: Source_System | AW1: Seed_Cluster_ID | AX1: Suggested_Vehicle_Type | AY1: Suggested_Action | AZ1: Validation_Status | BA1: Risk_Flag | BB1: Total_Service_Min | BC1: Direct_Drive_Min | BD1: Load_Class_kg | BE1: LeadTime_Check | BF1: Algorithm_Ready_Flag | BG1: Notes
A2: S3 | B2: 2026-06-05 | C2: S3-ORD-001 | D2: Linfox | E2: VINMART Võ Thị Sáu | F2: ST | G2: CHCA | H2: Bia lon Saigon Chill | I2: PK_LINFOX_VSIP | J2: Kho Linfox KCN VSIP Bắc Ninh | K2: Bắc Ninh | L2: Từ Sơn | M2: 21.082707 | N2: 105.99795 | O2: DL_HN_VOTHISAU | P2: VINMART Võ Thị Sáu | Q2: Hà Nội | R2: Hai Bà Trưng | S2: 21.00441 | T2: 105.85515 | U2: Nội thành Hà Nội | V2: Nội thành Hà Nội | W2: 26.9 | X2: 497 | Y2: 0.9 | Z2: 1 | AA2: 5 tạ | AB2: 1.25T | AC2: No | AD2: Yes | AE2: No | AF2: Yes | AG2: Giờ cấm tải, xe <=1.25T | AH2: 07:00 | AI2: 09:00 | AJ2: 08:31 | AK2: 11:31 | AL2: 45 | AM2: 25 | AN2: 20 | AO2: 271 | AP2: 510000 | AQ2: 0 | AR2: 0 | AS2: 80000 | AT2: B - Thường | AU2: CR-NỘIT-02 | AV2: Manual nhập điều phối | AW2: S3-C01 | AX2: 5 tạ | AY2: Send to Clustering | AZ2: OK | BA2: Cấm tải/đường nhỏ - đã chọn xe nhỏ | BB2: =AM2+AN2 | BC2: =ROUND(W2/'03_Cost_Constraints'!$B$4*60,0) | BD2: =IF(X2<=500,"5 tạ",IF(X2<=1250,"1.25T",IF(X2<=5000,"5T",IF(X2<=8000,"8T",IF(X2<=15000,"3 chân","4 chân"))))) | BE2: =IF((BB2+BC2)<=AO2,"OK","Risk") | BF2: =IF(AND(AZ2="OK",BE2="OK"),"Ready","Review")
A3: S3 | B3: 2026-06-05 | C3: S3-ORD-002 | D3: MM Mega Market | E3: VINMART Royal City | F3: MT | G3: LVCA | H3: Bia lon Lạc Việt | I3: PK_LINFOX_VSIP | J3: Kho Linfox KCN VSIP Bắc Ninh | K3: Bắc Ninh | L3: Từ Sơn | M3: 21.082707 | N3: 105.99795 | O3: DL_HN_ROYAL | P3: VINMART Royal City | Q3: Hà Nội | R3: Thanh Xuân | S3: 21.003388 | T3: 105.81621 | U3: Nội thành Hà Nội | V3: Nội thành Hà Nội | W3: 36.9 | X3: 481 | Y3: 1.21 | Z3: 1 | AA3: 5 tạ | AB3: 1.25T | AC3: No | AD3: Yes | AE3: No | AF3: Yes | AG3: Hầm trung tâm thương mại | AH3: 07:30 | AI3: 10:00 | AJ3: 10:18 | AK3: 11:48 | AL3: 30 | AM3: 25 | AN3: 30 | AO3: 258 | AP3: 530000 | AQ3: 0 | AR3: 120000 | AS3: 80000 | AT3: C - Có thể thương lượng | AU3: CR-NỘIT-03 | AV3: Excel khách hàng | AW3: S3-C02 | AX3: 5 tạ | AY3: Send to Clustering | AZ3: OK | BA3: Cấm tải/đường nhỏ - đã chọn xe nhỏ | BB3: =AM3+AN3 | BC3: =ROUND(W3/'03_Cost_Constraints'!$B$4*60,0) | BD3: =IF(X3<=500,"5 tạ",IF(X3<=1250,"1.25T",IF(X3<=5000,"5T",IF(X3<=8000,"8T",IF(X3<=15000,"3 chân","4 chân"))))) | BE3: =IF((BB3+BC3)<=AO3,"OK","Risk") | BF3: =IF(AND(AZ3="OK",BE3="OK"),"Ready","Review")
A4: S3 | B4: 2026-06-05 | C4: S3-ORD-003 | D4: VinCommerce | E4: MM Hạ Long | F4: MT | G4: NOODLE | H4: Mì gói/Acecook carton | I4: PK_HPL_LB | J4: HPL Depot Long Biên - 20 Thạch Bàn | K4: Hà Nội | L4: Long Biên | M4: 21.026155 | N4: 105.91418 | O4: DL_QN_HALONG | P4: MM Hạ Long | Q4: Quảng Ninh | R4: Hạ Long | S4: 20.95129 | T4: 107.08008 | U4: Đông Bắc | V4: Đông Bắc | W4: 161.6 | X4: 6568 | Y4: 49.49 | Z4: 41 | AA4: 3 chân | AB4: 8T | AC4: No | AD4: Yes | AE4: No | AF4: No | AG4: Đường ven biển, xe 8T vào được | AH4: 09:00 | AI4: 11:00 | AJ4: 15:03 | AK4: 16:33 | AL4: 45 | AM4: 120 | AN4: 100 | AO4: 453 | AP4: 6960000 | AQ4: 150000 | AR4: 120000 | AS4: 80000 | AT4: B - Thường | AU4: CR-ĐÔNG-04 | AV4: Hệ thống khách hàng | AW4: S3-C03 | AX4: Split/Chuyển tải | AY4: Split Order/Chuyển tải hoặc xin xe nhỏ nhiều chuyến | AZ4: Review | BA4: Vehicle Mismatch | BB4: =AM4+AN4 | BC4: =ROUND(W4/'03_Cost_Constraints'!$B$4*60,0) | BD4: =IF(X4<=500,"5 tạ",IF(X4<=1250,"1.25T",IF(X4<=5000,"5T",IF(X4<=8000,"8T",IF(X4<=15000,"3 chân","4 chân"))))) | BE4: =IF((BB4+BC4)<=AO4,"OK","Risk") | BF4: =IF(AND(AZ4="OK",BE4="OK"),"Ready","Review")
A5: S3 | B5: 2026-06-05 | C5: S3-ORD-004 | D5: Unilever | E5: Siêu thị Thanh Hóa | F5: MT | G5: CHCA | H5: Bia lon Saigon Chill | I5: PK_TH_QX | J5: Kho DC Thanh Hóa - Quảng Xương | K5: Thanh Hóa | L5: Quảng Xương | M5: 19.731 | N5: 105.815 | O5: DL_TH_SIEUTHI | P5: Siêu thị Thanh Hóa | Q5: Thanh Hóa | R5: Hạc Thành | S5: 19.8076 | T5: 105.77639 | U5: Bắc Trung Bộ | V5: Bắc Trung Bộ | W5: 19.6 | X5: 10489 | Y5: 23.77 | Z5: 19 | AA5: 3 chân | AB5: 5T | AC5: No | AD5: Yes | AE5: No | AF5: No | AG5: Đường đô thị, xe 5T vào được | AH5: 07:00 | AI5: 09:00 | AJ5: 10:46 | AK5: 12:46 | AL5: 45 | AM5: 120 | AN5: 100 | AO5: 346 | AP5: 1510000 | AQ5: 0 | AR5: 120000 | AS5: 150000 | AT5: A - SLA chặt | AU5: CR-BẮCT-05 | AV5: Zalo/Email plan 17:00 | AW5: S3-C04 | AX5: Split/Chuyển tải | AY5: Split Order/Chuyển tải hoặc xin xe nhỏ nhiều chuyến | AZ5: Review | BA5: Vehicle Mismatch | BB5: =AM5+AN5 | BC5: =ROUND(W5/'03_Cost_Constraints'!$B$4*60,0) | BD5: =IF(X5<=500,"5 tạ",IF(X5<=1250,"1.25T",IF(X5<=5000,"5T",IF(X5<=8000,"8T",IF(X5<=15000,"3 chân","4 chân"))))) | BE5: =IF((BB5+BC5)<=AO5,"OK","Risk") | BF5: =IF(AND(AZ5="OK",BE5="OK"),"Ready","Review") | BG5: Kế hoạch ngày hôm sau; cần chốt trước 19:00 và gửi tài xế sau duyệt
A6: S3 | B6: 2026-06-05 | C6: S3-ORD-005 | D6: VinCommerce | E6: LOTTE MART Ba Đình | F6: MT | G6: FMCG | H6: Hàng tiêu dùng nhanh hỗn hợp | I6: PK_HY_MYHAO | J6: Kho/Nhà máy khách hàng Mỹ Hào | K6: Hưng Yên | L6: Mỹ Hào | M6: 20.9329 | N6: 106.065 | O6: DL_HN_LOTTE_BD | P6: LOTTE MART Ba Đình | Q6: Hà Nội | R6: Ba Đình | S6: 21.032177 | T6: 105.81244 | U6: Nội thành Hà Nội | V6: Nội thành Hà Nội | W6: 47.8 | X6: 1455 | Y6: 6.44 | Z6: 5 | AA6: 5T | AB6: 1.25T | AC6: No | AD6: Yes | AE6: No | AF6: Yes | AG6: Giờ cấm tải, ưu tiên xe 1.25T | AH6: 08:30 | AI6: 10:00 | AJ6: 09:51 | AK6: 12:21 | AL6: 45 | AM6: 40 | AN6: 45 | AO6: 231 | AP6: 920000 | AQ6: 0 | AR6: 120000 | AS6: 80000 | AT6: B - Thường | AU6: CR-NỘIT-01 | AV6: Manual nhập điều phối | AW6: S3-C05 | AX6: Split/Chuyển tải | AY6: Split Order/Chuyển tải hoặc xin xe nhỏ nhiều chuyến | AZ6: Review | BA6: Vehicle Mismatch | BB6: =AM6+AN6 | BC6: =ROUND(W6/'03_Cost_Constraints'!$B$4*60,0) | BD6: =IF(X6<=500,"5 tạ",IF(X6<=1250,"1.25T",IF(X6<=5000,"5T",IF(X6<=8000,"8T",IF(X6<=15000,"3 chân","4 chân"))))) | BE6: =IF((BB6+BC6)<=AO6,"OK","Risk") | BF6: =IF(AND(AZ6="OK",BE6="OK"),"Ready","Review") | BG6: Lead time hẹp, cần cảnh báo hoặc xin nới giờ
A7: S3 | B7: 2026-06-05 | C7: S3-ORD-006 | D7: Unilever | E7: VINMART Võ Thị Sáu | F7: ST | G7: MILK | H7: Sữa hộp carton | I7: PK_HY_MYHAO | J7: Kho/Nhà máy khách hàng Mỹ Hào | K7: Hưng Yên | L7: Mỹ Hào | M7: 20.9329 | N7: 106.065 | O7: DL_HN_VOTHISAU | P7: VINMART Võ Thị Sáu | Q7: Hà Nội | R7: Hai Bà Trưng | S7: 21.00441 | T7: 105.85515 | U7: Nội thành Hà Nội | V7: Nội thành Hà Nội | W7: 40.5 | X7: 642 | Y7: 1.64 | Z7: 1 | AA7: 1.25T | AB7: 1.25T | AC7: No | AD7: Yes | AE7: No | AF7: Yes | AG7: Giờ cấm tải, xe <=1.25T | AH7: 08:30 | AI7: 10:00 | AJ7: 11:54 | AK7: 13:54 | AL7: 45 | AM7: 25 | AN7: 20 | AO7: 324 | AP7: 570000 | AQ7: 150000 | AR7: 0 | AS7: 150000 | AT7: A - SLA chặt | AU7: CR-NỘIT-02 | AV7: Excel khách hàng | AW7: S3-C06 | AX7: 1.25T | AY7: Send to Clustering | AZ7: OK | BA7: Cấm tải/đường nhỏ - đã chọn xe nhỏ | BB7: =AM7+AN7 | BC7: =ROUND(W7/'03_Cost_Constraints'!$B$4*60,0) | BD7: =IF(X7<=500,"5 tạ",IF(X7<=1250,"1.25T",IF(X7<=5000,"5T",IF(X7<=8000,"8T",IF(X7<=15000,"3 chân","4 chân"))))) | BE7: =IF((BB7+BC7)<=AO7,"OK","Risk") | BF7: =IF(AND(AZ7="OK",BE7="OK"),"Ready","Review")
A8: S3 | B8: 2026-06-05 | C8: S3-ORD-007 | D8: Unilever | E8: VINMART Royal City | F8: MT | G8: SP33 | H8: Bia lon Saigon Special | I8: PK_HY_MYHAO | J8: Kho/Nhà máy khách hàng Mỹ Hào | K8: Hưng Yên | L8: Mỹ Hào | M8: 20.9329 | N8: 106.065 | O8: DL_HN_ROYAL | P8: VINMART Royal City | Q8: Hà Nội | R8: Thanh Xuân | S8: 21.003388 | T8: 105.81621 | U8: Nội thành Hà Nội | V8: Nội thành Hà Nội | W8: 41.5 | X8: 400 | Y8: 0.71 | Z8: 1 | AA8: 5 tạ | AB8: 1.25T | AC8: No | AD8: Yes | AE8: No | AF8: Yes | AG8: Hầm trung tâm thương mại | AH8: 07:30 | AI8: 10:00 | AJ8: 10:26 | AK8: 12:26 | AL8: 45 | AM8: 25 | AN8: 30 | AO8: 296 | AP8: 670000 | AQ8: 0 | AR8: 120000 | AS8: 80000 | AT8: C - Có thể thương lượng | AU8: CR-NỘIT-03 | AV8: Hệ thống khách hàng | AW8: S3-C07 | AX8: 5 tạ | AY8: Send to Clustering | AZ8: OK | BA8: Cấm tải/đường nhỏ - đã chọn xe nhỏ | BB8: =AM8+AN8 | BC8: =ROUND(W8/'03_Cost_Constraints'!$B$4*60,0) | BD8: =IF(X8<=500,"5 tạ",IF(X8<=1250,"1.25T",IF(X8<=5000,"5T",IF(X8<=8000,"8T",IF(X8<=15000,"3 chân","4 chân"))))) | BE8: =IF((BB8+BC8)<=AO8,"OK","Risk") | BF8: =IF(AND(AZ8="OK",BE8="OK"),"Ready","Review")
A9: S3 | B9: 2026-06-05 | C9: S3-ORD-008 | D9: Masan | E9: Siêu thị Ninh Bình | F9: ST | G9: POSM | H9: POSM trưng bày | I9: PK_HPL_LB | J9: HPL Depot Long Biên - 20 Thạch Bàn | K9: Hà Nội | L9: Long Biên | M9: 21.026155 | N9: 105.91418 | O9: DL_NB_SIEUTHI | P9: Siêu thị Ninh Bình | Q9: Ninh Bình | R9: Hoa Lư | S9: 20.250614 | T9: 105.97445 | U9: Bắc Trung Bộ | V9: Bắc Trung Bộ | W9: 112.5 | X9: 7895 | Y9: 151.81 | Z9: 126 | AA9: Container | AB9: 8T | AC9: No | AD9: Yes | AE9: No | AF9: No | AG9: Xe 8T vào được | AH9: 07:00 | AI9: 08:30 | AJ9: 11:50 | AK9: 14:50 | AL9: 30 | AM9: 120 | AN9: 90 | AO9: 470 | AP9: 5410000 | AQ9: 0 | AR9: 0 | AS9: 80000 | AT9: B - Thường | AU9: CR-BẮCT-04 | AV9: Zalo/Email plan 17:00 | AW9: S3-C08 | AX9: Split/Chuyển tải | AY9: Split Order/Chuyển tải hoặc xin xe nhỏ nhiều chuyến | AZ9: Review | BA9: Vehicle Mismatch | BB9: =AM9+AN9 | BC9: =ROUND(W9/'03_Cost_Constraints'!$B$4*60,0) | BD9: =IF(X9<=500,"5 tạ",IF(X9<=1250,"1.25T",IF(X9<=5000,"5T",IF(X9<=8000,"8T",IF(X9<=15000,"3 chân","4 chân"))))) | BE9: =IF((BB9+BC9)<=AO9,"OK","Risk") | BF9: =IF(AND(AZ9="OK",BE9="OK"),"Ready","Review") | BG9: Kế hoạch ngày hôm sau; cần chốt trước 19:00 và gửi tài xế sau duyệt
A10: S3 | B10: 2026-06-05 | C10: S3-ORD-009 | D10: Sabeco | E10: Minh Tuấn | F10: Đại lý | G10: EXPL | H10: Bia lon Saigon Export | I10: PK_LINFOX_VSIP | J10: Kho Linfox KCN VSIP Bắc Ninh | K10: Bắc Ninh | L10: Từ Sơn | M10: 21.082707 | N10: 105.99795 | O10: DL_HN_MINHTUAN | P10: Minh Tuấn | Q10: Hà Nội | R10: Hà Nội | S10: 20.954079 | T10: 105.83725 | U10: Nội thành Hà Nội | V10: Nội thành Hà Nội | W10: 39.6 | X10: 730 | Y10: 1.55 | Z10: 1 | AA10: 1.25T | AB10: 1.25T | AC10: No | AD10: Yes | AE10: No | AF10: Yes | AG10: Đường nhỏ, dây điện thấp | AH10: 08:00 | AI10: 10:00 | AJ10: 10:52 | AK10: 13:22 | AL10: 30 | AM10: 25 | AN10: 20 | AO10: 322 | AP10: 730000 | AQ10: 150000 | AR10: 0 | AS10: 80000 | AT10: C - Có thể thương lượng | AU10: CR-NỘIT-05 | AV10: Manual nhập điều phối | AW10: S3-C09 | AX10: 1.25T | AY10: Send to Clustering | AZ10: OK | BA10: Cấm tải/đường nhỏ - đã chọn xe nhỏ | BB10: =AM10+AN10 | BC10: =ROUND(W10/'03_Cost_Constraints'!$B$4*60,0) | BD10: =IF(X10<=500,"5 tạ",IF(X10<=1250,"1.25T",IF(X10<=5000,"5T",IF(X10<=8000,"8T",IF(X10<=15000,"3 chân","4 chân"))))) | BE10: =IF((BB10+BC10)<=AO10,"OK","Risk") | BF10: =IF(AND(AZ10="OK",BE10="OK"),"Ready","Review")
A11: S3 | B11: 2026-06-05 | C11: S3-ORD-010 | D11: Bách Hóa Xanh | E11: AKJUKY | F11: Đại lý | G11: PAT2 | H11: Bia lon 333 | I11: PK_LINFOX_VSIP | J11: Kho Linfox KCN VSIP Bắc Ninh | K11: Bắc Ninh | L11: Từ Sơn | M11: 21.082707 | N11: 105.99795 | O11: DL_HN_AKJUKY | P11: AKJUKY | Q11: Hà Nội | R11: Long Biên | S11: 21.063695 | T11: 105.88999 | U11: Nội thành Hà Nội | V11: Nội thành Hà Nội | W11: 19.6 | X11: 1566 | Y11: 4 | Z11: 3 | AA11: 5T | AB11: 1.25T | AC11: No | AD11: Yes | AE11: No | AF11: Yes | AG11: Đường nhỏ nội đô | AH11: 07:00 | AI11: 09:00 | AJ11: 10:03 | AK11: 13:03 | AL11: 45 | AM11: 40 | AN11: 35 | AO11: 363 | AP11: 940000 | AQ11: 0 | AR11: 0 | AS11: 80000 | AT11: C - Có thể thương lượng | AU11: CR-NỘIT-01 | AV11: Excel khách hàng | AW11: S3-C10 | AX11: Split/Chuyển tải | AY11: Split Order/Chuyển tải hoặc xin xe nhỏ nhiều chuyến | AZ11: Review | BA11: Vehicle Mismatch | BB11: =AM11+AN11 | BC11: =ROUND(W11/'03_Cost_Constraints'!$B$4*60,0) | BD11: =IF(X11<=500,"5 tạ",IF(X11<=1250,"1.25T",IF(X11<=5000,"5T",IF(X11<=8000,"8T",IF(X11<=15000,"3 chân","4 chân"))))) | BE11: =IF((BB11+BC11)<=AO11,"OK","Risk") | BF11: =IF(AND(AZ11="OK",BE11="OK"),"Ready","Review")
A12: S3 | B12: 2026-06-05 | C12: S3-ORD-011 | D12: VinCommerce | E12: VINMART Phạm Ngọc Thạch | F12: ST | G12: LVCA | H12: Bia lon Lạc Việt | I12: PK_LINFOX_VSIP | J12: Kho Linfox KCN VSIP Bắc Ninh | K12: Bắc Ninh | L12: Từ Sơn | M12: 21.082707 | N12: 105.99795 | O12: DL_HN_PNT | P12: VINMART Phạm Ngọc Thạch | Q12: Hà Nội | R12: Đống Đa | S12: 21.006268 | T12: 105.83193 | U12: Nội thành Hà Nội | V12: Nội thành Hà Nội | W12: 34.7 | X12: 1606 | Y12: 4.1 | Z12: 3 | AA12: 5T | AB12: 1.25T | AC12: No | AD12: Yes | AE12: No | AF12: Yes | AG12: Đường đông, cần giao đúng slot | AH12: 08:30 | AI12: 10:00 | AJ12: 11:29 | AK12: 14:29 | AL12: 45 | AM12: 40 | AN12: 35 | AO12: 359 | AP12: 860000 | AQ12: 0 | AR12: 0 | AS12: 80000 | AT12: B - Thường | AU12: CR-NỘIT-02 | AV12: Hệ thống khách hàng | AW12: S3-C11 | AX12: Split/Chuyển tải | AY12: Split Order/Chuyển tải hoặc xin xe nhỏ nhiều chuyến | AZ12: Review | BA12: Vehicle Mismatch | BB12: =AM12+AN12 | BC12: =ROUND(W12/'03_Cost_Constraints'!$B$4*60,0) | BD12: =IF(X12<=500,"5 tạ",IF(X12<=1250,"1.25T",IF(X12<=5000,"5T",IF(X12<=8000,"8T",IF(X12<=15000,"3 chân","4 chân"))))) | BE12: =IF((BB12+BC12)<=AO12,"OK","Risk") | BF12: =IF(AND(AZ12="OK",BE12="OK"),"Ready","Review")
A13: S3 | B13: 2026-06-05 | C13: S3-ORD-012 | D13: Bách Hóa Xanh | E13: Siêu thị Hải Dương | F13: ST | G13: EXPL | H13: Bia lon Saigon Export | I13: PK_HPL_LB | J13: HPL Depot Long Biên - 20 Thạch Bàn | K13: Hà Nội | L13: Long Biên | M13: 21.026155 | N13: 105.91418 | O13: DL_HD_SIEUTHI | P13: Siêu thị Hải Dương | Q13: Hải Phòng | R13: Hải Dương | S13: 20.937341 | T13: 106.31455 | U13: Đông Bắc | V13: Đông Bắc | W13: 62.1 | X13: 4877 | Y13: 9.96 | Z13: 8 | AA13: 5T | AB13: 8T | AC13: No | AD13: Yes | AE13: No | AF13: No | AG13: Quốc lộ 5, xe 8T vào được | AH13: 09:00 | AI13: 11:30 | AJ13: 11:52 | AK13: 13:52 | AL13: 45 | AM13: 40 | AN13: 35 | AO13: 292 | AP13: 2170000 | AQ13: 0 | AR13: 0 | AS13: 80000 | AT13: C - Có thể thương lượng | AU13: CR-ĐÔNG-03 | AV13: Zalo/Email plan 17:00 | AW13: S3-C11 | AX13: 5T | AY13: Send to Clustering | AZ13: OK | BA13: OK | BB13: =AM13+AN13 | BC13: =ROUND(W13/'03_Cost_Constraints'!$B$4*60,0) | BD13: =IF(X13<=500,"5 tạ",IF(X13<=1250,"1.25T",IF(X13<=5000,"5T",IF(X13<=8000,"8T",IF(X13<=15000,"3 chân","4 chân"))))) | BE13: =IF((BB13+BC13)<=AO13,"OK","Risk") | BF13: =IF(AND(AZ13="OK",BE13="OK"),"Ready","Review") | BG13: Kế hoạch ngày hôm sau; cần chốt trước 19:00 và gửi tài xế sau duyệt
A14: S3 | B14: 2026-06-05 | C14: S3-ORD-013 | D14: Masan | E14: BHX Thanh Hóa - Kho DC Quảng Xương | F14: DC | G14: MILK | H14: Sữa hộp carton | I14: PK_TH_QX | J14: Kho DC Thanh Hóa - Quảng Xương | K14: Thanh Hóa | L14: Quảng Xương | M14: 19.731 | N14: 105.815 | O14: DL_TH_BHX_QX | P14: BHX Thanh Hóa - Kho DC Quảng Xương | Q14: Thanh Hóa | R14: Quảng Xương | S14: 19.731 | T14: 105.815 | U14: Bắc Trung Bộ | V14: Bắc Trung Bộ | W14: 3.5 | X14: 9506 | Y14: 30.41 | Z14: 25 | AA14: 3 chân | AB14: 3 chân | AC14: No | AD14: No | AE14: Yes | AF14: No | AG14: DC có thể nhận xe 8T/3 chân | AH14: 09:00 | AI14: 11:00 | AJ14: 12:24 | AK14: 14:54 | AL14: 30 | AM14: 120 | AN14: 90 | AO14: 354 | AP14: 620000 | AQ14: 0 | AR14: 0 | AS14: 150000 | AT14: A - SLA chặt | AU14: CR-BẮCT-04 | AV14: Manual nhập điều phối | AW14: S3-C13 | AX14: 3 chân | AY14: Send to Clustering | AZ14: OK | BA14: OK | BB14: =AM14+AN14 | BC14: =ROUND(W14/'03_Cost_Constraints'!$B$4*60,0) | BD14: =IF(X14<=500,"5 tạ",IF(X14<=1250,"1.25T",IF(X14<=5000,"5T",IF(X14<=8000,"8T",IF(X14<=15000,"3 chân","4 chân"))))) | BE14: =IF((BB14+BC14)<=AO14,"OK","Risk") | BF14: =IF(AND(AZ14="OK",BE14="OK"),"Ready","Review")
A15: S3 | B15: 2026-06-05 | C15: S3-ORD-014 | D15: Unilever | E15: VINMART Uông Bí | F15: ST | G15: CHCA | H15: Bia lon Saigon Chill | I15: PK_HPL_LB | J15: HPL Depot Long Biên - 20 Thạch Bàn | K15: Hà Nội | L15: Long Biên | M15: 21.026155 | N15: 105.91418 | O15: DL_QN_UONGBI | P15: VINMART Uông Bí | Q15: Quảng Ninh | R15: Uông Bí | S15: 21.031495 | T15: 106.76688 | U15: Đông Bắc | V15: Đông Bắc | W15: 115.1 | X15: 1261 | Y15: 3.55 | Z15: 2 | AA15: 5T | AB15: 8T | AC15: No | AD15: Yes | AE15: No | AF15: No | AG15: Đường tỉnh, xe 5T/8T vào được | AH15: 09:00 | AI15: 11:30 | AJ15: 12:33 | AK15: 14:33 | AL15: 45 | AM15: 40 | AN15: 35 | AO15: 333 | AP15: 1200000 | AQ15: 0 | AR15: 0 | AS15: 80000 | AT15: C - Có thể thương lượng | AU15: CR-ĐÔNG-05 | AV15: Excel khách hàng | AW15: S3-C14 | AX15: 5T | AY15: Send to Clustering | AZ15: OK | BA15: Empty-run >100km cần tìm chuyến về | BB15: =AM15+AN15 | BC15: =ROUND(W15/'03_Cost_Constraints'!$B$4*60,0) | BD15: =IF(X15<=500,"5 tạ",IF(X15<=1250,"1.25T",IF(X15<=5000,"5T",IF(X15<=8000,"8T",IF(X15<=15000,"3 chân","4 chân"))))) | BE15: =IF((BB15+BC15)<=AO15,"OK","Risk") | BF15: =IF(AND(AZ15="OK",BE15="OK"),"Ready","Review")
A16: S3 | B16: 2026-06-05 | C16: S3-ORD-015 | D16: Unilever | E16: VINMART Trung Hòa | F16: ST | G16: MILK | H16: Sữa hộp carton | I16: PK_HY_MYHAO | J16: Kho/Nhà máy khách hàng Mỹ Hào | K16: Hưng Yên | L16: Mỹ Hào | M16: 20.9329 | N16: 106.065 | O16: DL_HN_TRUNGHOA | P16: VINMART Trung Hòa | Q16: Hà Nội | R16: Cầu Giấy | S16: 21.007288 | T16: 105.80157 | U16: Nội thành Hà Nội | V16: Nội thành Hà Nội | W16: 43.2 | X16: 958 | Y16: 2.2 | Z16: 1 | AA16: 1.25T | AB16: 1.25T | AC16: No | AD16: Yes | AE16: No | AF16: Yes | AG16: Khung giờ giao sát, bãi giao hẹp | AH16: 08:00 | AI16: 10:30 | AJ16: 11:29 | AK16: 13:29 | AL16: 45 | AM16: 25 | AN16: 20 | AO16: 329 | AP16: 790000 | AQ16: 150000 | AR16: 0 | AS16: 80000 | AT16: C - Có thể thương lượng | AU16: CR-NỘIT-01 | AV16: Hệ thống khách hàng | AW16: S3-C15 | AX16: 1.25T | AY16: Send to Clustering | AZ16: OK | BA16: Cấm tải/đường nhỏ - đã chọn xe nhỏ | BB16: =AM16+AN16 | BC16: =ROUND(W16/'03_Cost_Constraints'!$B$4*60,0) | BD16: =IF(X16<=500,"5 tạ",IF(X16<=1250,"1.25T",IF(X16<=5000,"5T",IF(X16<=8000,"8T",IF(X16<=15000,"3 chân","4 chân"))))) | BE16: =IF((BB16+BC16)<=AO16,"OK","Risk") | BF16: =IF(AND(AZ16="OK",BE16="OK"),"Ready","Review")
A17: S3 | B17: 2026-06-05 | C17: S3-ORD-016 | D17: Acecook | E17: TOPS MARKET ParkCity | F17: MT | G17: FMCG | H17: Hàng tiêu dùng nhanh hỗn hợp | I17: PK_HPL_LB | J17: HPL Depot Long Biên - 20 Thạch Bàn | K17: Hà Nội | L17: Long Biên | M17: 21.026155 | N17: 105.91418 | O17: DL_HN_PARKCITY | P17: TOPS MARKET ParkCity | Q17: Hà Nội | R17: Hà Đông | S17: 20.965724 | T17: 105.75614 | U17: Nội thành Hà Nội | V17: Nội thành Hà Nội | W17: 31.7 | X17: 1705 | Y17: 7.94 | Z17: 6 | AA17: 5T | AB17: 1.25T | AC17: No | AD17: Yes | AE17: No | AF17: Yes | AG17: Bãi giao giới hạn chiều cao | AH17: 07:00 | AI17: 09:30 | AJ17: 09:24 | AK17: 11:24 | AL17: 45 | AM17: 40 | AN17: 45 | AO17: 264 | AP17: 700000 | AQ17: 0 | AR17: 120000 | AS17: 80000 | AT17: B - Thường | AU17: CR-NỘIT-02 | AV17: Zalo/Email plan 17:00 | AW17: S3-C16 | AX17: Split/Chuyển tải | AY17: Split Order/Chuyển tải hoặc xin xe nhỏ nhiều chuyến | AZ17: Review | BA17: Vehicle Mismatch | BB17: =AM17+AN17 | BC17: =ROUND(W17/'03_Cost_Constraints'!$B$4*60,0) | BD17: =IF(X17<=500,"5 tạ",IF(X17<=1250,"1.25T",IF(X17<=5000,"5T",IF(X17<=8000,"8T",IF(X17<=15000,"3 chân","4 chân"))))) | BE17: =IF((BB17+BC17)<=AO17,"OK","Risk") | BF17: =IF(AND(AZ17="OK",BE17="OK"),"Ready","Review") | BG17: Kế hoạch ngày hôm sau; cần chốt trước 19:00 và gửi tài xế sau duyệt
A18: S3 | B18: 2026-06-05 | C18: S3-ORD-017 | D18: MM Mega Market | E18: Siêu thị Thanh Hóa | F18: MT | G18: MILK | H18: Sữa hộp carton | I18: PK_NA_BACVINH | J18: Kho DC Vinh - KCN Bắc Vinh | K18: Nghệ An | L18: Vinh | M18: 18.733 | N18: 105.681 | O18: DL_TH_SIEUTHI | P18: Siêu thị Thanh Hóa | Q18: Thanh Hóa | R18: Hạc Thành | S18: 19.8076 | T18: 105.77639 | U18: Bắc Trung Bộ | V18: Bắc Trung Bộ | W18: 156.3 | X18: 7727 | Y18: 25.47 | Z18: 21 | AA18: 8T | AB18: 5T | AC18: No | AD18: No | AE18: Yes | AF18: No | AG18: Đường đô thị, xe 5T vào được | AH18: 08:00 | AI18: 10:30 | AJ18: 12:07 | AK18: 15:07 | AL18: 30 | AM18: 40 | AN18: 45 | AO18: 427 | AP18: 7840000 | AQ18: 0 | AR18: 120000 | AS18: 80000 | AT18: C - Có thể thương lượng | AU18: CR-BẮCT-03 | AV18: Manual nhập điều phối | AW18: S3-C17 | AX18: Split/Chuyển tải | AY18: Split Order/Chuyển tải hoặc xin xe nhỏ nhiều chuyến | AZ18: Review | BA18: Vehicle Mismatch | BB18: =AM18+AN18 | BC18: =ROUND(W18/'03_Cost_Constraints'!$B$4*60,0) | BD18: =IF(X18<=500,"5 tạ",IF(X18<=1250,"1.25T",IF(X18<=5000,"5T",IF(X18<=8000,"8T",IF(X18<=15000,"3 chân","4 chân"))))) | BE18: =IF((BB18+BC18)<=AO18,"OK","Risk") | BF18: =IF(AND(AZ18="OK",BE18="OK"),"Ready","Review")
A19: S3 | B19: 2026-06-05 | C19: S3-ORD-018 | D19: Acecook | E19: Minh Tuấn | F19: Đại lý | G19: POSM | H19: POSM trưng bày | I19: PK_LINFOX_VSIP | J19: Kho Linfox KCN VSIP Bắc Ninh | K19: Bắc Ninh | L19: Từ Sơn | M19: 21.082707 | N19: 105.99795 | O19: DL_HN_MINHTUAN | P19: Minh Tuấn | Q19: Hà Nội | R19: Hà Nội | S19: 20.954079 | T19: 105.83725 | U19: Nội thành Hà Nội | V19: Nội thành Hà Nội | W19: 39 | X19: 274 | Y19: 4.62 | Z19: 3 | AA19: 1.25T | AB19: 1.25T | AC19: No | AD19: Yes | AE19: No | AF19: Yes | AG19: Đường nhỏ, dây điện thấp | AH19: 08:00 | AI19: 10:00 | AJ19: 11:21 | AK19: 13:51 | AL19: 45 | AM19: 25 | AN19: 20 | AO19: 351 | AP19: 850000 | AQ19: 0 | AR19: 0 | AS19: 80000 | AT19: B - Thường | AU19: CR-NỘIT-04 | AV19: Excel khách hàng | AW19: S3-C17 | AX19: 1.25T | AY19: Send to Clustering | AZ19: OK | BA19: Cấm tải/đường nhỏ - đã chọn xe nhỏ | BB19: =AM19+AN19 | BC19: =ROUND(W19/'03_Cost_Constraints'!$B$4*60,0) | BD19: =IF(X19<=500,"5 tạ",IF(X19<=1250,"1.25T",IF(X19<=5000,"5T",IF(X19<=8000,"8T",IF(X19<=15000,"3 chân","4 chân"))))) | BE19: =IF((BB19+BC19)<=AO19,"OK","Risk") | BF19: =IF(AND(AZ19="OK",BE19="OK"),"Ready","Review")
A20: S3 | B20: 2026-06-05 | C20: S3-ORD-019 | D20: VinCommerce | E20: AKJUKY | F20: Đại lý | G20: SP33 | H20: Bia lon Saigon Special | I20: PK_HPL_LB | J20: HPL Depot Long Biên - 20 Thạch Bàn | K20: Hà Nội | L20: Long Biên | M20: 21.026155 | N20: 105.91418 | O20: DL_HN_AKJUKY | P20: AKJUKY | Q20: Hà Nội | R20: Long Biên | S20: 21.063695 | T20: 105.88999 | U20: Nội thành Hà Nội | V20: Nội thành Hà Nội | W20: 11.8 | X20: 301 | Y20: 0.7 | Z20: 1 | AA20: 5 tạ | AB20: 1.25T | AC20: No | AD20: Yes | AE20: No | AF20: Yes | AG20: Đường nhỏ nội đô | AH20: 07:30 | AI20: 09:00 | AJ20: 09:35 | AK20: 11:05 | AL20: 45 | AM20: 25 | AN20: 20 | AO20: 215 | AP20: 810000 | AQ20: 0 | AR20: 0 | AS20: 80000 | AT20: C - Có thể thương lượng | AU20: CR-NỘIT-05 | AV20: Hệ thống khách hàng | AW20: S3-C19 | AX20: 5 tạ | AY20: Send to Clustering | AZ20: OK | BA20: Cấm tải/đường nhỏ - đã chọn xe nhỏ | BB20: =AM20+AN20 | BC20: =ROUND(W20/'03_Cost_Constraints'!$B$4*60,0) | BD20: =IF(X20<=500,"5 tạ",IF(X20<=1250,"1.25T",IF(X20<=5000,"5T",IF(X20<=8000,"8T",IF(X20<=15000,"3 chân","4 chân"))))) | BE20: =IF((BB20+BC20)<=AO20,"OK","Risk") | BF20: =IF(AND(AZ20="OK",BE20="OK"),"Ready","Review")
A21: S3 | B21: 2026-06-05 | C21: S3-ORD-020 | D21: Unilever | E21: VINMART Vũ Trọng Phụng | F21: ST | G21: LVCA | H21: Bia lon Lạc Việt | I21: PK_HY_MYHAO | J21: Kho/Nhà máy khách hàng Mỹ Hào | K21: Hưng Yên | L21: Mỹ Hào | M21: 20.9329 | N21: 106.065 | O21: DL_HN_VUTRONGPHUNG | P21: VINMART Vũ Trọng Phụng | Q21: Hà Nội | R21: Thanh Xuân | S21: 20.997621 | T21: 105.80944 | U21: Nội thành Hà Nội | V21: Nội thành Hà Nội | W21: 43.8 | X21: 783 | Y21: 2.1 | Z21: 1 | AA21: 1.25T | AB21: 1.25T | AC21: No | AD21: Yes | AE21: No | AF21: Yes | AG21: Hầm giao nhận thấp | AH21: 07:30 | AI21: 09:30 | AJ21: 08:30 | AK21: 10:00 | AL21: 45 | AM21: 25 | AN21: 20 | AO21: 150 | AP21: 610000 | AQ21: 0 | AR21: 0 | AS21: 80000 | AT21: C - Có thể thương lượng | AU21: CR-NỘIT-01 | AV21: Zalo/Email plan 17:00 | AW21: S3-C20 | AX21: 1.25T | AY21: Send to Clustering | AZ21: OK | BA21: Cấm tải/đường nhỏ - đã chọn xe nhỏ | BB21: =AM21+AN21 | BC21: =ROUND(W21/'03_Cost_Constraints'!$B$4*60,0) | BD21: =IF(X21<=500,"5 tạ",IF(X21<=1250,"1.25T",IF(X21<=5000,"5T",IF(X21<=8000,"8T",IF(X21<=15000,"3 chân","4 chân"))))) | BE21: =IF((BB21+BC21)<=AO21,"OK","Risk") | BF21: =IF(AND(AZ21="OK",BE21="OK"),"Ready","Review") | BG21: Lead time hẹp, cần cảnh báo hoặc xin nới giờ
A22: S3 | B22: 2026-06-05 | C22: S3-ORD-021 | D22: VinCommerce | E22: Siêu thị Hải Phòng | F22: MT | G22: LVCA | H22: Bia lon Lạc Việt | I22: PK_HP_DINHVU | J22: Kho Hải Phòng - Đình Vũ | K22: Hải Phòng | L22: Hải An | M22: 20.8425 | N22: 106.77 | O22: DL_HP_SIEUTHI | P22: Siêu thị Hải Phòng | Q22: Hải Phòng | R22: Gia Viên | S22: 20.84442 | T22: 106.7011 | U22: Đông Bắc | V22: Đông Bắc | W22: 12.2 | X22: 4727 | Y22: 8.36 | Z22: 6 | AA22: 5T | AB22: 5T | AC22: No | AD22: Yes | AE22: No | AF22: No | AG22: Khung giờ nhập kho 13:00-16:00 | AH22: 09:00 | AI22: 11:00 | AJ22: 10:46 | AK22: 12:16 | AL22: 45 | AM22: 40 | AN22: 45 | AO22: 196 | AP22: 890000 | AQ22: 150000 | AR22: 120000 | AS22: 80000 | AT22: B - Thường | AU22: CR-ĐÔNG-02 | AV22: Manual nhập điều phối | AW22: S3-C21 | AX22: 5T | AY22: Send to Clustering | AZ22: OK | BA22: OK | BB22: =AM22+AN22 | BC22: =ROUND(W22/'03_Cost_Constraints'!$B$4*60,0) | BD22: =IF(X22<=500,"5 tạ",IF(X22<=1250,"1.25T",IF(X22<=5000,"5T",IF(X22<=8000,"8T",IF(X22<=15000,"3 chân","4 chân"))))) | BE22: =IF((BB22+BC22)<=AO22,"OK","Risk") | BF22: =IF(AND(AZ22="OK",BE22="OK"),"Ready","Review")
A23: S3 | B23: 2026-06-05 | C23: S3-ORD-022 | D23: VinCommerce | E23: MM Vinh | F23: MT | G23: PAT2 | H23: Bia lon 333 | I23: PK_TH_QX | J23: Kho DC Thanh Hóa - Quảng Xương | K23: Thanh Hóa | L23: Quảng Xương | M23: 19.731 | N23: 105.815 | O23: DL_NA_MM_VINH | P23: MM Vinh | Q23: Nghệ An | R23: Vinh | S23: 18.68052 | T23: 105.68133 | U23: Bắc Trung Bộ | V23: Bắc Trung Bộ | W23: 156 | X23: 6414 | Y23: 17.74 | Z23: 14 | AA23: 8T | AB23: 8T | AC23: No | AD23: Yes | AE23: No | AF23: No | AG23: Xe 8T vào được | AH23: 07:30 | AI23: 09:00 | AJ23: 12:37 | AK23: 14:37 | AL23: 45 | AM23: 40 | AN23: 45 | AO23: 427 | AP23: 6600000 | AQ23: 0 | AR23: 120000 | AS23: 80000 | AT23: B - Thường | AU23: CR-BẮCT-03 | AV23: Excel khách hàng | AW23: S3-C22 | AX23: 8T | AY23: Send to Clustering | AZ23: OK | BA23: Empty-run >100km cần tìm chuyến về | BB23: =AM23+AN23 | BC23: =ROUND(W23/'03_Cost_Constraints'!$B$4*60,0) | BD23: =IF(X23<=500,"5 tạ",IF(X23<=1250,"1.25T",IF(X23<=5000,"5T",IF(X23<=8000,"8T",IF(X23<=15000,"3 chân","4 chân"))))) | BE23: =IF((BB23+BC23)<=AO23,"OK","Risk") | BF23: =IF(AND(AZ23="OK",BE23="OK"),"Ready","Review")
A24: S3 | B24: 2026-06-05 | C24: S3-ORD-023 | D24: Unilever | E24: Nam Dương | F24: Đại lý | G24: EXPL | H24: Bia lon Saigon Export | I24: PK_HY_MYHAO | J24: Kho/Nhà máy khách hàng Mỹ Hào | K24: Hưng Yên | L24: Mỹ Hào | M24: 20.9329 | N24: 106.065 | O24: DL_HN_NAMDUONG | P24: Nam Dương | Q24: Hà Nội | R24: Hà Nội | S24: 21.062911 | T24: 105.83235 | U24: Nội thành Hà Nội | V24: Nội thành Hà Nội | W24: 42.4 | X24: 1034 | Y24: 2.72 | Z24: 2 | AA24: 1.25T | AB24: 1.25T | AC24: No | AD24: Yes | AE24: No | AF24: Yes | AG24: Đường nội đô, có khung giờ cấm tải | AH24: 08:00 | AI24: 10:30 | AJ24: 11:27 | AK24: 14:27 | AL24: 45 | AM24: 25 | AN24: 20 | AO24: 387 | AP24: 650000 | AQ24: 0 | AR24: 0 | AS24: 150000 | AT24: A - SLA chặt | AU24: CR-NỘIT-04 | AV24: Hệ thống khách hàng | AW24: S3-C23 | AX24: 1.25T | AY24: Send to Clustering | AZ24: OK | BA24: Cấm tải/đường nhỏ - đã chọn xe nhỏ | BB24: =AM24+AN24 | BC24: =ROUND(W24/'03_Cost_Constraints'!$B$4*60,0) | BD24: =IF(X24<=500,"5 tạ",IF(X24<=1250,"1.25T",IF(X24<=5000,"5T",IF(X24<=8000,"8T",IF(X24<=15000,"3 chân","4 chân"))))) | BE24: =IF((BB24+BC24)<=AO24,"OK","Risk") | BF24: =IF(AND(AZ24="OK",BE24="OK"),"Ready","Review")
A25: S3 | B25: 2026-06-05 | C25: S3-ORD-024 | D25: Masan | E25: VINMART Vũ Trọng Phụng | F25: ST | G25: NOODLE | H25: Mì gói/Acecook carton | I25: PK_HY_MYHAO | J25: Kho/Nhà máy khách hàng Mỹ Hào | K25: Hưng Yên | L25: Mỹ Hào | M25: 20.9329 | N25: 106.065 | O25: DL_HN_VUTRONGPHUNG | P25: VINMART Vũ Trọng Phụng | Q25: Hà Nội | R25: Thanh Xuân | S25: 20.997621 | T25: 105.80944 | U25: Nội thành Hà Nội | V25: Nội thành Hà Nội | W25: 44.5 | X25: 2215 | Y25: 22.3 | Z25: 18 | AA25: 5T | AB25: 1.25T | AC25: No | AD25: No | AE25: Yes | AF25: Yes | AG25: Hầm giao nhận thấp | AH25: 08:30 | AI25: 10:30 | AJ25: 09:46 | AK25: 12:16 | AL25: 30 | AM25: 40 | AN25: 35 | AO25: 226 | AP25: 1260000 | AQ25: 0 | AR25: 0 | AS25: 80000 | AT25: C - Có thể thương lượng | AU25: CR-NỘIT-05 | AV25: Zalo/Email plan 17:00 | AW25: S3-C23 | AX25: Split/Chuyển tải | AY25: Split Order/Chuyển tải hoặc xin xe nhỏ nhiều chuyến | AZ25: Review | BA25: Vehicle Mismatch | BB25: =AM25+AN25 | BC25: =ROUND(W25/'03_Cost_Constraints'!$B$4*60,0) | BD25: =IF(X25<=500,"5 tạ",IF(X25<=1250,"1.25T",IF(X25<=5000,"5T",IF(X25<=8000,"8T",IF(X25<=15000,"3 chân","4 chân"))))) | BE25: =IF((BB25+BC25)<=AO25,"OK","Risk") | BF25: =IF(AND(AZ25="OK",BE25="OK"),"Ready","Review") | BG25: Lead time hẹp, cần cảnh báo hoặc xin nới giờ
A26: S3 | B26: 2026-06-05 | C26: S3-ORD-025 | D26: Sabeco | E26: MM Hồng Bàng | F26: MT | G26: POSM | H26: POSM trưng bày | I26: PK_LINFOX_VSIP | J26: Kho Linfox KCN VSIP Bắc Ninh | K26: Bắc Ninh | L26: Từ Sơn | M26: 21.082707 | N26: 105.99795 | O26: DL_HP_HONGBANG | P26: MM Hồng Bàng | Q26: Hải Phòng | R26: Hồng Bàng | S26: 20.856112 | T26: 106.68224 | U26: Đông Bắc | V26: Đông Bắc | W26: 99.6 | X26: 2616 | Y26: 43.81 | Z26: 36 | AA26: 8T | AB26: 5T | AC26: No | AD26: Yes | AE26: No | AF26: No | AG26: Đường đô thị Hải Phòng, xe 5T vào được | AH26: 07:00 | AI26: 08:30 | AJ26: 10:42 | AK26: 13:42 | AL26: 30 | AM26: 40 | AN26: 45 | AO26: 402 | AP26: 1800000 | AQ26: 0 | AR26: 120000 | AS26: 80000 | AT26: B - Thường | AU26: CR-ĐÔNG-01 | AV26: Manual nhập điều phối | AW26: S3-C25 | AX26: Split/Chuyển tải | AY26: Split Order/Chuyển tải hoặc xin xe nhỏ nhiều chuyến | AZ26: Review | BA26: Vehicle Mismatch | BB26: =AM26+AN26 | BC26: =ROUND(W26/'03_Cost_Constraints'!$B$4*60,0) | BD26: =IF(X26<=500,"5 tạ",IF(X26<=1250,"1.25T",IF(X26<=5000,"5T",IF(X26<=8000,"8T",IF(X26<=15000,"3 chân","4 chân"))))) | BE26: =IF((BB26+BC26)<=AO26,"OK","Risk") | BF26: =IF(AND(AZ26="OK",BE26="OK"),"Ready","Review")
A27: S3 | B27: 2026-06-05 | C27: S3-ORD-026 | D27: Acecook | E27: Siêu thị Ninh Bình | F27: ST | G27: MILK | H27: Sữa hộp carton | I27: PK_TH_QX | J27: Kho DC Thanh Hóa - Quảng Xương | K27: Thanh Hóa | L27: Quảng Xương | M27: 19.731 | N27: 105.815 | O27: DL_NB_SIEUTHI | P27: Siêu thị Ninh Bình | Q27: Ninh Bình | R27: Hoa Lư | S27: 20.250614 | T27: 105.97445 | U27: Bắc Trung Bộ | V27: Bắc Trung Bộ | W27: 80.1 | X27: 3531 | Y27: 10.13 | Z27: 8 | AA27: 5T | AB27: 8T | AC27: No | AD27: Yes | AE27: No | AF27: No | AG27: Xe 8T vào được | AH27: 07:00 | AI27: 09:30 | AJ27: 10:16 | AK27: 12:16 | AL27: 45 | AM27: 40 | AN27: 35 | AO27: 316 | AP27: 1920000 | AQ27: 0 | AR27: 0 | AS27: 80000 | AT27: B - Thường | AU27: CR-BẮCT-02 | AV27: Excel khách hàng | AW27: S3-C26 | AX27: 5T | AY27: Send to Clustering | AZ27: OK | BA27: OK | BB27: =AM27+AN27 | BC27: =ROUND(W27/'03_Cost_Constraints'!$B$4*60,0) | BD27: =IF(X27<=500,"5 tạ",IF(X27<=1250,"1.25T",IF(X27<=5000,"5T",IF(X27<=8000,"8T",IF(X27<=15000,"3 chân","4 chân"))))) | BE27: =IF((BB27+BC27)<=AO27,"OK","Risk") | BF27: =IF(AND(AZ27="OK",BE27="OK"),"Ready","Review")
A28: S3 | B28: 2026-06-05 | C28: S3-ORD-027 | D28: Linfox | E28: VINMART Quế Võ | F28: ST | G28: LASG | H28: Bia lon Saigon Lager 330ml | I28: PK_HPL_LB | J28: HPL Depot Long Biên - 20 Thạch Bàn | K28: Hà Nội | L28: Long Biên | M28: 21.026155 | N28: 105.91418 | O28: DL_BN_QUEVO_01 | P28: VINMART Quế Võ | Q28: Bắc Ninh | R28: Quế Võ | S28: 21.170139 | T28: 106.1024 | U28: Đông Bắc | V28: Đông Bắc | W28: 40.2 | X28: 1906 | Y28: 4.64 | Z28: 3 | AA28: 5T | AB28: 8T | AC28: No | AD28: Yes | AE28: No | AF28: No | AG28: Đường rộng, xe 5T/8T vào được | AH28: 08:30 | AI28: 11:00 | AJ28: 10:23 | AK28: 11:53 | AL28: 45 | AM28: 40 | AN28: 35 | AO28: 203 | AP28: 1190000 | AQ28: 150000 | AR28: 0 | AS28: 150000 | AT28: A - SLA chặt | AU28: CR-ĐÔNG-03 | AV28: Hệ thống khách hàng | AW28: S3-C27 | AX28: 5T | AY28: Send to Clustering | AZ28: OK | BA28: OK | BB28: =AM28+AN28 | BC28: =ROUND(W28/'03_Cost_Constraints'!$B$4*60,0) | BD28: =IF(X28<=500,"5 tạ",IF(X28<=1250,"1.25T",IF(X28<=5000,"5T",IF(X28<=8000,"8T",IF(X28<=15000,"3 chân","4 chân"))))) | BE28: =IF((BB28+BC28)<=AO28,"OK","Risk") | BF28: =IF(AND(AZ28="OK",BE28="OK"),"Ready","Review")
A29: S3 | B29: 2026-06-05 | C29: S3-ORD-028 | D29: Unilever | E29: LOTTE MART Ba Đình | F29: MT | G29: FMCG | H29: Hàng tiêu dùng nhanh hỗn hợp | I29: PK_HPL_LB | J29: HPL Depot Long Biên - 20 Thạch Bàn | K29: Hà Nội | L29: Long Biên | M29: 21.026155 | N29: 105.91418 | O29: DL_HN_LOTTE_BD | P29: LOTTE MART Ba Đình | Q29: Hà Nội | R29: Ba Đình | S29: 21.032177 | T29: 105.81244 | U29: Nội thành Hà Nội | V29: Nội thành Hà Nội | W29: 21.4 | X29: 2249 | Y29: 11.28 | Z29: 9 | AA29: 5T | AB29: 1.25T | AC29: No | AD29: Yes | AE29: No | AF29: Yes | AG29: Giờ cấm tải, ưu tiên xe 1.25T | AH29: 07:00 | AI29: 08:30 | AJ29: 07:56 | AK29: 09:26 | AL29: 45 | AM29: 40 | AN29: 45 | AO29: 146 | AP29: 1020000 | AQ29: 0 | AR29: 120000 | AS29: 80000 | AT29: B - Thường | AU29: CR-NỘIT-04 | AV29: Zalo/Email plan 17:00 | AW29: S3-C28 | AX29: Split/Chuyển tải | AY29: Split Order/Chuyển tải hoặc xin xe nhỏ nhiều chuyến | AZ29: Review | BA29: Vehicle Mismatch | BB29: =AM29+AN29 | BC29: =ROUND(W29/'03_Cost_Constraints'!$B$4*60,0) | BD29: =IF(X29<=500,"5 tạ",IF(X29<=1250,"1.25T",IF(X29<=5000,"5T",IF(X29<=8000,"8T",IF(X29<=15000,"3 chân","4 chân"))))) | BE29: =IF((BB29+BC29)<=AO29,"OK","Risk") | BF29: =IF(AND(AZ29="OK",BE29="OK"),"Ready","Review") | BG29: Lead time hẹp, cần cảnh báo hoặc xin nới giờ
A30: S3 | B30: 2026-06-05 | C30: S3-ORD-029 | D30: VinCommerce | E30: VINMART Trương Định | F30: ST | G30: SP33 | H30: Bia lon Saigon Special | I30: PK_HPL_LB | J30: HPL Depot Long Biên - 20 Thạch Bàn | K30: Hà Nội | L30: Long Biên | M30: 21.026155 | N30: 105.91418 | O30: DL_HN_TRUONGDINH | P30: VINMART Trương Định | Q30: Hà Nội | R30: Hoàng Mai | S30: 20.979293 | T30: 105.84471 | U30: Nội thành Hà Nội | V30: Nội thành Hà Nội | W30: 16.8 | X30: 271 | Y30: 0.76 | Z30: 1 | AA30: 5 tạ | AB30: 1.25T | AC30: No | AD30: Yes | AE30: No | AF30: Yes | AG30: Đường nhỏ, khó quay đầu | AH30: 07:00 | AI30: 09:00 | AJ30: 08:13 | AK30: 09:43 | AL30: 45 | AM30: 25 | AN30: 20 | AO30: 163 | AP30: 470000 | AQ30: 0 | AR30: 0 | AS30: 80000 | AT30: C - Có thể thương lượng | AU30: CR-NỘIT-05 | AV30: Manual nhập điều phối | AW30: S3-C29 | AX30: 5 tạ | AY30: Send to Clustering | AZ30: OK | BA30: Cấm tải/đường nhỏ - đã chọn xe nhỏ | BB30: =AM30+AN30 | BC30: =ROUND(W30/'03_Cost_Constraints'!$B$4*60,0) | BD30: =IF(X30<=500,"5 tạ",IF(X30<=1250,"1.25T",IF(X30<=5000,"5T",IF(X30<=8000,"8T",IF(X30<=15000,"3 chân","4 chân"))))) | BE30: =IF((BB30+BC30)<=AO30,"OK","Risk") | BF30: =IF(AND(AZ30="OK",BE30="OK"),"Ready","Review")
A31: S3 | B31: 2026-06-05 | C31: S3-ORD-030 | D31: Masan | E31: MM Hồng Bàng | F31: MT | G31: LASG | H31: Bia lon Saigon Lager 330ml | I31: PK_LINFOX_VSIP | J31: Kho Linfox KCN VSIP Bắc Ninh | K31: Bắc Ninh | L31: Từ Sơn | M31: 21.082707 | N31: 105.99795 | O31: DL_HP_HONGBANG | P31: MM Hồng Bàng | Q31: Hải Phòng | R31: Hồng Bàng | S31: 20.856112 | T31: 106.68224 | U31: Đông Bắc | V31: Đông Bắc | W31: 101 | X31: 1138 | Y31: 2.04 | Z31: 1 | AA31: 1.25T | AB31: 5T | AC31: No | AD31: Yes | AE31: No | AF31: No | AG31: Đường đô thị Hải Phòng, xe 5T vào được | AH31: 08:30 | AI31: 10:30 | AJ31: 12:29 | AK31: 13:59 | AL31: 30 | AM31: 25 | AN31: 30 | AO31: 329 | AP31: 1390000 | AQ31: 0 | AR31: 120000 | AS31: 80000 | AT31: B - Thường | AU31: CR-ĐÔNG-01 | AV31: Excel khách hàng | AW31: S3-C29 | AX31: 1.25T | AY31: Send to Clustering | AZ31: OK | BA31: Empty-run >100km cần tìm chuyến về | BB31: =AM31+AN31 | BC31: =ROUND(W31/'03_Cost_Constraints'!$B$4*60,0) | BD31: =IF(X31<=500,"5 tạ",IF(X31<=1250,"1.25T",IF(X31<=5000,"5T",IF(X31<=8000,"8T",IF(X31<=15000,"3 chân","4 chân"))))) | BE31: =IF((BB31+BC31)<=AO31,"OK","Risk") | BF31: =IF(AND(AZ31="OK",BE31="OK"),"Ready","Review")
A32: S3 | B32: 2026-06-05 | C32: S3-ORD-031 | D32: Sabeco | E32: GO! Hà Nam | F32: MT | G32: CHCA | H32: Bia lon Saigon Chill | I32: PK_HPL_LB | J32: HPL Depot Long Biên - 20 Thạch Bàn | K32: Hà Nội | L32: Long Biên | M32: 21.026155 | N32: 105.91418 | O32: DL_HN_GO_HANAM | P32: GO! Hà Nam | Q32: Ninh Bình | R32: Phủ Lý | S32: 20.541 | T32: 105.913 | U32: Bắc Trung Bộ | V32: Bắc Trung Bộ | W32: 75.6 | X32: 1826 | Y32: 3.26 | Z32: 2 | AA32: 5T | AB32: 8T | AC32: No | AD32: Yes | AE32: No | AF32: No | AG32: Xe 5T/8T vào được | AH32: 07:30 | AI32: 09:00 | AJ32: 10:10 | AK32: 13:10 | AL32: 30 | AM32: 40 | AN32: 45 | AO32: 340 | AP32: 1310000 | AQ32: 0 | AR32: 120000 | AS32: 80000 | AT32: C - Có thể thương lượng | AU32: CR-BẮCT-02 | AV32: Hệ thống khách hàng | AW32: S3-C31 | AX32: 5T | AY32: Send to Clustering | AZ32: OK | BA32: OK | BB32: =AM32+AN32 | BC32: =ROUND(W32/'03_Cost_Constraints'!$B$4*60,0) | BD32: =IF(X32<=500,"5 tạ",IF(X32<=1250,"1.25T",IF(X32<=5000,"5T",IF(X32<=8000,"8T",IF(X32<=15000,"3 chân","4 chân"))))) | BE32: =IF((BB32+BC32)<=AO32,"OK","Risk") | BF32: =IF(AND(AZ32="OK",BE32="OK"),"Ready","Review")
A33: S3 | B33: 2026-06-05 | C33: S3-ORD-032 | D33: Sabeco | E33: Thái Dương | F33: Đại lý | G33: NOODLE | H33: Mì gói/Acecook carton | I33: PK_LINFOX_VSIP | J33: Kho Linfox KCN VSIP Bắc Ninh | K33: Bắc Ninh | L33: Từ Sơn | M33: 21.082707 | N33: 105.99795 | O33: DL_HN_THAIDUONG | P33: Thái Dương | Q33: Hà Nội | R33: Hà Nội | S33: 20.929215 | T33: 105.87 | U33: Nội thành Hà Nội | V33: Nội thành Hà Nội | W33: 37.2 | X33: 472 | Y33: 3.17 | Z33: 2 | AA33: 5 tạ | AB33: 1.25T | AC33: No | AD33: Yes | AE33: No | AF33: Yes | AG33: Đường nhỏ, ưu tiên xe <=1.25T | AH33: 07:00 | AI33: 09:30 | AJ33: 08:48 | AK33: 10:48 | AL33: 30 | AM33: 25 | AN33: 20 | AO33: 228 | AP33: 530000 | AQ33: 0 | AR33: 0 | AS33: 80000 | AT33: B - Thường | AU33: CR-NỘIT-03 | AV33: Zalo/Email plan 17:00 | AW33: S3-C32 | AX33: 5 tạ | AY33: Send to Clustering | AZ33: OK | BA33: Cấm tải/đường nhỏ - đã chọn xe nhỏ | BB33: =AM33+AN33 | BC33: =ROUND(W33/'03_Cost_Constraints'!$B$4*60,0) | BD33: =IF(X33<=500,"5 tạ",IF(X33<=1250,"1.25T",IF(X33<=5000,"5T",IF(X33<=8000,"8T",IF(X33<=15000,"3 chân","4 chân"))))) | BE33: =IF((BB33+BC33)<=AO33,"OK","Risk") | BF33: =IF(AND(AZ33="OK",BE33="OK"),"Ready","Review") | BG33: Kế hoạch ngày hôm sau; cần chốt trước 19:00 và gửi tài xế sau duyệt
A34: S3 | B34: 2026-06-05 | C34: S3-ORD-033 | D34: Sabeco | E34: VINMART Uông Bí | F34: ST | G34: MILK | H34: Sữa hộp carton | I34: PK_HPL_LB | J34: HPL Depot Long Biên - 20 Thạch Bàn | K34: Hà Nội | L34: Long Biên | M34: 21.026155 | N34: 105.91418 | O34: DL_QN_UONGBI | P34: VINMART Uông Bí | Q34: Quảng Ninh | R34: Uông Bí | S34: 21.031495 | T34: 106.76688 | U34: Đông Bắc | V34: Đông Bắc | W34: 117.3 | X34: 2518 | Y34: 7.36 | Z34: 6 | AA34: 5T | AB34: 8T | AC34: No | AD34: Yes | AE34: No | AF34: No | AG34: Đường tỉnh, xe 5T/8T vào được | AH34: 07:30 | AI34: 10:00 | AJ34: 12:36 | AK34: 14:06 | AL34: 30 | AM34: 40 | AN34: 35 | AO34: 396 | AP34: 2330000 | AQ34: 150000 | AR34: 0 | AS34: 80000 | AT34: C - Có thể thương lượng | AU34: CR-ĐÔNG-04 | AV34: Manual nhập điều phối | AW34: S3-C33 | AX34: 5T | AY34: Send to Clustering | AZ34: OK | BA34: Empty-run >100km cần tìm chuyến về | BB34: =AM34+AN34 | BC34: =ROUND(W34/'03_Cost_Constraints'!$B$4*60,0) | BD34: =IF(X34<=500,"5 tạ",IF(X34<=1250,"1.25T",IF(X34<=5000,"5T",IF(X34<=8000,"8T",IF(X34<=15000,"3 chân","4 chân"))))) | BE34: =IF((BB34+BC34)<=AO34,"OK","Risk") | BF34: =IF(AND(AZ34="OK",BE34="OK"),"Ready","Review")
A35: S3 | B35: 2026-06-05 | C35: S3-ORD-034 | D35: Bách Hóa Xanh | E35: VINMART Times City | F35: MT | G35: NOODLE | H35: Mì gói/Acecook carton | I35: PK_LINFOX_VSIP | J35: Kho Linfox KCN VSIP Bắc Ninh | K35: Bắc Ninh | L35: Từ Sơn | M35: 21.082707 | N35: 105.99795 | O35: DL_HN_TIMESCITY | P35: VINMART Times City | Q35: Hà Nội | R35: Hai Bà Trưng | S35: 20.994022 | T35: 105.86964 | U35: Nội thành Hà Nội | V35: Nội thành Hà Nội | W35: 26.4 | X35: 1131 | Y35: 10.14 | Z35: 8 | AA35: 5T | AB35: 1.25T | AC35: No | AD35: Yes | AE35: No | AF35: Yes | AG35: Nội khu, xe lớn hạn chế | AH35: 08:30 | AI35: 10:30 | AJ35: 10:45 | AK35: 13:45 | AL35: 45 | AM35: 40 | AN35: 45 | AO35: 315 | AP35: 740000 | AQ35: 0 | AR35: 120000 | AS35: 80000 | AT35: C - Có thể thương lượng | AU35: CR-NỘIT-05 | AV35: Excel khách hàng | AW35: S3-C34 | AX35: Split/Chuyển tải | AY35: Split Order/Chuyển tải hoặc xin xe nhỏ nhiều chuyến | AZ35: Review | BA35: Vehicle Mismatch | BB35: =AM35+AN35 | BC35: =ROUND(W35/'03_Cost_Constraints'!$B$4*60,0) | BD35: =IF(X35<=500,"5 tạ",IF(X35<=1250,"1.25T",IF(X35<=5000,"5T",IF(X35<=8000,"8T",IF(X35<=15000,"3 chân","4 chân"))))) | BE35: =IF((BB35+BC35)<=AO35,"OK","Risk") | BF35: =IF(AND(AZ35="OK",BE35="OK"),"Ready","Review")
A36: S3 | B36: 2026-06-05 | C36: S3-ORD-035 | D36: MM Mega Market | E36: Siêu thị Thái Nguyên | F36: MT | G36: FMCG | H36: Hàng tiêu dùng nhanh hỗn hợp | I36: PK_HPL_LB | J36: HPL Depot Long Biên - 20 Thạch Bàn | K36: Hà Nội | L36: Long Biên | M36: 21.026155 | N36: 105.91418 | O36: DL_TN_SIEUTHI | P36: Siêu thị Thái Nguyên | Q36: Thái Nguyên | R36: Thái Nguyên | S36: 21.594221 | T36: 105.84817 | U36: Tây Bắc | V36: Tây Bắc | W36: 90.5 | X36: 2482 | Y36: 12.43 | Z36: 10 | AA36: 5T | AB36: 8T | AC36: No | AD36: Yes | AE36: No | AF36: No | AG36: Đường tỉnh, xe 8T vào được | AH36: 08:30 | AI36: 11:00 | AJ36: 11:30 | AK36: 14:00 | AL36: 30 | AM36: 40 | AN36: 45 | AO36: 330 | AP36: 1610000 | AQ36: 0 | AR36: 120000 | AS36: 80000 | AT36: B - Thường | AU36: CR-TÂYB-01 | AV36: Hệ thống khách hàng | AW36: S3-C35 | AX36: 5T | AY36: Send to Clustering | AZ36: OK | BA36: OK | BB36: =AM36+AN36 | BC36: =ROUND(W36/'03_Cost_Constraints'!$B$4*60,0) | BD36: =IF(X36<=500,"5 tạ",IF(X36<=1250,"1.25T",IF(X36<=5000,"5T",IF(X36<=8000,"8T",IF(X36<=15000,"3 chân","4 chân"))))) | BE36: =IF((BB36+BC36)<=AO36,"OK","Risk") | BF36: =IF(AND(AZ36="OK",BE36="OK"),"Ready","Review")
A37: S3 | B37: 2026-06-05 | C37: S3-ORD-036 | D37: Unilever | E37: Siêu thị Vinh | F37: ST | G37: LASG | H37: Bia lon Saigon Lager 330ml | I37: PK_NA_BACVINH | J37: Kho DC Vinh - KCN Bắc Vinh | K37: Nghệ An | L37: Vinh | M37: 18.733 | N37: 105.681 | O37: DL_NA_SIEUTHI | P37: Siêu thị Vinh | Q37: Nghệ An | R37: Vinh | S37: 18.679586 | T37: 105.6811 | U37: Bắc Trung Bộ | V37: Bắc Trung Bộ | W37: 9.8 | X37: 6564 | Y37: 11.81 | Z37: 9 | AA37: 8T | AB37: 5T | AC37: No | AD37: Yes | AE37: No | AF37: No | AG37: Khung giờ nhập kho chiều | AH37: 08:30 | AI37: 10:00 | AJ37: 10:13 | AK37: 11:43 | AL37: 45 | AM37: 40 | AN37: 35 | AO37: 193 | AP37: 1130000 | AQ37: 0 | AR37: 0 | AS37: 80000 | AT37: B - Thường | AU37: CR-BẮCT-02 | AV37: Zalo/Email plan 17:00 | AW37: S3-C35 | AX37: Split/Chuyển tải | AY37: Split Order/Chuyển tải hoặc xin xe nhỏ nhiều chuyến | AZ37: Review | BA37: Vehicle Mismatch | BB37: =AM37+AN37 | BC37: =ROUND(W37/'03_Cost_Constraints'!$B$4*60,0) | BD37: =IF(X37<=500,"5 tạ",IF(X37<=1250,"1.25T",IF(X37<=5000,"5T",IF(X37<=8000,"8T",IF(X37<=15000,"3 chân","4 chân"))))) | BE37: =IF((BB37+BC37)<=AO37,"OK","Risk") | BF37: =IF(AND(AZ37="OK",BE37="OK"),"Ready","Review") | BG37: Kế hoạch ngày hôm sau; cần chốt trước 19:00 và gửi tài xế sau duyệt
A38: S3 | B38: 2026-06-05 | C38: S3-ORD-037 | D38: VinCommerce | E38: VINMART Uông Bí | F38: ST | G38: LASG | H38: Bia lon Saigon Lager 330ml | I38: PK_HPL_LB | J38: HPL Depot Long Biên - 20 Thạch Bàn | K38: Hà Nội | L38: Long Biên | M38: 21.026155 | N38: 105.91418 | O38: DL_QN_UONGBI | P38: VINMART Uông Bí | Q38: Quảng Ninh | R38: Uông Bí | S38: 21.031495 | T38: 106.76688 | U38: Đông Bắc | V38: Đông Bắc | W38: 118.4 | X38: 1831 | Y38: 4.46 | Z38: 3 | AA38: 5T | AB38: 8T | AC38: No | AD38: Yes | AE38: No | AF38: No | AG38: Đường tỉnh, xe 5T/8T vào được | AH38: 08:00 | AI38: 10:30 | AJ38: 12:37 | AK38: 14:07 | AL38: 45 | AM38: 40 | AN38: 35 | AO38: 367 | AP38: 1720000 | AQ38: 0 | AR38: 0 | AS38: 80000 | AT38: C - Có thể thương lượng | AU38: CR-ĐÔNG-03 | AV38: Manual nhập điều phối | AW38: S3-C37 | AX38: 5T | AY38: Send to Clustering | AZ38: OK | BA38: Empty-run >100km cần tìm chuyến về | BB38: =AM38+AN38 | BC38: =ROUND(W38/'03_Cost_Constraints'!$B$4*60,0) | BD38: =IF(X38<=500,"5 tạ",IF(X38<=1250,"1.25T",IF(X38<=5000,"5T",IF(X38<=8000,"8T",IF(X38<=15000,"3 chân","4 chân"))))) | BE38: =IF((BB38+BC38)<=AO38,"OK","Risk") | BF38: =IF(AND(AZ38="OK",BE38="OK"),"Ready","Review")
A39: S3 | B39: 2026-06-05 | C39: S3-ORD-038 | D39: VinCommerce | E39: TOPS MARKET Garden Mall | F39: MT | G39: POSM | H39: POSM trưng bày | I39: PK_LINFOX_VSIP | J39: Kho Linfox KCN VSIP Bắc Ninh | K39: Bắc Ninh | L39: Từ Sơn | M39: 21.082707 | N39: 105.99795 | O39: DL_HN_GARDEN | P39: TOPS MARKET Garden Mall | Q39: Hà Nội | R39: Nam Từ Liêm | S39: 21.015324 | T39: 105.77784 | U39: Nội thành Hà Nội | V39: Nội thành Hà Nội | W39: 40.4 | X39: 635 | Y39: 16.26 | Z39: 13 | AA39: 5T | AB39: 1.25T | AC39: No | AD39: Yes | AE39: No | AF39: Yes | AG39: Khung giờ nhập kho cố định | AH39: 07:30 | AI39: 10:00 | AJ39: 11:09 | AK39: 13:39 | AL39: 45 | AM39: 40 | AN39: 45 | AO39: 369 | AP39: 920000 | AQ39: 0 | AR39: 120000 | AS39: 150000 | AT39: A - SLA chặt | AU39: CR-NỘIT-04 | AV39: Excel khách hàng | AW39: S3-C38 | AX39: Split/Chuyển tải | AY39: Split Order/Chuyển tải hoặc xin xe nhỏ nhiều chuyến | AZ39: Review | BA39: Vehicle Mismatch | BB39: =AM39+AN39 | BC39: =ROUND(W39/'03_Cost_Constraints'!$B$4*60,0) | BD39: =IF(X39<=500,"5 tạ",IF(X39<=1250,"1.25T",IF(X39<=5000,"5T",IF(X39<=8000,"8T",IF(X39<=15000,"3 chân","4 chân"))))) | BE39: =IF((BB39+BC39)<=AO39,"OK","Risk") | BF39: =IF(AND(AZ39="OK",BE39="OK"),"Ready","Review")
A40: S3 | B40: 2026-06-05 | C40: S3-ORD-039 | D40: Sabeco | E40: VINMART Phạm Ngọc Thạch | F40: ST | G40: LASG | H40: Bia lon Saigon Lager 330ml | I40: PK_HY_MYHAO | J40: Kho/Nhà máy khách hàng Mỹ Hào | K40: Hưng Yên | L40: Mỹ Hào | M40: 20.9329 | N40: 106.065 | O40: DL_HN_PNT | P40: VINMART Phạm Ngọc Thạch | Q40: Hà Nội | R40: Đống Đa | S40: 21.006268 | T40: 105.83193 | U40: Nội thành Hà Nội | V40: Nội thành Hà Nội | W40: 40.4 | X40: 375 | Y40: 0.72 | Z40: 1 | AA40: 5 tạ | AB40: 1.25T | AC40: No | AD40: Yes | AE40: No | AF40: Yes | AG40: Đường đông, cần giao đúng slot | AH40: 08:30 | AI40: 10:00 | AJ40: 10:54 | AK40: 13:24 | AL40: 30 | AM40: 25 | AN40: 20 | AO40: 294 | AP40: 870000 | AQ40: 150000 | AR40: 0 | AS40: 150000 | AT40: A - SLA chặt | AU40: CR-NỘIT-05 | AV40: Hệ thống khách hàng | AW40: S3-C39 | AX40: 5 tạ | AY40: Send to Clustering | AZ40: OK | BA40: Cấm tải/đường nhỏ - đã chọn xe nhỏ | BB40: =AM40+AN40 | BC40: =ROUND(W40/'03_Cost_Constraints'!$B$4*60,0) | BD40: =IF(X40<=500,"5 tạ",IF(X40<=1250,"1.25T",IF(X40<=5000,"5T",IF(X40<=8000,"8T",IF(X40<=15000,"3 chân","4 chân"))))) | BE40: =IF((BB40+BC40)<=AO40,"OK","Risk") | BF40: =IF(AND(AZ40="OK",BE40="OK"),"Ready","Review")
A41: S3 | B41: 2026-06-05 | C41: S3-ORD-040 | D41: Linfox | E41: Siêu thị Ninh Bình | F41: ST | G41: PAT2 | H41: Bia lon 333 | I41: PK_NA_BACVINH | J41: Kho DC Vinh - KCN Bắc Vinh | K41: Nghệ An | L41: Vinh | M41: 18.733 | N41: 105.681 | O41: DL_NB_SIEUTHI | P41: Siêu thị Ninh Bình | Q41: Ninh Bình | R41: Hoa Lư | S41: 20.250614 | T41: 105.97445 | U41: Bắc Trung Bộ | V41: Bắc Trung Bộ | W41: 222 | X41: 7877 | Y41: 13.8 | Z41: 11 | AA41: 8T | AB41: 8T | AC41: No | AD41: No | AE41: Yes | AF41: No | AG41: Xe 8T vào được | AH41: 08:00 | AI41: 09:30 | AJ41: 14:26 | AK41: 16:26 | AL41: 45 | AM41: 40 | AN41: 35 | AO41: 506 | AP41: 11290000 | AQ41: 0 | AR41: 0 | AS41: 80000 | AT41: B - Thường | AU41: CR-BẮCT-01 | AV41: Zalo/Email plan 17:00 | AW41: S3-C40 | AX41: 8T | AY41: Send to Clustering | AZ41: OK | BA41: Empty-run >100km cần tìm chuyến về | BB41: =AM41+AN41 | BC41: =ROUND(W41/'03_Cost_Constraints'!$B$4*60,0) | BD41: =IF(X41<=500,"5 tạ",IF(X41<=1250,"1.25T",IF(X41<=5000,"5T",IF(X41<=8000,"8T",IF(X41<=15000,"3 chân","4 chân"))))) | BE41: =IF((BB41+BC41)<=AO41,"OK","Risk") | BF41: =IF(AND(AZ41="OK",BE41="OK"),"Ready","Review") | BG41: Kế hoạch ngày hôm sau; cần chốt trước 19:00 và gửi tài xế sau duyệt
A42: S3 | B42: 2026-06-05 | C42: S3-ORD-041 | D42: MM Mega Market | E42: Nam Dương | F42: Đại lý | G42: EXPL | H42: Bia lon Saigon Export | I42: PK_HPL_LB | J42: HPL Depot Long Biên - 20 Thạch Bàn | K42: Hà Nội | L42: Long Biên | M42: 21.026155 | N42: 105.91418 | O42: DL_HN_NAMDUONG | P42: Nam Dương | Q42: Hà Nội | R42: Hà Nội | S42: 21.062911 | T42: 105.83235 | U42: Nội thành Hà Nội | V42: Nội thành Hà Nội | W42: 16 | X42: 383 | Y42: 0.83 | Z42: 1 | AA42: 5 tạ | AB42: 1.25T | AC42: No | AD42: Yes | AE42: No | AF42: Yes | AG42: Đường nội đô, có khung giờ cấm tải | AH42: 07:30 | AI42: 10:00 | AJ42: 08:42 | AK42: 11:12 | AL42: 30 | AM42: 25 | AN42: 20 | AO42: 222 | AP42: 820000 | AQ42: 0 | AR42: 0 | AS42: 150000 | AT42: A - SLA chặt | AU42: CR-NỘIT-02 | AV42: Manual nhập điều phối | AW42: S3-C41 | AX42: 5 tạ | AY42: Send to Clustering | AZ42: OK | BA42: Cấm tải/đường nhỏ - đã chọn xe nhỏ | BB42: =AM42+AN42 | BC42: =ROUND(W42/'03_Cost_Constraints'!$B$4*60,0) | BD42: =IF(X42<=500,"5 tạ",IF(X42<=1250,"1.25T",IF(X42<=5000,"5T",IF(X42<=8000,"8T",IF(X42<=15000,"3 chân","4 chân"))))) | BE42: =IF((BB42+BC42)<=AO42,"OK","Risk") | BF42: =IF(AND(AZ42="OK",BE42="OK"),"Ready","Review")
A43: S3 | B43: 2026-06-05 | C43: S3-ORD-042 | D43: Acecook | E43: VINMART Uông Bí | F43: ST | G43: PAT2 | H43: Bia lon 333 | I43: PK_LINFOX_VSIP | J43: Kho Linfox KCN VSIP Bắc Ninh | K43: Bắc Ninh | L43: Từ Sơn | M43: 21.082707 | N43: 105.99795 | O43: DL_QN_UONGBI | P43: VINMART Uông Bí | Q43: Quảng Ninh | R43: Uông Bí | S43: 21.031495 | T43: 106.76688 | U43: Đông Bắc | V43: Đông Bắc | W43: 107.6 | X43: 1735 | Y43: 4.15 | Z43: 3 | AA43: 5T | AB43: 8T | AC43: No | AD43: Yes | AE43: No | AF43: No | AG43: Đường tỉnh, xe 5T/8T vào được | AH43: 07:00 | AI43: 09:30 | AJ43: 10:53 | AK43: 12:23 | AL43: 45 | AM43: 40 | AN43: 35 | AO43: 323 | AP43: 1770000 | AQ43: 0 | AR43: 0 | AS43: 80000 | AT43: C - Có thể thương lượng | AU43: CR-ĐÔNG-03 | AV43: Excel khách hàng | AW43: S3-C41 | AX43: 5T | AY43: Send to Clustering | AZ43: OK | BA43: Empty-run >100km cần tìm chuyến về | BB43: =AM43+AN43 | BC43: =ROUND(W43/'03_Cost_Constraints'!$B$4*60,0) | BD43: =IF(X43<=500,"5 tạ",IF(X43<=1250,"1.25T",IF(X43<=5000,"5T",IF(X43<=8000,"8T",IF(X43<=15000,"3 chân","4 chân"))))) | BE43: =IF((BB43+BC43)<=AO43,"OK","Risk") | BF43: =IF(AND(AZ43="OK",BE43="OK"),"Ready","Review")
A44: S3 | B44: 2026-06-05 | C44: S3-ORD-043 | D44: Linfox | E44: VINMART Royal City | F44: MT | G44: MILK | H44: Sữa hộp carton | I44: PK_HPL_LB | J44: HPL Depot Long Biên - 20 Thạch Bàn | K44: Hà Nội | L44: Long Biên | M44: 21.026155 | N44: 105.91418 | O44: DL_HN_ROYAL | P44: VINMART Royal City | Q44: Hà Nội | R44: Thanh Xuân | S44: 21.003388 | T44: 105.81621 | U44: Nội thành Hà Nội | V44: Nội thành Hà Nội | W44: 18.1 | X44: 1414 | Y44: 2.67 | Z44: 2 | AA44: 5T | AB44: 1.25T | AC44: No | AD44: Yes | AE44: No | AF44: Yes | AG44: Hầm trung tâm thương mại | AH44: 09:00 | AI44: 11:00 | AJ44: 10:31 | AK44: 13:31 | AL44: 45 | AM44: 40 | AN44: 45 | AO44: 271 | AP44: 720000 | AQ44: 0 | AR44: 120000 | AS44: 150000 | AT44: A - SLA chặt | AU44: CR-NỘIT-04 | AV44: Hệ thống khách hàng | AW44: S3-C43 | AX44: Split/Chuyển tải | AY44: Split Order/Chuyển tải hoặc xin xe nhỏ nhiều chuyến | AZ44: Review | BA44: Vehicle Mismatch | BB44: =AM44+AN44 | BC44: =ROUND(W44/'03_Cost_Constraints'!$B$4*60,0) | BD44: =IF(X44<=500,"5 tạ",IF(X44<=1250,"1.25T",IF(X44<=5000,"5T",IF(X44<=8000,"8T",IF(X44<=15000,"3 chân","4 chân"))))) | BE44: =IF((BB44+BC44)<=AO44,"OK","Risk") | BF44: =IF(AND(AZ44="OK",BE44="OK"),"Ready","Review")
A45: S3 | B45: 2026-06-05 | C45: S3-ORD-044 | D45: MM Mega Market | E45: MM Hồng Bàng | F45: MT | G45: LVCA | H45: Bia lon Lạc Việt | I45: PK_HPL_LB | J45: HPL Depot Long Biên - 20 Thạch Bàn | K45: Hà Nội | L45: Long Biên | M45: 21.026155 | N45: 105.91418 | O45: DL_HP_HONGBANG | P45: MM Hồng Bàng | Q45: Hải Phòng | R45: Hồng Bàng | S45: 20.856112 | T45: 106.68224 | U45: Đông Bắc | V45: Đông Bắc | W45: 112.1 | X45: 7725 | Y45: 14.89 | Z45: 12 | AA45: 8T | AB45: 5T | AC45: No | AD45: Yes | AE45: No | AF45: No | AG45: Đường đô thị Hải Phòng, xe 5T vào được | AH45: 08:00 | AI45: 09:30 | AJ45: 12:59 | AK45: 15:29 | AL45: 30 | AM45: 40 | AN45: 45 | AO45: 449 | AP45: 4950000 | AQ45: 0 | AR45: 120000 | AS45: 150000 | AT45: A - SLA chặt | AU45: CR-ĐÔNG-05 | AV45: Zalo/Email plan 17:00 | AW45: S3-C44 | AX45: Split/Chuyển tải | AY45: Split Order/Chuyển tải hoặc xin xe nhỏ nhiều chuyến | AZ45: Review | BA45: Vehicle Mismatch | BB45: =AM45+AN45 | BC45: =ROUND(W45/'03_Cost_Constraints'!$B$4*60,0) | BD45: =IF(X45<=500,"5 tạ",IF(X45<=1250,"1.25T",IF(X45<=5000,"5T",IF(X45<=8000,"8T",IF(X45<=15000,"3 chân","4 chân"))))) | BE45: =IF((BB45+BC45)<=AO45,"OK","Risk") | BF45: =IF(AND(AZ45="OK",BE45="OK"),"Ready","Review") | BG45: Kế hoạch ngày hôm sau; cần chốt trước 19:00 và gửi tài xế sau duyệt
A46: S3 | B46: 2026-06-05 | C46: S3-ORD-045 | D46: Masan | E46: GO! Hà Nam | F46: MT | G46: POSM | H46: POSM trưng bày | I46: PK_NA_BACVINH | J46: Kho DC Vinh - KCN Bắc Vinh | K46: Nghệ An | L46: Vinh | M46: 18.733 | N46: 105.681 | O46: DL_HN_GO_HANAM | P46: GO! Hà Nam | Q46: Ninh Bình | R46: Phủ Lý | S46: 20.541 | T46: 105.913 | U46: Bắc Trung Bộ | V46: Bắc Trung Bộ | W46: 265.4 | X46: 7891 | Y46: 135.51 | Z46: 112 | AA46: Container | AB46: 8T | AC46: No | AD46: No | AE46: Yes | AF46: No | AG46: Xe 5T/8T vào được | AH46: 07:00 | AI46: 09:30 | AJ46: 14:38 | AK46: 16:38 | AL46: 30 | AM46: 120 | AN46: 100 | AO46: 578 | AP46: 13160000 | AQ46: 150000 | AR46: 120000 | AS46: 80000 | AT46: B - Thường | AU46: CR-BẮCT-01 | AV46: Manual nhập điều phối | AW46: S3-C45 | AX46: Split/Chuyển tải | AY46: Split Order/Chuyển tải hoặc xin xe nhỏ nhiều chuyến | AZ46: Review | BA46: Vehicle Mismatch | BB46: =AM46+AN46 | BC46: =ROUND(W46/'03_Cost_Constraints'!$B$4*60,0) | BD46: =IF(X46<=500,"5 tạ",IF(X46<=1250,"1.25T",IF(X46<=5000,"5T",IF(X46<=8000,"8T",IF(X46<=15000,"3 chân","4 chân"))))) | BE46: =IF((BB46+BC46)<=AO46,"OK","Risk") | BF46: =IF(AND(AZ46="OK",BE46="OK"),"Ready","Review")
A47: S3 | B47: 2026-06-05 | C47: S3-ORD-046 | D47: VinCommerce | E47: VINMART Uông Bí | F47: ST | G47: FMCG | H47: Hàng tiêu dùng nhanh hỗn hợp | I47: PK_LINFOX_VSIP | J47: Kho Linfox KCN VSIP Bắc Ninh | K47: Bắc Ninh | L47: Từ Sơn | M47: 21.082707 | N47: 105.99795 | O47: DL_QN_UONGBI | P47: VINMART Uông Bí | Q47: Quảng Ninh | R47: Uông Bí | S47: 21.031495 | T47: 106.76688 | U47: Đông Bắc | V47: Đông Bắc | W47: 106.1 | X47: 6612 | Y47: 26.07 | Z47: 21 | AA47: 8T | AB47: 8T | AC47: No | AD47: Yes | AE47: No | AF47: No | AG47: Đường tỉnh, xe 5T/8T vào được | AH47: 08:00 | AI47: 10:00 | AJ47: 11:21 | AK47: 14:21 | AL47: 45 | AM47: 40 | AN47: 35 | AO47: 381 | AP47: 4090000 | AQ47: 0 | AR47: 0 | AS47: 80000 | AT47: C - Có thể thương lượng | AU47: CR-ĐÔNG-02 | AV47: Excel khách hàng | AW47: S3-C46 | AX47: 8T | AY47: Ưu tiên 3PL/thuê ngoài nếu thiếu xe nội bộ | AZ47: OK | BA47: Capacity Shortage Candidate | BB47: =AM47+AN47 | BC47: =ROUND(W47/'03_Cost_Constraints'!$B$4*60,0) | BD47: =IF(X47<=500,"5 tạ",IF(X47<=1250,"1.25T",IF(X47<=5000,"5T",IF(X47<=8000,"8T",IF(X47<=15000,"3 chân","4 chân"))))) | BE47: =IF((BB47+BC47)<=AO47,"OK","Risk") | BF47: =IF(AND(AZ47="OK",BE47="OK"),"Ready","Review")
A48: S3 | B48: 2026-06-05 | C48: S3-ORD-047 | D48: Sabeco | E48: VINMART Bắc Từ Liêm | F48: ST | G48: POSM | H48: POSM trưng bày | I48: PK_HY_MYHAO | J48: Kho/Nhà máy khách hàng Mỹ Hào | K48: Hưng Yên | L48: Mỹ Hào | M48: 20.9329 | N48: 106.065 | O48: DL_HN_BACTULIEM | P48: VINMART Bắc Từ Liêm | Q48: Hà Nội | R48: Bắc Từ Liêm | S48: 21.052701 | T48: 105.78073 | U48: Nội thành Hà Nội | V48: Nội thành Hà Nội | W48: 50.5 | X48: 535 | Y48: 12.91 | Z48: 10 | AA48: 5T | AB48: 1.25T | AC48: No | AD48: No | AE48: Yes | AF48: Yes | AG48: Nội đô, khung giờ hạn chế xe tải | AH48: 08:00 | AI48: 10:00 | AJ48: 10:26 | AK48: 12:26 | AL48: 30 | AM48: 40 | AN48: 35 | AO48: 266 | AP48: 920000 | AQ48: 0 | AR48: 0 | AS48: 80000 | AT48: B - Thường | AU48: CR-NỘIT-03 | AV48: Hệ thống khách hàng | AW48: S3-C47 | AX48: Split/Chuyển tải | AY48: Split Order/Chuyển tải hoặc xin xe nhỏ nhiều chuyến | AZ48: Review | BA48: Vehicle Mismatch | BB48: =AM48+AN48 | BC48: =ROUND(W48/'03_Cost_Constraints'!$B$4*60,0) | BD48: =IF(X48<=500,"5 tạ",IF(X48<=1250,"1.25T",IF(X48<=5000,"5T",IF(X48<=8000,"8T",IF(X48<=15000,"3 chân","4 chân"))))) | BE48: =IF((BB48+BC48)<=AO48,"OK","Risk") | BF48: =IF(AND(AZ48="OK",BE48="OK"),"Ready","Review")
A49: S3 | B49: 2026-06-05 | C49: S3-ORD-048 | D49: Acecook | E49: TOPS MARKET ParkCity | F49: MT | G49: FMCG | H49: Hàng tiêu dùng nhanh hỗn hợp | I49: PK_HY_MYHAO | J49: Kho/Nhà máy khách hàng Mỹ Hào | K49: Hưng Yên | L49: Mỹ Hào | M49: 20.9329 | N49: 106.065 | O49: DL_HN_PARKCITY | P49: TOPS MARKET ParkCity | Q49: Hà Nội | R49: Hà Đông | S49: 20.965724 | T49: 105.75614 | U49: Nội thành Hà Nội | V49: Nội thành Hà Nội | W49: 49.7 | X49: 1639 | Y49: 8.3 | Z49: 6 | AA49: 5T | AB49: 1.25T | AC49: No | AD49: Yes | AE49: No | AF49: Yes | AG49: Bãi giao giới hạn chiều cao | AH49: 08:30 | AI49: 11:00 | AJ49: 09:55 | AK49: 11:25 | AL49: 45 | AM49: 40 | AN49: 45 | AO49: 175 | AP49: 980000 | AQ49: 0 | AR49: 120000 | AS49: 150000 | AT49: A - SLA chặt | AU49: CR-NỘIT-04 | AV49: Zalo/Email plan 17:00 | AW49: S3-C47 | AX49: Split/Chuyển tải | AY49: Split Order/Chuyển tải hoặc xin xe nhỏ nhiều chuyến | AZ49: Review | BA49: Vehicle Mismatch | BB49: =AM49+AN49 | BC49: =ROUND(W49/'03_Cost_Constraints'!$B$4*60,0) | BD49: =IF(X49<=500,"5 tạ",IF(X49<=1250,"1.25T",IF(X49<=5000,"5T",IF(X49<=8000,"8T",IF(X49<=15000,"3 chân","4 chân"))))) | BE49: =IF((BB49+BC49)<=AO49,"OK","Risk") | BF49: =IF(AND(AZ49="OK",BE49="OK"),"Ready","Review") | BG49: Lead time hẹp, cần cảnh báo hoặc xin nới giờ
A50: S3 | B50: 2026-06-05 | C50: S3-ORD-049 | D50: Sabeco | E50: Siêu thị Thanh Hóa | F50: MT | G50: PAT2 | H50: Bia lon 333 | I50: PK_HPL_LB | J50: HPL Depot Long Biên - 20 Thạch Bàn | K50: Hà Nội | L50: Long Biên | M50: 21.026155 | N50: 105.91418 | O50: DL_TH_SIEUTHI | P50: Siêu thị Thanh Hóa | Q50: Thanh Hóa | R50: Hạc Thành | S50: 19.8076 | T50: 105.77639 | U50: Bắc Trung Bộ | V50: Bắc Trung Bộ | W50: 180.9 | X50: 4395 | Y50: 7.61 | Z50: 6 | AA50: 5T | AB50: 5T | AC50: No | AD50: Yes | AE50: No | AF50: No | AG50: Đường đô thị, xe 5T vào được | AH50: 07:00 | AI50: 08:30 | AJ50: 11:17 | AK50: 13:17 | AL50: 30 | AM50: 40 | AN50: 45 | AO50: 377 | AP50: 5220000 | AQ50: 0 | AR50: 120000 | AS50: 80000 | AT50: C - Có thể thương lượng | AU50: CR-BẮCT-05 | AV50: Manual nhập điều phối | AW50: S3-C49 | AX50: 5T | AY50: Send to Clustering | AZ50: OK | BA50: Empty-run >100km cần tìm chuyến về | BB50: =AM50+AN50 | BC50: =ROUND(W50/'03_Cost_Constraints'!$B$4*60,0) | BD50: =IF(X50<=500,"5 tạ",IF(X50<=1250,"1.25T",IF(X50<=5000,"5T",IF(X50<=8000,"8T",IF(X50<=15000,"3 chân","4 chân"))))) | BE50: =IF((BB50+BC50)<=AO50,"OK","Risk") | BF50: =IF(AND(AZ50="OK",BE50="OK"),"Ready","Review") | BG50: Lead time hẹp, cần cảnh báo hoặc xin nới giờ
A51: S3 | B51: 2026-06-05 | C51: S3-ORD-050 | D51: Bách Hóa Xanh | E51: MM Vinh | F51: MT | G51: LVCA | H51: Bia lon Lạc Việt | I51: PK_TH_QX | J51: Kho DC Thanh Hóa - Quảng Xương | K51: Thanh Hóa | L51: Quảng Xương | M51: 19.731 | N51: 105.815 | O51: DL_NA_MM_VINH | P51: MM Vinh | Q51: Nghệ An | R51: Vinh | S51: 18.68052 | T51: 105.68133 | U51: Bắc Trung Bộ | V51: Bắc Trung Bộ | W51: 156.4 | X51: 10503 | Y51: 29.58 | Z51: 24 | AA51: 3 chân | AB51: 8T | AC51: No | AD51: Yes | AE51: No | AF51: No | AG51: Xe 8T vào được | AH51: 07:00 | AI51: 09:00 | AJ51: 12:27 | AK51: 14:27 | AL51: 45 | AM51: 120 | AN51: 100 | AO51: 447 | AP51: 10300000 | AQ51: 0 | AR51: 120000 | AS51: 80000 | AT51: C - Có thể thương lượng | AU51: CR-BẮCT-01 | AV51: Excel khách hàng | AW51: S3-C50 | AX51: Split/Chuyển tải | AY51: Split Order/Chuyển tải hoặc xin xe nhỏ nhiều chuyến | AZ51: Review | BA51: Vehicle Mismatch | BB51: =AM51+AN51 | BC51: =ROUND(W51/'03_Cost_Constraints'!$B$4*60,0) | BD51: =IF(X51<=500,"5 tạ",IF(X51<=1250,"1.25T",IF(X51<=5000,"5T",IF(X51<=8000,"8T",IF(X51<=15000,"3 chân","4 chân"))))) | BE51: =IF((BB51+BC51)<=AO51,"OK","Risk") | BF51: =IF(AND(AZ51="OK",BE51="OK"),"Ready","Review")
A52: S3 | B52: 2026-06-05 | C52: S3-ORD-051 | D52: Linfox | E52: VINMART Bắc Từ Liêm | F52: ST | G52: LVCA | H52: Bia lon Lạc Việt | I52: PK_HPL_LB | J52: HPL Depot Long Biên - 20 Thạch Bàn | K52: Hà Nội | L52: Long Biên | M52: 21.026155 | N52: 105.91418 | O52: DL_HN_BACTULIEM | P52: VINMART Bắc Từ Liêm | Q52: Hà Nội | R52: Bắc Từ Liêm | S52: 21.052701 | T52: 105.78073 | U52: Nội thành Hà Nội | V52: Nội thành Hà Nội | W52: 26.8 | X52: 1220 | Y52: 2.46 | Z52: 2 | AA52: 1.25T | AB52: 1.25T | AC52: No | AD52: Yes | AE52: No | AF52: Yes | AG52: Nội đô, khung giờ hạn chế xe tải | AH52: 08:30 | AI52: 10:30 | AJ52: 11:30 | AK52: 13:00 | AL52: 45 | AM52: 25 | AN52: 20 | AO52: 270 | AP52: 750000 | AQ52: 150000 | AR52: 0 | AS52: 80000 | AT52: C - Có thể thương lượng | AU52: CR-NỘIT-02 | AV52: Hệ thống khách hàng | AW52: S3-C51 | AX52: 1.25T | AY52: Send to Clustering | AZ52: OK | BA52: Cấm tải/đường nhỏ - đã chọn xe nhỏ | BB52: =AM52+AN52 | BC52: =ROUND(W52/'03_Cost_Constraints'!$B$4*60,0) | BD52: =IF(X52<=500,"5 tạ",IF(X52<=1250,"1.25T",IF(X52<=5000,"5T",IF(X52<=8000,"8T",IF(X52<=15000,"3 chân","4 chân"))))) | BE52: =IF((BB52+BC52)<=AO52,"OK","Risk") | BF52: =IF(AND(AZ52="OK",BE52="OK"),"Ready","Review")
A53: S3 | B53: 2026-06-05 | C53: S3-ORD-052 | D53: VinCommerce | E53: VINMART Times City | F53: MT | G53: PAT2 | H53: Bia lon 333 | I53: PK_HPL_LB | J53: HPL Depot Long Biên - 20 Thạch Bàn | K53: Hà Nội | L53: Long Biên | M53: 21.026155 | N53: 105.91418 | O53: DL_HN_TIMESCITY | P53: VINMART Times City | Q53: Hà Nội | R53: Hai Bà Trưng | S53: 20.994022 | T53: 105.86964 | U53: Nội thành Hà Nội | V53: Nội thành Hà Nội | W53: 12 | X53: 201 | Y53: 0.6 | Z53: 1 | AA53: 5 tạ | AB53: 1.25T | AC53: No | AD53: Yes | AE53: No | AF53: Yes | AG53: Nội khu, xe lớn hạn chế | AH53: 07:00 | AI53: 09:30 | AJ53: 09:05 | AK53: 11:05 | AL53: 45 | AM53: 25 | AN53: 30 | AO53: 245 | AP53: 460000 | AQ53: 0 | AR53: 120000 | AS53: 150000 | AT53: A - SLA chặt | AU53: CR-NỘIT-03 | AV53: Zalo/Email plan 17:00 | AW53: S3-C52 | AX53: 5 tạ | AY53: Send to Clustering | AZ53: OK | BA53: Cấm tải/đường nhỏ - đã chọn xe nhỏ | BB53: =AM53+AN53 | BC53: =ROUND(W53/'03_Cost_Constraints'!$B$4*60,0) | BD53: =IF(X53<=500,"5 tạ",IF(X53<=1250,"1.25T",IF(X53<=5000,"5T",IF(X53<=8000,"8T",IF(X53<=15000,"3 chân","4 chân"))))) | BE53: =IF((BB53+BC53)<=AO53,"OK","Risk") | BF53: =IF(AND(AZ53="OK",BE53="OK"),"Ready","Review") | BG53: Kế hoạch ngày hôm sau; cần chốt trước 19:00 và gửi tài xế sau duyệt
A54: S3 | B54: 2026-06-05 | C54: S3-ORD-053 | D54: Unilever | E54: Siêu thị Thái Bình | F54: ST | G54: NOODLE | H54: Mì gói/Acecook carton | I54: PK_HPL_LB | J54: HPL Depot Long Biên - 20 Thạch Bàn | K54: Hà Nội | L54: Long Biên | M54: 21.026155 | N54: 105.91418 | O54: DL_TB_SIEUTHI | P54: Siêu thị Thái Bình | Q54: Hưng Yên | R54: Thái Bình | S54: 20.446344 | T54: 106.33658 | U54: Đông Nam Hà Nội | V54: Đông Nam Hà Nội | W54: 107.3 | X54: 4852 | Y54: 41.52 | Z54: 34 | AA54: 8T | AB54: 8T | AC54: No | AD54: Yes | AE54: No | AF54: No | AG54: Ngoại thành, xe 5T/8T | AH54: 09:00 | AI54: 10:30 | AJ54: 13:53 | AK54: 16:53 | AL54: 45 | AM54: 40 | AN54: 35 | AO54: 473 | AP54: 3150000 | AQ54: 0 | AR54: 0 | AS54: 80000 | AT54: C - Có thể thương lượng | AU54: CR-ĐÔNG-04 | AV54: Manual nhập điều phối | AW54: S3-C02 | AX54: 8T | AY54: Ưu tiên 3PL/thuê ngoài nếu thiếu xe nội bộ | AZ54: OK | BA54: Capacity Shortage Candidate | BB54: =AM54+AN54 | BC54: =ROUND(W54/'03_Cost_Constraints'!$B$4*60,0) | BD54: =IF(X54<=500,"5 tạ",IF(X54<=1250,"1.25T",IF(X54<=5000,"5T",IF(X54<=8000,"8T",IF(X54<=15000,"3 chân","4 chân"))))) | BE54: =IF((BB54+BC54)<=AO54,"OK","Risk") | BF54: =IF(AND(AZ54="OK",BE54="OK"),"Ready","Review")
A55: S3 | B55: 2026-06-05 | C55: S3-ORD-054 | D55: Masan | E55: Siêu thị Vinh | F55: ST | G55: CHCA | H55: Bia lon Saigon Chill | I55: PK_NA_BACVINH | J55: Kho DC Vinh - KCN Bắc Vinh | K55: Nghệ An | L55: Vinh | M55: 18.733 | N55: 105.681 | O55: DL_NA_SIEUTHI | P55: Siêu thị Vinh | Q55: Nghệ An | R55: Vinh | S55: 18.679586 | T55: 105.6811 | U55: Bắc Trung Bộ | V55: Bắc Trung Bộ | W55: 15.4 | X55: 3694 | Y55: 7.2 | Z55: 6 | AA55: 5T | AB55: 5T | AC55: No | AD55: Yes | AE55: No | AF55: No | AG55: Khung giờ nhập kho chiều | AH55: 07:30 | AI55: 10:00 | AJ55: 09:20 | AK55: 10:50 | AL55: 30 | AM55: 40 | AN55: 35 | AO55: 200 | AP55: 1090000 | AQ55: 0 | AR55: 0 | AS55: 150000 | AT55: A - SLA chặt | AU55: CR-BẮCT-05 | AV55: Excel khách hàng | AW55: S3-C53 | AX55: 5T | AY55: Send to Clustering | AZ55: OK | BA55: OK | BB55: =AM55+AN55 | BC55: =ROUND(W55/'03_Cost_Constraints'!$B$4*60,0) | BD55: =IF(X55<=500,"5 tạ",IF(X55<=1250,"1.25T",IF(X55<=5000,"5T",IF(X55<=8000,"8T",IF(X55<=15000,"3 chân","4 chân"))))) | BE55: =IF((BB55+BC55)<=AO55,"OK","Risk") | BF55: =IF(AND(AZ55="OK",BE55="OK"),"Ready","Review")
A56: S3 | B56: 2026-06-05 | C56: S3-ORD-055 | D56: Sabeco | E56: LOTTE MART Đống Đa | F56: MT | G56: CHCA | H56: Bia lon Saigon Chill | I56: PK_HPL_LB | J56: HPL Depot Long Biên - 20 Thạch Bàn | K56: Hà Nội | L56: Long Biên | M56: 21.026155 | N56: 105.91418 | O56: DL_HN_LOTTE_DD | P56: LOTTE MART Đống Đa | Q56: Hà Nội | R56: Đống Đa | S56: 21.005536 | T56: 105.82394 | U56: Nội thành Hà Nội | V56: Nội thành Hà Nội | W56: 21.5 | X56: 1035 | Y56: 2.2 | Z56: 1 | AA56: 1.25T | AB56: 1.25T | AC56: No | AD56: Yes | AE56: No | AF56: Yes | AG56: Hầm giao nhận, chỉ xe nhỏ/1.25T | AH56: 08:30 | AI56: 10:00 | AJ56: 10:21 | AK56: 12:51 | AL56: 30 | AM56: 25 | AN56: 30 | AO56: 261 | AP56: 550000 | AQ56: 0 | AR56: 120000 | AS56: 150000 | AT56: A - SLA chặt | AU56: CR-NỘIT-01 | AV56: Hệ thống khách hàng | AW56: S3-C04 | AX56: 1.25T | AY56: Send to Clustering | AZ56: OK | BA56: Cấm tải/đường nhỏ - đã chọn xe nhỏ | BB56: =AM56+AN56 | BC56: =ROUND(W56/'03_Cost_Constraints'!$B$4*60,0) | BD56: =IF(X56<=500,"5 tạ",IF(X56<=1250,"1.25T",IF(X56<=5000,"5T",IF(X56<=8000,"8T",IF(X56<=15000,"3 chân","4 chân"))))) | BE56: =IF((BB56+BC56)<=AO56,"OK","Risk") | BF56: =IF(AND(AZ56="OK",BE56="OK"),"Ready","Review")
A57: S3 | B57: 2026-06-05 | C57: S3-ORD-056 | D57: Sabeco | E57: VINMART Bắc Từ Liêm | F57: ST | G57: POSM | H57: POSM trưng bày | I57: PK_HY_MYHAO | J57: Kho/Nhà máy khách hàng Mỹ Hào | K57: Hưng Yên | L57: Mỹ Hào | M57: 20.9329 | N57: 106.065 | O57: DL_HN_BACTULIEM | P57: VINMART Bắc Từ Liêm | Q57: Hà Nội | R57: Bắc Từ Liêm | S57: 21.052701 | T57: 105.78073 | U57: Nội thành Hà Nội | V57: Nội thành Hà Nội | W57: 50.9 | X57: 1044 | Y57: 20.32 | Z57: 16 | AA57: 5T | AB57: 1.25T | AC57: No | AD57: Yes | AE57: No | AF57: Yes | AG57: Nội đô, khung giờ hạn chế xe tải | AH57: 07:30 | AI57: 09:30 | AJ57: 11:27 | AK57: 13:57 | AL57: 30 | AM57: 40 | AN57: 35 | AO57: 387 | AP57: 690000 | AQ57: 0 | AR57: 0 | AS57: 150000 | AT57: A - SLA chặt | AU57: CR-NỘIT-02 | AV57: Zalo/Email plan 17:00 | AW57: S3-C05 | AX57: Split/Chuyển tải | AY57: Split Order/Chuyển tải hoặc xin xe nhỏ nhiều chuyến | AZ57: Review | BA57: Vehicle Mismatch | BB57: =AM57+AN57 | BC57: =ROUND(W57/'03_Cost_Constraints'!$B$4*60,0) | BD57: =IF(X57<=500,"5 tạ",IF(X57<=1250,"1.25T",IF(X57<=5000,"5T",IF(X57<=8000,"8T",IF(X57<=15000,"3 chân","4 chân"))))) | BE57: =IF((BB57+BC57)<=AO57,"OK","Risk") | BF57: =IF(AND(AZ57="OK",BE57="OK"),"Ready","Review") | BG57: Kế hoạch ngày hôm sau; cần chốt trước 19:00 và gửi tài xế sau duyệt
A58: S3 | B58: 2026-06-05 | C58: S3-ORD-057 | D58: Sabeco | E58: TOPS MARKET ParkCity | F58: MT | G58: SP33 | H58: Bia lon Saigon Special | I58: PK_HY_MYHAO | J58: Kho/Nhà máy khách hàng Mỹ Hào | K58: Hưng Yên | L58: Mỹ Hào | M58: 20.9329 | N58: 106.065 | O58: DL_HN_PARKCITY | P58: TOPS MARKET ParkCity | Q58: Hà Nội | R58: Hà Đông | S58: 20.965724 | T58: 105.75614 | U58: Nội thành Hà Nội | V58: Nội thành Hà Nội | W58: 52 | X58: 351 | Y58: 0.9 | Z58: 1 | AA58: 5 tạ | AB58: 1.25T | AC58: No | AD58: Yes | AE58: No | AF58: Yes | AG58: Bãi giao giới hạn chiều cao | AH58: 07:00 | AI58: 08:30 | AJ58: 09:44 | AK58: 11:44 | AL58: 30 | AM58: 25 | AN58: 30 | AO58: 284 | AP58: 880000 | AQ58: 150000 | AR58: 120000 | AS58: 150000 | AT58: A - SLA chặt | AU58: CR-NỘIT-03 | AV58: Manual nhập điều phối | AW58: S3-C06 | AX58: 5 tạ | AY58: Ưu tiên 3PL/thuê ngoài nếu thiếu xe nội bộ | AZ58: OK | BA58: Capacity Shortage Candidate | BB58: =AM58+AN58 | BC58: =ROUND(W58/'03_Cost_Constraints'!$B$4*60,0) | BD58: =IF(X58<=500,"5 tạ",IF(X58<=1250,"1.25T",IF(X58<=5000,"5T",IF(X58<=8000,"8T",IF(X58<=15000,"3 chân","4 chân"))))) | BE58: =IF((BB58+BC58)<=AO58,"OK","Risk") | BF58: =IF(AND(AZ58="OK",BE58="OK"),"Ready","Review")
A59: S3 | B59: 2026-06-05 | C59: S3-ORD-058 | D59: Acecook | E59: MM Hạ Long | F59: MT | G59: FMCG | H59: Hàng tiêu dùng nhanh hỗn hợp | I59: PK_LINFOX_VSIP | J59: Kho Linfox KCN VSIP Bắc Ninh | K59: Bắc Ninh | L59: Từ Sơn | M59: 21.082707 | N59: 105.99795 | O59: DL_QN_HALONG | P59: MM Hạ Long | Q59: Quảng Ninh | R59: Hạ Long | S59: 20.95129 | T59: 107.08008 | U59: Đông Bắc | V59: Đông Bắc | W59: 152 | X59: 7922 | Y59: 30.2 | Z59: 25 | AA59: 8T | AB59: 8T | AC59: No | AD59: Yes | AE59: No | AF59: No | AG59: Đường ven biển, xe 8T vào được | AH59: 07:30 | AI59: 09:00 | AJ59: 12:32 | AK59: 15:02 | AL59: 45 | AM59: 40 | AN59: 45 | AO59: 452 | AP59: 8020000 | AQ59: 0 | AR59: 120000 | AS59: 80000 | AT59: B - Thường | AU59: CR-ĐÔNG-04 | AV59: Excel khách hàng | AW59: S3-C07 | AX59: 8T | AY59: Send to Clustering | AZ59: OK | BA59: Empty-run >100km cần tìm chuyến về | BB59: =AM59+AN59 | BC59: =ROUND(W59/'03_Cost_Constraints'!$B$4*60,0) | BD59: =IF(X59<=500,"5 tạ",IF(X59<=1250,"1.25T",IF(X59<=5000,"5T",IF(X59<=8000,"8T",IF(X59<=15000,"3 chân","4 chân"))))) | BE59: =IF((BB59+BC59)<=AO59,"OK","Risk") | BF59: =IF(AND(AZ59="OK",BE59="OK"),"Ready","Review")
A60: S3 | B60: 2026-06-05 | C60: S3-ORD-059 | D60: Bách Hóa Xanh | E60: BHX Thanh Hóa - Kho DC Quảng Xương | F60: DC | G60: PAT2 | H60: Bia lon 333 | I60: PK_HPL_LB | J60: HPL Depot Long Biên - 20 Thạch Bàn | K60: Hà Nội | L60: Long Biên | M60: 21.026155 | N60: 105.91418 | O60: DL_TH_BHX_QX | P60: BHX Thanh Hóa - Kho DC Quảng Xương | Q60: Thanh Hóa | R60: Quảng Xương | S60: 19.731 | T60: 105.815 | U60: Bắc Trung Bộ | V60: Bắc Trung Bộ | W60: 192.2 | X60: 11995 | Y60: 29.05 | Z60: 24 | AA60: 3 chân | AB60: 3 chân | AC60: No | AD60: No | AE60: Yes | AF60: No | AG60: DC có thể nhận xe 8T/3 chân | AH60: 07:30 | AI60: 10:00 | AJ60: 14:10 | AK60: 15:40 | AL60: 45 | AM60: 120 | AN60: 90 | AO60: 490 | AP60: 14630000 | AQ60: 0 | AR60: 0 | AS60: 80000 | AT60: C - Có thể thương lượng | AU60: CR-BẮCT-05 | AV60: Hệ thống khách hàng | AW60: S3-C08 | AX60: 3 chân | AY60: Ưu tiên 3PL/thuê ngoài nếu thiếu xe nội bộ | AZ60: OK | BA60: Capacity Shortage Candidate | BB60: =AM60+AN60 | BC60: =ROUND(W60/'03_Cost_Constraints'!$B$4*60,0) | BD60: =IF(X60<=500,"5 tạ",IF(X60<=1250,"1.25T",IF(X60<=5000,"5T",IF(X60<=8000,"8T",IF(X60<=15000,"3 chân","4 chân"))))) | BE60: =IF((BB60+BC60)<=AO60,"OK","Risk") | BF60: =IF(AND(AZ60="OK",BE60="OK"),"Ready","Review")
A61: S3 | B61: 2026-06-05 | C61: S3-ORD-060 | D61: Bách Hóa Xanh | E61: VINMART Bắc Từ Liêm | F61: ST | G61: LASG | H61: Bia lon Saigon Lager 330ml | I61: PK_HY_MYHAO | J61: Kho/Nhà máy khách hàng Mỹ Hào | K61: Hưng Yên | L61: Mỹ Hào | M61: 20.9329 | N61: 106.065 | O61: DL_HN_BACTULIEM | P61: VINMART Bắc Từ Liêm | Q61: Hà Nội | R61: Bắc Từ Liêm | S61: 21.052701 | T61: 105.78073 | U61: Nội thành Hà Nội | V61: Nội thành Hà Nội | W61: 49.5 | X61: 2177 | Y61: 5.48 | Z61: 4 | AA61: 5T | AB61: 1.25T | AC61: No | AD61: Yes | AE61: No | AF61: Yes | AG61: Nội đô, khung giờ hạn chế xe tải | AH61: 08:30 | AI61: 10:00 | AJ61: 11:24 | AK61: 12:54 | AL61: 45 | AM61: 40 | AN61: 35 | AO61: 264 | AP61: 1300000 | AQ61: 150000 | AR61: 0 | AS61: 80000 | AT61: C - Có thể thương lượng | AU61: CR-NỘIT-01 | AV61: Zalo/Email plan 17:00 | AW61: S3-C09 | AX61: Split/Chuyển tải | AY61: Split Order/Chuyển tải hoặc xin xe nhỏ nhiều chuyến | AZ61: Review | BA61: Vehicle Mismatch | BB61: =AM61+AN61 | BC61: =ROUND(W61/'03_Cost_Constraints'!$B$4*60,0) | BD61: =IF(X61<=500,"5 tạ",IF(X61<=1250,"1.25T",IF(X61<=5000,"5T",IF(X61<=8000,"8T",IF(X61<=15000,"3 chân","4 chân"))))) | BE61: =IF((BB61+BC61)<=AO61,"OK","Risk") | BF61: =IF(AND(AZ61="OK",BE61="OK"),"Ready","Review") | BG61: Kế hoạch ngày hôm sau; cần chốt trước 19:00 và gửi tài xế sau duyệt

Sheet 08_Algorithm_Nodes
A1: Scenario_ID | B1: Order_ID | C1: Node_ID | D1: Node_Type | E1: Pair_Node_ID | F1: Precedence_Group | G1: Location_ID | H1: Location_Name | I1: Province | J1: District | K1: Latitude | L1: Longitude | M1: Time_Window_Start_Min | N1: Time_Window_End_Min | O1: Time_Window_Start_Text | P1: Time_Window_End_Text | Q1: Service_Time_Min | R1: Demand_Weight_kg | S1: Demand_Volume_m3 | T1: Compatible_Min_Vehicle | U1: Max_Vehicle_Allowed | V1: Corridor | W1: Contract_Route_ID | X1: Priority | Y1: Revenue_If_Served_VND | Z1: Late_Penalty_VND_per_30m | AA1: Hard_Time_Window | AB1: Planning_Date | AC1: Ready_Flag | AD1: Notes
A2: S1 | B2: S1-ORD-001 | C2: S1-ORD-001-P | D2: Pickup | E2: S1-ORD-001-D | F2: S1-ORD-001 | G2: PK_HY_MYHAO | H2: Kho/Nhà máy khách hàng Mỹ Hào | I2: Hưng Yên | J2: Mỹ Hào | K2: 20.9329 | L2: 106.065 | M2: 480 | N2: 630 | O2: 08:00 | P2: 10:30 | Q2: 25 | R2: 385 | S2: 0.93 | T2: 5 tạ | U2: 1.25T | V2: Nội thành Hà Nội | W2: CR-NỘIT-02 | X2: A - SLA chặt | Y2: 670000 | Z2: 150000 | AA2: Yes | AB2: 2026-06-05 | AC2: Ready | AD2: Pickup must happen before paired delivery
A3: S1 | B3: S1-ORD-001 | C3: S1-ORD-001-D | D3: Delivery | E3: S1-ORD-001-P | F3: S1-ORD-001 | G3: DL_HN_VOTHISAU | H3: VINMART Võ Thị Sáu | I3: Hà Nội | J3: Hai Bà Trưng | K3: 21.00441 | L3: 105.85515 | M3: 655 | N3: 745 | O3: 10:55 | P3: 12:25 | Q3: 20 | R3: -385 | S3: -0.93 | T3: 5 tạ | U3: 1.25T | V3: Nội thành Hà Nội | W3: CR-NỘIT-02 | X3: A - SLA chặt | Y3: 0 | Z3: 150000 | AA3: Yes | AB3: 2026-06-05 | AC3: Ready | AD3: Delivery paired with same order and same vehicle unless transshipment enabled
A4: S1 | B4: S1-ORD-002 | C4: S1-ORD-002-P | D4: Pickup | E4: S1-ORD-002-D | F4: S1-ORD-002 | G4: PK_HY_MYHAO | H4: Kho/Nhà máy khách hàng Mỹ Hào | I4: Hưng Yên | J4: Mỹ Hào | K4: 20.9329 | L4: 106.065 | M4: 510 | N4: 600 | O4: 08:30 | P4: 10:00 | Q4: 25 | R4: 307 | S4: 0.88 | T4: 5 tạ | U4: 1.25T | V4: Nội thành Hà Nội | W4: CR-NỘIT-03 | X4: B - Thường | Y4: 860000 | Z4: 80000 | AA4: Yes | AB4: 2026-06-05 | AC4: Ready | AD4: Pickup must happen before paired delivery
A5: S1 | B5: S1-ORD-002 | C5: S1-ORD-002-D | D5: Delivery | E5: S1-ORD-002-P | F5: S1-ORD-002 | G5: DL_HN_ROYAL | H5: VINMART Royal City | I5: Hà Nội | J5: Thanh Xuân | K5: 21.003388 | L5: 105.81621 | M5: 718 | N5: 838 | O5: 11:58 | P5: 13:58 | Q5: 30 | R5: -307 | S5: -0.88 | T5: 5 tạ | U5: 1.25T | V5: Nội thành Hà Nội | W5: CR-NỘIT-03 | X5: B - Thường | Y5: 0 | Z5: 80000 | AA5: Yes | AB5: 2026-06-05 | AC5: Ready | AD5: Delivery paired with same order and same vehicle unless transshipment enabled
A6: S1 | B6: S1-ORD-003 | C6: S1-ORD-003-P | D6: Pickup | E6: S1-ORD-003-D | F6: S1-ORD-003 | G6: PK_LINFOX_VSIP | H6: Kho Linfox KCN VSIP Bắc Ninh | I6: Bắc Ninh | J6: Từ Sơn | K6: 21.082707 | L6: 105.99795 | M6: 450 | N6: 540 | O6: 07:30 | P6: 09:00 | Q6: 40 | R6: 7751 | S6: 16.16 | T6: 8T | U6: 8T | V6: Đông Bắc | W6: CR-ĐÔNG-04 | X6: C - Có thể thương lượng | Y6: 1810000 | Z6: 80000 | AA6: Yes | AB6: 2026-06-05 | AC6: Ready | AD6: Pickup must happen before paired delivery
A7: S1 | B7: S1-ORD-003 | C7: S1-ORD-003-D | D7: Delivery | E7: S1-ORD-003-P | F7: S1-ORD-003 | G7: DL_BN_QUEVO_01 | H7: VINMART Quế Võ | I7: Bắc Ninh | J7: Quế Võ | K7: 21.170139 | L7: 106.1024 | M7: 603 | N7: 723 | O7: 10:03 | P7: 12:03 | Q7: 35 | R7: -7751 | S7: -16.16 | T7: 8T | U7: 8T | V7: Đông Bắc | W7: CR-ĐÔNG-04 | X7: C - Có thể thương lượng | Y7: 0 | Z7: 80000 | AA7: Yes | AB7: 2026-06-05 | AC7: Ready | AD7: Delivery paired with same order and same vehicle unless transshipment enabled
A8: S1 | B8: S1-ORD-004 | C8: S1-ORD-004-P | D8: Pickup | E8: S1-ORD-004-D | F8: S1-ORD-004 | G8: PK_HY_MYHAO | H8: Kho/Nhà máy khách hàng Mỹ Hào | I8: Hưng Yên | J8: Mỹ Hào | K8: 20.9329 | L8: 106.065 | M8: 420 | N8: 540 | O8: 07:00 | P8: 09:00 | Q8: 25 | R8: 226 | S8: 0.6 | T8: 5 tạ | U8: 1.25T | V8: Nội thành Hà Nội | W8: CR-NỘIT-05 | X8: C - Có thể thương lượng | Y8: 850000 | Z8: 80000 | AA8: Yes | AB8: 2026-06-05 | AC8: Ready | AD8: Pickup must happen before paired delivery
A9: S1 | B9: S1-ORD-004 | C9: S1-ORD-004-D | D9: Delivery | E9: S1-ORD-004-P | F9: S1-ORD-004 | G9: DL_HN_BACTULIEM | H9: VINMART Bắc Từ Liêm | I9: Hà Nội | J9: Bắc Từ Liêm | K9: 21.052701 | L9: 105.78073 | M9: 557 | N9: 737 | O9: 09:17 | P9: 12:17 | Q9: 20 | R9: -226 | S9: -0.6 | T9: 5 tạ | U9: 1.25T | V9: Nội thành Hà Nội | W9: CR-NỘIT-05 | X9: C - Có thể thương lượng | Y9: 0 | Z9: 80000 | AA9: Yes | AB9: 2026-06-05 | AC9: Ready | AD9: Delivery paired with same order and same vehicle unless transshipment enabled
A10: S1 | B10: S1-ORD-005 | C10: S1-ORD-005-P | D10: Pickup | E10: S1-ORD-005-D | F10: S1-ORD-005 | G10: PK_HPL_LB | H10: HPL Depot Long Biên - 20 Thạch Bàn | I10: Hà Nội | J10: Long Biên | K10: 21.026155 | L10: 105.91418 | M10: 420 | N10: 570 | O10: 07:00 | P10: 09:30 | Q10: 25 | R10: 661 | S10: 1.58 | T10: 1.25T | U10: 1.25T | V10: Nội thành Hà Nội | W10: CR-NỘIT-01 | X10: B - Thường | Y10: 490000 | Z10: 80000 | AA10: Yes | AB10: 2026-06-05 | AC10: Ready | AD10: Pickup must happen before paired delivery
A11: S1 | B11: S1-ORD-005 | C11: S1-ORD-005-D | D11: Delivery | E11: S1-ORD-005-P | F11: S1-ORD-005 | G11: DL_HN_VOTHISAU | H11: VINMART Võ Thị Sáu | I11: Hà Nội | J11: Hai Bà Trưng | K11: 21.00441 | L11: 105.85515 | M11: 552 | N11: 672 | O11: 09:12 | P11: 11:12 | Q11: 20 | R11: -661 | S11: -1.58 | T11: 1.25T | U11: 1.25T | V11: Nội thành Hà Nội | W11: CR-NỘIT-01 | X11: B - Thường | Y11: 0 | Z11: 80000 | AA11: Yes | AB11: 2026-06-05 | AC11: Ready | AD11: Delivery paired with same order and same vehicle unless transshipment enabled
A12: S1 | B12: S1-ORD-006 | C12: S1-ORD-006-P | D12: Pickup | E12: S1-ORD-006-D | F12: S1-ORD-006 | G12: PK_HPL_LB | H12: HPL Depot Long Biên - 20 Thạch Bàn | I12: Hà Nội | J12: Long Biên | K12: 21.026155 | L12: 105.91418 | M12: 420 | N12: 570 | O12: 07:00 | P12: 09:30 | Q12: 120 | R12: 7814 | S12: 172.96 | T12: Container | U12: 8T | V12: Đông Bắc | W12: CR-ĐÔNG-02 | X12: C - Có thể thương lượng | Y12: 3320000 | Z12: 80000 | AA12: Yes | AB12: 2026-06-05 | AC12: Review | AD12: Pickup must happen before paired delivery
A13: S1 | B13: S1-ORD-006 | C13: S1-ORD-006-D | D13: Delivery | E13: S1-ORD-006-P | F13: S1-ORD-006 | G13: DL_HD_SIEUTHI | H13: Siêu thị Hải Dương | I13: Hải Phòng | J13: Hải Dương | K13: 20.937341 | L13: 106.31455 | M13: 732 | N13: 852 | O13: 12:12 | P13: 14:12 | Q13: 90 | R13: -7814 | S13: -172.96 | T13: Container | U13: 8T | V13: Đông Bắc | W13: CR-ĐÔNG-02 | X13: C - Có thể thương lượng | Y13: 0 | Z13: 80000 | AA13: Yes | AB13: 2026-06-05 | AC13: Review | AD13: Delivery paired with same order and same vehicle unless transshipment enabled
... A269: S3 | B269: S3-ORD-060 | C269: S3-ORD-060-D | D269: Delivery | E269: S3-ORD-060-P | F269: S3-ORD-060 | G269: DL_HN_BACTULIEM | H269: VINMART Bắc Từ Liêm | I269: Hà Nội | J269: Bắc Từ Liêm | K269: 21.052701 | L269: 105.78073 | M269: 684 | N269: 774 | O269: 11:24 | P269: 12:54 | Q269: 35 | R269: -2177 | S269: -5.48 | T269: 5T | U269: 1.25T | V269: Nội thành Hà Nội | W269: CR-NỘIT-01 | X269: C - Có thể thương lượng | Y269: 0 | Z269: 80000 | AA269: Yes | AB269: 2026-06-05 | AC269: Review | AD269: Delivery paired with same order and same vehicle unless transshipment enabled

Sheet 09_Scenario_Solutions
A1: Scenario_ID | B1: Case | C1: Orders | D1: Internal_Vehicles_Available | E1: Estimated_Route/Vehicle_Need | F1: Capacity_Gap | G1: Planning_Meaning | H1: Proposed_Operational_Response | I1: Algorithm_Settings | J1: Presentation_Note
A2: S1 | B2: Năng lực công ty còn thừa so với order khách hàng | C2: 30 | D2: 40 | E2: 28 | F2: 12 | G2: Có xe dự phòng, không cần thuê ngoài | H2: Ưu tiên phương án giảm km, giảm chạy rỗng, giữ 3-5 xe dự phòng cho phát sinh; chọn xe nhỏ cho nội đô và xe 5T/8T cho tuyến dài | I2: Balanced Mode + Empty-run Reduction | J2: Dùng để chứng minh hệ thống không chỉ tìm đường mà còn tối ưu năng lực dư
A3: S2 | B3: Năng lực công ty đáp ứng đủ so với order khách hàng | C3: 44 | D3: 40 | E3: 40 | F3: 0 | G3: Không còn nhiều xe dự phòng, cần khóa kế hoạch chặt | H3: Ưu tiên SLA và feasibility; giữ 1 danh sách xe backup/3PL standby nhưng chưa kích hoạt; dispatcher cần duyệt sớm và gửi tài xế trước 19:00 | I3: On-time Priority + Manual-assisted Mode | J3: Phù hợp case lập kế hoạch ngày hôm sau khi order vừa khớp năng lực
A4: S3 | B4: Năng lực công ty thiếu so với order khách hàng | C4: 60 | D4: 40 | E4: 52 | F4: -12 | G4: Thiếu xe nội bộ, phải thuê ngoài/chuyển tải/đàm phán giờ | H4: Kích hoạt 3PL/thuê ngoài cho tuyến dài và cụm low-margin; tách đơn quá tải nội đô; xin khách nới time window với đơn ưu tiên C; ưu tiên đơn SLA A và tuyến có lợi nhuận tốt | I4: Profit Maximization + On-time Priority + Split/Transshipment Enabled | J4: Dùng để trình bày năng lực xử lý thiếu xe và trade-off lead time/profit

Sheet 10_Solver_Settings
A1: Category | B1: Notation/Field | C1: Description | D1: Sheet/Column Used | E1: Required for
A2: Set | B2: K | C2: Tập xe/vehicle set | D2: 04_Fleet_40.Vehicle_ID | E2: VRPTW/PDPTW
A3: Set | B3: R | C3: Tập yêu cầu vận tải/order set | D3: S1/S2/S3 Orders.Order_ID | E3: Clustering + VRPTW
A4: Set | B4: N | C4: Tập node gồm depot, pickup và delivery | D4: 08_Algorithm_Nodes.Node_ID | E4: VRPTW/PDPTW
A5: Parameter | B5: cap_k | C5: Sức chứa/tải trọng của xe k | D5: 04_Fleet_40.Max_Weight_kg / Max_Volume_m3 | E5: Vehicle capacity
A6: Parameter | B6: cost_ijk | C6: Chi phí xe k đi từ i đến j | D6: 03_Cost_Constraints + Fuel_L_per_km + distance matrix from lat/lon | E6: Objective function
A7: Parameter | B7: time_ijk | C7: Thời gian xe k đi từ i đến j | D7: Lat/Lon + Avg_Speed + road/time rules | E7: Time windows
A8: Parameter | B8: [a_i,b_i] | C8: Khung giờ pickup/drop | D8: 08_Algorithm_Nodes.Time_Window_Start/End_Min | E8: VRPTW feasibility
A9: Parameter | B9: service_i | C9: Thời gian phục vụ/bốc/dỡ tại node | D9: 08_Algorithm_Nodes.Service_Time_Min | E9: Route sequencing
A10: Parameter | B10: q_i/v_i | C10: Nhu cầu tải trọng/thể tích; pickup dương, delivery âm | D10: 08_Algorithm_Nodes.Demand_Weight_kg / Demand_Volume_m3 | E10: Load flow
A11: Decision | B11: x_ijk | C11: Xe k đi trực tiếp từ node i đến node j | D11: Solver output | E11: Route planning
A12: Decision | B12: t_i | C12: Thời điểm đến node i | D12: Solver output | E12: ETA/ETD
... A16: Objective | B16: Max Expected Profit | C16: Revenue + extra-stop/waiting fee - fuel/toll/driver/fixed/empty-run/late penalty | D16: Orders + Fleet + Cost_Constraints | E16: Optimization
